Workbook

Sheet mybt
A1: id | B1: year | C1: company | D1: capital | E1: office | F1: yearg | G1: situated | H1: mine | I1: loc | J1: text | K1: lastname | L1: firstname | M1: middlename | N1: prof | O1: company | P1: capital | Q1: office | R1: yearg | S1: situated | T1: mine | U1: loc | V1: lastname | W1: firstname | X1: middlename | Y1: prof | Z1: cerco | AA1: totco | AB1: extracted/actual | AC1: positive | AD1: negative
A2: myb1734 | B2: 1887 | C2: AUSTRIAN OZOKERIT COMPANY | I2: kensington | J2: C. J. Elers, 6 Kensington Court | Z2: 0 | AA2: =LEN(C2)+LEN(D2)+LEN(E2)+LEN(F2)+LEN(G2)+LEN(H2)+LEN(I2)+LEN(K2)+LEN(L2)+LEN(M2)+LEN(N2) -> 35 | AB2: positive | AC2: t | AD2: f
A3: myb6799 | B3: 1887 | C3: COMPANY LIMITED | I3: mysore | J3: over by the Mysore- Wynaad Consolidated Gold Mining Company, Limited. | O3: b | Z3: 23 | AA3: =LEN(C3)+LEN(D3)+LEN(E3)+LEN(F3)+LEN(G3)+LEN(H3)+LEN(I3)+LEN(K3)+LEN(L3)+LEN(M3)+LEN(N3) -> 21 | AB3: negative | AC3: f | AD3: t
A4: myb13850 | B4: 1887 | C4: MOUNT TAOAHONG EXPLOBATION | I4: london | J4: The dividend for 1685 was 5 per cent., and for 1886, 6 per cent. The | Z4: {=+Z4:AZ4:Z397} -> 0 | AA4: =LEN(C4)+LEN(D4)+LEN(E4)+LEN(F4)+LEN(G4)+LEN(H4)+LEN(I4)+LEN(K4)+LEN(L4)+LEN(M4)+LEN(N4) -> 32
A5: myb14328 | B5: 1887 | C5: MORFA DU MINING COMPANY | I5: london | J5: limited. | AA5: =LEN(C5)+LEN(D5)+LEN(E5)+LEN(F5)+LEN(G5)+LEN(H5)+LEN(I5)+LEN(K5)+LEN(L5)+LEN(M5)+LEN(N5) -> 29 | AB5: code
A6: myb17600 | B6: 1887 | C6: OPAL MINES OF QUEENSLAND LIMITED | I6: queensland | J6: shares, of which 15,000 were taken by the vendor in addition to £27,500 in cash | AA6: =LEN(C6)+LEN(D6)+LEN(E6)+LEN(F6)+LEN(G6)+LEN(H6)+LEN(I6)+LEN(K6)+LEN(L6)+LEN(M6)+LEN(N6) -> 42 | AB6: extracted/actual | AC6: positive | AD6: negative
A7: myb19077 | B7: 1887 | C7: POLYEAR TIN MINING COMPANY LIMITED | D7: 48520.136 | I7: cornwall | J7: The capital is £10,000 in shares of £1 each. | AA7: =LEN(C7)+LEN(D7)+LEN(E7)+LEN(F7)+LEN(G7)+LEN(H7)+LEN(I7)+LEN(K7)+LEN(L7)+LEN(M7)+LEN(N7) -> 53 | AB7: positive | AD7: f
A8: myb19678 | B8: 1887 | C8: RAVENSCLIFF MINING COMPANY LIMITED | I8: new zealand | J8: necessary capital, to comply with the terms of the Act in this respect within a reasonable | AA8: =LEN(C8)+LEN(D8)+LEN(E8)+LEN(F8)+LEN(G8)+LEN(H8)+LEN(I8)+LEN(K8)+LEN(L8)+LEN(M8)+LEN(N8) -> 45 | AB8: negative | AC8: f
A9: myb20945 | B9: 1887 | C9: COMPANY LIMITED | E9: broad street london | I9: winchester | J9: 1, Winchester House, Old Broad Street, E.C. | O9: b | AA9: =LEN(C9)+LEN(D9)+LEN(E9)+LEN(F9)+LEN(G9)+LEN(H9)+LEN(I9)+LEN(K9)+LEN(L9)+LEN(M9)+LEN(N9) -> 44
A10: myb21637 | B10: 1887 | C10: PLUMAS EUREKA MINE | I10: plumas | J10: Seventy-Six Mine, 6,003 tons; Seventy-Six Ravine Mine, 8,160 tons; Elizal eth Mine, 20; | AA10: =LEN(C10)+LEN(D10)+LEN(E10)+LEN(F10)+LEN(G10)+LEN(H10)+LEN(I10)+LEN(K10)+LEN(L10)+LEN(M10)+LEN(N10) -> 24 | AB10: types of mistakes on true positives
A11: myb23491 | B11: 1887 | C11: TINDENE MINING COMPANY LIMITED | I11: aldersgate street merchant | J11: .1. M Call, Whipps Cross, Walthamstow, provision merchant 800 | AA11: =LEN(C11)+LEN(D11)+LEN(E11)+LEN(F11)+LEN(G11)+LEN(H11)+LEN(I11)+LEN(K11)+LEN(L11)+LEN(M11)+LEN(N11) -> 56 | AB11: no mistake
A12: myb27537 | B12: 1888 | C12: BELL STONE SLATE QUARRIES COMPANY | I12: broadway | J12: 1886 £4,329. | AA12: =LEN(C12)+LEN(D12)+LEN(E12)+LEN(F12)+LEN(G12)+LEN(H12)+LEN(I12)+LEN(K12)+LEN(L12)+LEN(M12)+LEN(N12) -> 41 | AB12: source to text (OCR misreads the text, extra spaces, wrong characters, etc.) | AC12: a
A13: myb31676 | B13: 1888 | C13: DAN O CONNELL GOLD MINING COMPANY | I13: london | J13: comprising togother an area of about 50 acres, both held under the usual | AA13: =LEN(C13)+LEN(D13)+LEN(E13)+LEN(F13)+LEN(G13)+LEN(H13)+LEN(I13)+LEN(K13)+LEN(L13)+LEN(M13)+LEN(N13) -> 39 | AB13: text to classification | AC13: b
A14: myb32402 | B14: 1888 | C14: DISRAELI MINE SYNDICATE COMPANY LIMITED | F14: 1885 | I14: broad street b | J14: This company was registered on the 10th February, 1885, to acquire and work a | AA14: =LEN(C14)+LEN(D14)+LEN(E14)+LEN(F14)+LEN(G14)+LEN(H14)+LEN(I14)+LEN(K14)+LEN(L14)+LEN(M14)+LEN(N14) -> 57
A15: myb37847 | B15: 1888 | C15: LINARES LEAD MINING COMPANY LIMITED | I15: linares | J15: 1875 . 15s. Od. | AA15: =LEN(C15)+LEN(D15)+LEN(E15)+LEN(F15)+LEN(G15)+LEN(H15)+LEN(I15)+LEN(K15)+LEN(L15)+LEN(M15)+LEN(N15) -> 42 | AB15: Progress indicator
A16: myb42349 | B16: 1888 | C16: DIRECTORS | I16: new zealand | J16: experienced, which have much delayed progress, but your directors are pleased to report that | O16: b | AA16: =LEN(C16)+LEN(D16)+LEN(E16)+LEN(F16)+LEN(G16)+LEN(H16)+LEN(I16)+LEN(K16)+LEN(L16)+LEN(M16)+LEN(N16) -> 20
A17: myb43124 | B17: 1888 | C17: NORTH KENNEDY COMPANY LIMITED | I17: wales | J17: extraction. The directors hero particularly refer to the discovery made iu the Fort una level ; which, according to the last advices received, is already sending to the crusher mineral of the | O17: b | U17: b | AA17: =LEN(C17)+LEN(D17)+LEN(E17)+LEN(F17)+LEN(G17)+LEN(H17)+LEN(I17)+LEN(K17)+LEN(L17)+LEN(M17)+LEN(N17) -> 34
A18: myb45795 | B18: 1888 | C18: REMEDIOS COLOMBIA UNITED GOLD MINES | I18: bolivia | J18: amount of £4,400 were also issued in exchange for the debentures of the old | AA18: =LEN(C18)+LEN(D18)+LEN(E18)+LEN(F18)+LEN(G18)+LEN(H18)+LEN(I18)+LEN(K18)+LEN(L18)+LEN(M18)+LEN(N18) -> 42
A19: myb47091 | B19: 1888 | C19: COMPANY LIMITED | I19: franklin | J19: COMPANY, LIMITED. | AA19: =LEN(C19)+LEN(D19)+LEN(E19)+LEN(F19)+LEN(G19)+LEN(H19)+LEN(I19)+LEN(K19)+LEN(L19)+LEN(M19)+LEN(N19) -> 23
A20: myb50222 | B20: 1888 | C20: UNITED MAY LUNDY GOLD COMPANY LIMITED | D20: 730638.09 | I20: colorado | J20: The authorised capital is £150,000, in fully-paid shares of £1 each. Tho | O20: b | AA20: =LEN(C20)+LEN(D20)+LEN(E20)+LEN(F20)+LEN(G20)+LEN(H20)+LEN(I20)+LEN(K20)+LEN(L20)+LEN(M20)+LEN(N20) -> 56
A21: myb51339 | B21: 1888 | C21: WEST ARGENTINE GOLD COMPANY LIMITED | I21: cornwall | J21: £9o 13s. 5d. per ton, £0,709 9s. ; discounts from merchants, £18 4s. 10d., which with the Inlance | O21: b | AA21: =LEN(C21)+LEN(D21)+LEN(E21)+LEN(F21)+LEN(G21)+LEN(H21)+LEN(I21)+LEN(K21)+LEN(L21)+LEN(M21)+LEN(N21) -> 43
A22: myb54857 | B22: 1888 | C22: HOMESTEAD KOMATI GOLDFIELDS OF SOUTH | I22: sierra | J22: HOMESTEAD KOMATI GOLDFIELDS OF SOUTH | K22: gold | L22: homestead | M22: komati | N22: board | U22: b | V22: b | W22: b | X22: b | Y22: b | AA22: =LEN(C22)+LEN(D22)+LEN(E22)+LEN(F22)+LEN(G22)+LEN(H22)+LEN(I22)+LEN(K22)+LEN(L22)+LEN(M22)+LEN(N22) -> 66
A23: myb59106 | B23: 1889 | C23: ANGLO ASIATIC SYNDICATE LIMITED | I23: mexico | J23: The bullion produced during the year 18 7 realised £105,687 18s. 8 1., and for the first nine | O23: b | AA23: =LEN(C23)+LEN(D23)+LEN(E23)+LEN(F23)+LEN(G23)+LEN(H23)+LEN(I23)+LEN(K23)+LEN(L23)+LEN(M23)+LEN(N23) -> 37
A24: myb62668 | B24: 1889 | C24: CLONCURRY COPPER AND SMELTING COMPANY | I24: glasgow | J24: CLONCURRY COPPER AND SMELTHTG. | AA24: =LEN(C24)+LEN(D24)+LEN(E24)+LEN(F24)+LEN(G24)+LEN(H24)+LEN(I24)+LEN(K24)+LEN(L24)+LEN(M24)+LEN(N24) -> 44
A25: myb69619 | B25: 1889 | C25: AND PUBLIC WORKS SYNDICATE LIMITED | I25: brazil | J25: exploring mining properties, Ac., in Brazil and elsewhere. | O25: b | AA25: =LEN(C25)+LEN(D25)+LEN(E25)+LEN(F25)+LEN(G25)+LEN(H25)+LEN(I25)+LEN(K25)+LEN(L25)+LEN(M25)+LEN(N25) -> 40
A26: myb75402 | B26: 1889 | C26: QUEEN CHARLOTTE SOUND GOLD MINE LIMITED | I26: new zealand | J26: and this sample, not picked in any way and without any visible signs of gold, yielded, on assay | AA26: =LEN(C26)+LEN(D26)+LEN(E26)+LEN(F26)+LEN(G26)+LEN(H26)+LEN(I26)+LEN(K26)+LEN(L26)+LEN(M26)+LEN(N26) -> 50
A27: myb75700 | B27: 1889 | C27: REPUBLICAN MOUNTAIN SILVER MINES LIMITED | I27: georgetown | J27: vendor in fall payment for the property, and are not entitled to any dividend | AA27: =LEN(C27)+LEN(D27)+LEN(E27)+LEN(F27)+LEN(G27)+LEN(H27)+LEN(I27)+LEN(K27)+LEN(L27)+LEN(M27)+LEN(N27) -> 50
A28: myb85575 | B28: 1889 | C28: KANYA EXPLORATION COMPANY LIMITED | I28: s of territories | J28: covered by the grant ; and prospecting work, conducted under the supervision of Mr. A. 8. | U28: a/b | AA28: =LEN(C28)+LEN(D28)+LEN(E28)+LEN(F28)+LEN(G28)+LEN(H28)+LEN(I28)+LEN(K28)+LEN(L28)+LEN(M28)+LEN(N28) -> 49
A29: myb87517 | B29: 1889 | C29: MORGENZON GOLD MINING COMPANY LIMITED | I29: johannesburg | J29: No. 73, granted by the Government of the South African Republic for 15 years, | AA29: =LEN(C29)+LEN(D29)+LEN(E29)+LEN(F29)+LEN(G29)+LEN(H29)+LEN(I29)+LEN(K29)+LEN(L29)+LEN(M29)+LEN(N29) -> 49
A30: myb88079 | B30: 1889 | C30: NIGEL GOLD MINING COMPANY LIMITED | I30: heidelberg | J30: THIS company was formed in July, 1888, for the purpose of acquiring a mining | AA30: =LEN(C30)+LEN(D30)+LEN(E30)+LEN(F30)+LEN(G30)+LEN(H30)+LEN(I30)+LEN(K30)+LEN(L30)+LEN(M30)+LEN(N30) -> 43
A31: myb90530 | B31: 1889 | C31: MINING AND EXPLORATION CO LTD | I31: australia | J31: and £32,132 5s. paid up ; the 100 founders shares and 20,000 ordinary shares | AA31: =LEN(C31)+LEN(D31)+LEN(E31)+LEN(F31)+LEN(G31)+LEN(H31)+LEN(I31)+LEN(K31)+LEN(L31)+LEN(M31)+LEN(N31) -> 38
A32: myb93188 | B32: 1889 | C32: ZAMBESI CONCESSIONS COMPANY LIMITED | I32: london | J32: Directors. | AA32: =LEN(C32)+LEN(D32)+LEN(E32)+LEN(F32)+LEN(G32)+LEN(H32)+LEN(I32)+LEN(K32)+LEN(L32)+LEN(M32)+LEN(N32) -> 41
A33: myb95061 | B33: 1891 | C33: BAHANCANNE COPFEH | D33: NA | E33: NA | F33: NA | G33: NA | H33: NA | I33: NA | J33: is common and the fee 2s. 6d. per deed. | K33: NA | L33: NA | M33: NA | N33: NA | O33: a | Z33: 2 | AA33: =LEN(C33) -> 17
A34: myb97309 | B34: 1891 | C34: CENTRAL ARGENTINE GOLD FIELDS LIMITED | I34: florence | J34: Sarawak Coal Concession acquired in April, 1889 , which gives the right to mine for cos , | O34: b | U34: b | AA34: =LEN(C34)+LEN(D34)+LEN(E34)+LEN(F34)+LEN(G34)+LEN(H34)+LEN(I34)+LEN(K34)+LEN(L34)+LEN(M34)+LEN(N34) -> 45
A35: myb97977 | B35: 1891 | C35: UNION CORPORATION LTD | I35: somerset | J35: the proportion which the amount of capital subscribed bears to the nominal | O35: b | U35: b | AA35: =LEN(C35)+LEN(D35)+LEN(E35)+LEN(F35)+LEN(G35)+LEN(H35)+LEN(I35)+LEN(K35)+LEN(L35)+LEN(M35)+LEN(N35) -> 29
A36: myb100462 | B36: 1891 | C36: ENGLISH CROWN SPELTER COMPANY LIMITED | I36: swansea | J36: creation of 16,000 new shares of £1 each, and the £4 shares were sub-divided | AA36: =LEN(C36)+LEN(D36)+LEN(E36)+LEN(F36)+LEN(G36)+LEN(H36)+LEN(I36)+LEN(K36)+LEN(L36)+LEN(M36)+LEN(N36) -> 44
A37: myb103335 | B37: 1891 | C37: ISLE OF MAN MINING COMPANY LIMITED | J37: Beckwith e shaft has been sunk 17 fathoms, or deep enough for another level below the | AA37: =LEN(C37)+LEN(D37)+LEN(E37)+LEN(F37)+LEN(G37)+LEN(H37)+LEN(I37)+LEN(K37)+LEN(L37)+LEN(M37)+LEN(N37) -> 34
A38: myb107969 | B38: 1891 | C38: NEW MINERA MININ G | D38: NA | E38: NA | F38: NA | G38: NA | H38: NA | I38: lima | J38: 25th August and 9th September, 1890, to wind up the oompany voluntarily and | K38: NA | L38: NA | M38: NA | N38: NA | O38: a | U38: b | Z38: 2 | AA38: =LEN(C38) -> 18
A39: myb119202 | B39: 1891 | C39: SYNDICATE LIMITED | I39: london | J39: Directors. | AA39: =LEN(C39)+LEN(D39)+LEN(E39)+LEN(F39)+LEN(G39)+LEN(H39)+LEN(I39)+LEN(K39)+LEN(L39)+LEN(M39)+LEN(N39) -> 23
A40: myb123322 | B40: 1891 | C40: NORTH AFRICAN EXPLORATION SYNDICATE | I40: transvaal | J40: Offloes. | U40: b | AA40: =LEN(C40)+LEN(D40)+LEN(E40)+LEN(F40)+LEN(G40)+LEN(H40)+LEN(I40)+LEN(K40)+LEN(L40)+LEN(M40)+LEN(N40) -> 44
A41: myb124568 | B41: 1891 | C41: SHEBA GOLD MINING COMPANY LIMITED | I41: transvaal | J41: the 31st March, 1838. The accounts to the 30th September, 1839, showed a profit or the twelve | AA41: =LEN(C41)+LEN(D41)+LEN(E41)+LEN(F41)+LEN(G41)+LEN(H41)+LEN(I41)+LEN(K41)+LEN(L41)+LEN(M41)+LEN(N41) -> 42
A42: myb127174 | B42: 1891 | C42: WEST AFRICAN CONCESSIONS SYNDICATE | I42: western | J42: Government. | U42: b | AA42: =LEN(C42)+LEN(D42)+LEN(E42)+LEN(F42)+LEN(G42)+LEN(H42)+LEN(I42)+LEN(K42)+LEN(L42)+LEN(M42)+LEN(N42) -> 41
A43: myb129379 | B43: 1893 | C43: AVALA QUICKSILVER MINES LIMITED | I43: london | J43: In 1890 Mr. Weifert one of the Servian directors , who was one of the vendors, agreed to find a sufficient sum of money to carry the works to a greater | AA43: =LEN(C43)+LEN(D43)+LEN(E43)+LEN(F43)+LEN(G43)+LEN(H43)+LEN(I43)+LEN(K43)+LEN(L43)+LEN(M43)+LEN(N43) -> 37
A44: myb133288 | B44: 1893 | C44: DON PEDRO GOLD MINING COMPANY LIMITED | I44: england | J44: of mining account of £12,541 9s., making a total debit of £66,346 15s 4d. | AA44: =LEN(C44)+LEN(D44)+LEN(E44)+LEN(F44)+LEN(G44)+LEN(H44)+LEN(I44)+LEN(K44)+LEN(L44)+LEN(M44)+LEN(N44) -> 44
A45: myb138263 | B45: 1893 | C45: MESQUITAL DEL ORO MINING COMPANY | I45: zacatecas | J45: Zacatecas, Republic of Mexico, and in 1886 the company purchased the adjoining | AA45: =LEN(C45)+LEN(D45)+LEN(E45)+LEN(F45)+LEN(G45)+LEN(H45)+LEN(I45)+LEN(K45)+LEN(L45)+LEN(M45)+LEN(N45) -> 41
A46: myb146526 | B46: 1893 | C46: DIRECTORS | J46: :ne whole business. | O46: b | AA46: =LEN(C46)+LEN(D46)+LEN(E46)+LEN(F46)+LEN(G46)+LEN(H46)+LEN(I46)+LEN(K46)+LEN(L46)+LEN(M46)+LEN(N46) -> 9
A47: myb154294 | B47: 1893 | C47: LONDON AND FOREIGN CONTRACT CORPORATION | F47: 1888 | I47: london | J47: This syndicate was registered on the 16th January, 1888, to acquire concessions, | K47: registered | L47: this | M47: syndicate | N47: board | O47: b | V47: b | W47: b | X47: b | Y47: b | AA47: =LEN(C47)+LEN(D47)+LEN(E47)+LEN(F47)+LEN(G47)+LEN(H47)+LEN(I47)+LEN(K47)+LEN(L47)+LEN(M47)+LEN(N47) -> 77
A48: myb155873 | B48: 1893 | C48: NEW MYNPACHT GOLD MINING COMPANY | I48: transvaal | J48: Potchefstroom District, Transvaal, formerly the property of the Mynpacht Lui- | AA48: =LEN(C48)+LEN(D48)+LEN(E48)+LEN(F48)+LEN(G48)+LEN(H48)+LEN(I48)+LEN(K48)+LEN(L48)+LEN(M48)+LEN(N48) -> 41
A49: myb160413 | B49: 1894 | C49: ACHILLES GOLDFIELDS LIMITED | I49: london | J49: F. M. Eden, Chairman. | K49: eddy | L49: frederick | M49: morton | N49: chair | V49: b | W49: b | X49: b | AA49: =LEN(C49)+LEN(D49)+LEN(E49)+LEN(F49)+LEN(G49)+LEN(H49)+LEN(I49)+LEN(K49)+LEN(L49)+LEN(M49)+LEN(N49) -> 57
A50: myb160514 | B50: 1894 | C50: ALADDIN S LAMP GOLD MINING COMPANY LIMITED | I50: wales | J50: Proprietary Company for 20 years from the 1st March, 1892, subject to a royalty | AA50: =LEN(C50)+LEN(D50)+LEN(E50)+LEN(F50)+LEN(G50)+LEN(H50)+LEN(I50)+LEN(K50)+LEN(L50)+LEN(M50)+LEN(N50) -> 47
A51: myb162808 | B51: 1894 | C51: BLINMAN MINING COMPANY LIMITED | I51: australia | J51: 21st December, 1885, to acquire from Henry Keudrick, as liquidator of the Cor | R51: b | AA51: =LEN(C51)+LEN(D51)+LEN(E51)+LEN(F51)+LEN(G51)+LEN(H51)+LEN(I51)+LEN(K51)+LEN(L51)+LEN(M51)+LEN(N51) -> 39
A52: myb171939 | B52: 1894 | C52: NEW MOUNT ALBION SILVER | I52: pachuca | J52: working the silver-mining grants known as San Miguel del Tajo, La Union, and | O52: b | AA52: =LEN(C52)+LEN(D52)+LEN(E52)+LEN(F52)+LEN(G52)+LEN(H52)+LEN(I52)+LEN(K52)+LEN(L52)+LEN(M52)+LEN(N52) -> 30
A53: myb173419 | B53: 1894 | C53: OURAY GOLD MINING COMPANY LIMITED | I53: united states | J53: have been suspended, and the company is practicajly defunct. | AA53: =LEN(C53)+LEN(D53)+LEN(E53)+LEN(F53)+LEN(G53)+LEN(H53)+LEN(I53)+LEN(K53)+LEN(L53)+LEN(M53)+LEN(N53) -> 46
A54: myb177208 | B54: 1894 | C54: SPANISH COPPER CQMEANY LIMITED | I54: london | J54: M. Mnmford. 2, Tokenhouse Buildings, E.C. | Q54: b | V54: b | W54: b | AA54: =LEN(C54)+LEN(D54)+LEN(E54)+LEN(F54)+LEN(G54)+LEN(H54)+LEN(I54)+LEN(K54)+LEN(L54)+LEN(M54)+LEN(N54) -> 36
A55: myb179154 | B55: 1894 | C55: WESTWOETH GOLD FIELDS | I55: morton | J55: as either to be paid off by the vendors or a corresponding reduction made in the | U55: b | AA55: =LEN(C55)+LEN(D55)+LEN(E55)+LEN(F55)+LEN(G55)+LEN(H55)+LEN(I55)+LEN(K55)+LEN(L55)+LEN(M55)+LEN(N55) -> 27
A56: myb180450 | B56: 1894 | C56: BANTJES REEF GOLD MINING COMPANY | D56: 463414.6 | I56: western | J56: The authorised capital is £95,000, in 95,000 shares of £1 each, of which 83,000 | U56: b | AA56: =LEN(C56)+LEN(D56)+LEN(E56)+LEN(F56)+LEN(G56)+LEN(H56)+LEN(I56)+LEN(K56)+LEN(L56)+LEN(M56)+LEN(N56) -> 47
A57: myb180875 | B57: 1894 | C57: BBITISH SOUTH AFRICA | I57: oaxaca | J57: including the region to the north and west of the Bechuanaland Protectorate, | U57: b | AA57: =LEN(C57)+LEN(D57)+LEN(E57)+LEN(F57)+LEN(G57)+LEN(H57)+LEN(I57)+LEN(K57)+LEN(L57)+LEN(M57)+LEN(N57) -> 26
A58: myb192007 | B58: 1895 | C58: BAYLEY S WEST EXTENDED LIMITED | I58: hopewell | J58: October, 1801, as to the joint management and use of plant. | AA58: =LEN(C58)+LEN(D58)+LEN(E58)+LEN(F58)+LEN(G58)+LEN(H58)+LEN(I58)+LEN(K58)+LEN(L58)+LEN(M58)+LEN(N58) -> 38
A59: myb194632 | B59: 1895 | C59: CENTRAL COLLIERIES LIMITED | I59: marshall | J59: are not obtainable. Transfer form, common ; fee, 2s. 6d. per deed. | U59: b | AA59: =LEN(C59)+LEN(D59)+LEN(E59)+LEN(F59)+LEN(G59)+LEN(H59)+LEN(I59)+LEN(K59)+LEN(L59)+LEN(M59)+LEN(N59) -> 34
A60: myb195436 | B60: 1895 | C60: COHTEZ MINES | J60: with the balance from September, 1891, made £15,398 10s. 9d. available for | U60: b | AA60: =LEN(C60)+LEN(D60)+LEN(E60)+LEN(F60)+LEN(G60)+LEN(H60)+LEN(I60)+LEN(K60)+LEN(L60)+LEN(M60)+LEN(N60) -> 12
A61: myb195639 | B61: 1895 | C61: CRACKER CREEK GOLD MINES COMPANY LIMITED | I61: oregon | J61: CRACKER CREEK GOLD MINES COMPANY, LIMITED. | AA61: =LEN(C61)+LEN(D61)+LEN(E61)+LEN(F61)+LEN(G61)+LEN(H61)+LEN(I61)+LEN(K61)+LEN(L61)+LEN(M61)+LEN(N61) -> 46
A62: myb195811 | B62: 1895 | C62: CUE GOLDFIELD OF WESTERN AUSTRALIA | I62: western | J62: Australian Government are for periods of 21 years, renewable in perpetuity, at a | AA62: =LEN(C62)+LEN(D62)+LEN(E62)+LEN(F62)+LEN(G62)+LEN(H62)+LEN(I62)+LEN(K62)+LEN(L62)+LEN(M62)+LEN(N62) -> 41
A63: myb198587 | B63: 1895 | C63: GOLDEN FEATHER LIMITED | I63: london | J63: Agents in America. Bankers. Solicitors. | AA63: =LEN(C63)+LEN(D63)+LEN(E63)+LEN(F63)+LEN(G63)+LEN(H63)+LEN(I63)+LEN(K63)+LEN(L63)+LEN(M63)+LEN(N63) -> 28
A64: myb206195 | B64: 1895 | C64: COMPANY LIMITED | I64: france | J64: 1878 9 | O64: b | AA64: =LEN(C64)+LEN(D64)+LEN(E64)+LEN(F64)+LEN(G64)+LEN(H64)+LEN(I64)+LEN(K64)+LEN(L64)+LEN(M64)+LEN(N64) -> 21
A65: myb206913 | B65: 1895 | C65: RAVENSCLIFF MINING COMPANY LIMITED | I65: new zealand | J65: Charles Henry Turner, Kelson, N.Z. | V65: f | W65: f | X65: f | AA65: =LEN(C65)+LEN(D65)+LEN(E65)+LEN(F65)+LEN(G65)+LEN(H65)+LEN(I65)+LEN(K65)+LEN(L65)+LEN(M65)+LEN(N65) -> 45
A66: myb213759 | B66: 1895 | C66: TPHEEGAT COAL | D66: NA | E66: NA | F66: NA | G66: NA | H66: NA | I66: dalton | J66: s Denny-Dalton Syndicate, Limited, about 1,300 acres of land, forming a | K66: NA | L66: NA | M66: NA | N66: NA | O66: b | U66: b | Z66: 1 | AA66: =LEN(C66) -> 13
A67: myb215149 | B67: 1895 | C67: GOLD FIELDS OF MASHONALAND LIMITED | I67: london | J67: is company was registered on the 21st February, 1893, for the purpose of | O67: b | R67: b | AA67: =LEN(C67)+LEN(D67)+LEN(E67)+LEN(F67)+LEN(G67)+LEN(H67)+LEN(I67)+LEN(K67)+LEN(L67)+LEN(M67)+LEN(N67) -> 40
A68: myb216558 | B68: 1895 | C68: KOBOLONDO DEVELOPMENT SYNDICATE LTD | I68: london | J68: 1893, showed expenditure to date, £2,008 7s. ; cash balances, £356 7s. Id. | AA68: =LEN(C68)+LEN(D68)+LEN(E68)+LEN(F68)+LEN(G68)+LEN(H68)+LEN(I68)+LEN(K68)+LEN(L68)+LEN(M68)+LEN(N68) -> 41
A69: myb222618 | B69: 1895 | C69: MINE LIMITED | I69: london | J69: All work has remained suspended and the mine shut down since April, 1892. The | O69: b | AA69: =LEN(C69)+LEN(D69)+LEN(E69)+LEN(F69)+LEN(G69)+LEN(H69)+LEN(I69)+LEN(K69)+LEN(L69)+LEN(M69)+LEN(N69) -> 18
A70: myb224504 | B70: 1895 | C70: VILLAGE MAIN REEF GOLD MINING CO LTD | I70: transvaal | J70: west for 37,000 fully-paid shares. | AA70: =LEN(C70)+LEN(D70)+LEN(E70)+LEN(F70)+LEN(G70)+LEN(H70)+LEN(I70)+LEN(K70)+LEN(L70)+LEN(M70)+LEN(N70) -> 45
A71: myb225024 | B71: 1895 | C71: WOLHUTER GOLD MINING COMPANY LIMITED | I71: london | J71: Mink. The large amount of development work done during the pa t year have greatlv | AA71: =LEN(C71)+LEN(D71)+LEN(E71)+LEN(F71)+LEN(G71)+LEN(H71)+LEN(I71)+LEN(K71)+LEN(L71)+LEN(M71)+LEN(N71) -> 42
A72: myb225838 | B72: 1895 | C72: MINING DIRECTORS | E72: victoria road old cliarlton | I72: transvaal | J72: Barwell, Major-General William Harwell, 33, Victoria Road, Old Cliarlton, 8.E., is a director | O72: b | Q72: b | U72: b | AA72: =LEN(C72)+LEN(D72)+LEN(E72)+LEN(F72)+LEN(G72)+LEN(H72)+LEN(I72)+LEN(K72)+LEN(L72)+LEN(M72)+LEN(N72) -> 52
A73: myb228991 | B73: 1895 | C73: 754 THM . | I73: colombia | J73: Randt Coal Mining and Land Company, Limited. | O73: b | U73: b | AA73: =LEN(C73)+LEN(D73)+LEN(E73)+LEN(F73)+LEN(G73)+LEN(H73)+LEN(I73)+LEN(K73)+LEN(L73)+LEN(M73)+LEN(N73) -> 17
A74: myb231370 | B74: 1895 | C74: AFRICAN GOLD RECOVERY COMPANY LIMITED | I74: johannesburg | J74: placed to reserve, and the balance of £913 13s. 41. was carried forward. Thi | AA74: =LEN(C74)+LEN(D74)+LEN(E74)+LEN(F74)+LEN(G74)+LEN(H74)+LEN(I74)+LEN(K74)+LEN(L74)+LEN(M74)+LEN(N74) -> 49
A75: myb234853 | B75: 1895 | C75: GOLD FIELDS OF MASHONALAND LIMITED | I75: london | J75: is company was registered on the 21st February, 1893, for the purpose of | AA75: =LEN(C75)+LEN(D75)+LEN(E75)+LEN(F75)+LEN(G75)+LEN(H75)+LEN(I75)+LEN(K75)+LEN(L75)+LEN(M75)+LEN(N75) -> 40
A76: myb235048 | B76: 1895 | C76: DUTOITSPAN MINE LIMITED | I76: london | J76: payable, the Griqnaland Company has the right to re-enter and take possession | O76: b | AA76: =LEN(C76)+LEN(D76)+LEN(E76)+LEN(F76)+LEN(G76)+LEN(H76)+LEN(I76)+LEN(K76)+LEN(L76)+LEN(M76)+LEN(N76) -> 29
A77: myb236115 | B77: 1895 | C77: SYNDICATE LIMITED | I77: great namaqualand | J77: interest. Transfer form, common ; fee, 2s. 6d. per deed. | O77: b | AA77: =LEN(C77)+LEN(D77)+LEN(E77)+LEN(F77)+LEN(G77)+LEN(H77)+LEN(I77)+LEN(K77)+LEN(L77)+LEN(M77)+LEN(N77) -> 34
A78: myb251549 | B78: 1903 | C78: ANGLO ALASKAN SYNDICATE LIMITED | F78: 1809 | I78: london | J78: THIS syndicate was registered on the 11th March, 1809, and is a reconstruction | AA78: =LEN(C78)+LEN(D78)+LEN(E78)+LEN(F78)+LEN(G78)+LEN(H78)+LEN(I78)+LEN(K78)+LEN(L78)+LEN(M78)+LEN(N78) -> 41
A79: myb252170 | B79: 1903 | C79: ARIZONA COPPER COMPANY LIMITED | I79: somerset | J79: shares £131,625 have been issued and are now converted into fully-paid | U79: b | AA79: =LEN(C79)+LEN(D79)+LEN(E79)+LEN(F79)+LEN(G79)+LEN(H79)+LEN(I79)+LEN(K79)+LEN(L79)+LEN(M79)+LEN(N79) -> 38
A80: myb252386 | B80: 1903 | C80: ATLIN LAKE COMPANY LIMITED | I80: prescott | J80: Directors Qualification, £100 . | U80: b | AA80: =LEN(C80)+LEN(D80)+LEN(E80)+LEN(F80)+LEN(G80)+LEN(H80)+LEN(I80)+LEN(K80)+LEN(L80)+LEN(M80)+LEN(N80) -> 34
A81: myb253695 | B81: 1903 | C81: BLAINSCOUGH CVOLLIERY COMPANY LIMITED | I81: darlington | J81: The accounts are made up half-yearly to the 30th June and 81st December, | U81: b | AA81: =LEN(C81)+LEN(D81)+LEN(E81)+LEN(F81)+LEN(G81)+LEN(H81)+LEN(I81)+LEN(K81)+LEN(L81)+LEN(M81)+LEN(N81) -> 47
A82: myb258586 | B82: 1903 | C82: EDINBURGH COLLIERIES CO LTD | J82: Robert Thomas Moore, M.E. I Alexander H. Nasmyth. l Adam Nimrnc. | K82: moore | L82: robert | M82: thomas | N82: board | U82: b | AA82: =LEN(C82)+LEN(D82)+LEN(E82)+LEN(F82)+LEN(G82)+LEN(H82)+LEN(I82)+LEN(K82)+LEN(L82)+LEN(M82)+LEN(N82) -> 49
A83: myb258586 | B83: 1903 | C83: EDINBURGH COLLIERIES CO LTD | J83: Robert Thomas Moore, M.E. I Alexander H. Nasmyth. l Adam Nimrnc. | K83: nash | L83: alexander | N83: board | U83: b | V83: b | X83: b | AA83: =LEN(C83)+LEN(D83)+LEN(E83)+LEN(F83)+LEN(G83)+LEN(H83)+LEN(I83)+LEN(K83)+LEN(L83)+LEN(M83)+LEN(N83) -> 45
A84: myb260430 | B84: 1903 | C84: GLENAVON RHONDDA COLLIERIES COMPANYI | J84: 6,105 preference and 15.000 ordinary being issued credited as paid. There are | U84: b | AA84: =LEN(C84)+LEN(D84)+LEN(E84)+LEN(F84)+LEN(G84)+LEN(H84)+LEN(I84)+LEN(K84)+LEN(L84)+LEN(M84)+LEN(N84) -> 36
A85: myb261902 | B85: 1903 | C85: HUTTI NIZAM S GOLD MINES LTD | I85: cannon street ec | J85: Bankers N ational Bank of India, Limited. | AA85: =LEN(C85)+LEN(D85)+LEN(E85)+LEN(F85)+LEN(G85)+LEN(H85)+LEN(I85)+LEN(K85)+LEN(L85)+LEN(M85)+LEN(N85) -> 44
A86: myb271839 | B86: 1903 | C86: SHELTON IRON STEEL AND COAL CO LTD | I86: april | J86: and 21,966 ordinary shares have been issued and are fully paid. The preference | U86: b | AA86: =LEN(C86)+LEN(D86)+LEN(E86)+LEN(F86)+LEN(G86)+LEN(H86)+LEN(I86)+LEN(K86)+LEN(L86)+LEN(M86)+LEN(N86) -> 39
A87: myb272594 | B87: 1903 | C87: SYHELAIEIMITED | I87: united kingdom | J87: shire, or elsewhere in the United Kingdom. | O87: b | AA87: =LEN(C87)+LEN(D87)+LEN(E87)+LEN(F87)+LEN(G87)+LEN(H87)+LEN(I87)+LEN(K87)+LEN(L87)+LEN(M87)+LEN(N87) -> 28
A88: myb275015 | B88: 1903 | C88: WELCOME HILL MOEL Y GROESAU MINES | I88: wales | J88: Festiniog, 1,072 acres in extent, with an option over an adjoining block | AA88: =LEN(C88)+LEN(D88)+LEN(E88)+LEN(F88)+LEN(G88)+LEN(H88)+LEN(I88)+LEN(K88)+LEN(L88)+LEN(M88)+LEN(N88) -> 38
A89: myb279132 | B89: 1908 | C89: GREAT BOULDER NO LTD | I89: kalgoorlie | J89: per ton. Estimated ore reserves at December 31st, 1906 : 383,410 tons, assay | AA89: =LEN(C89)+LEN(D89)+LEN(E89)+LEN(F89)+LEN(G89)+LEN(H89)+LEN(I89)+LEN(K89)+LEN(L89)+LEN(M89)+LEN(N89) -> 30
A90: myb281049 | B90: 1908 | C90: MINING AND GUARANTEE COMPANY LIMITED | D90: 632603.4 | I90: wales | J90: The authorised capital is £130,000, in 130,000 shares of £1 each ; 65,005 shares | O90: b | AA90: =LEN(C90)+LEN(D90)+LEN(E90)+LEN(F90)+LEN(G90)+LEN(H90)+LEN(I90)+LEN(K90)+LEN(L90)+LEN(M90)+LEN(N90) -> 49
A91: myb284283 | B91: 1908 | C91: VICTORIAN CORNISH GOLD MINES LIMITED | I91: london | J91: all the shares | AA91: =LEN(C91)+LEN(D91)+LEN(E91)+LEN(F91)+LEN(G91)+LEN(H91)+LEN(I91)+LEN(K91)+LEN(L91)+LEN(M91)+LEN(N91) -> 42
A92: myb286531 | B92: 1908 | C92: APEX MINES LTD | I92: london | J92: in July, 1895, 25,000 shares being issued to shareholders at 35s. each and 31,500 | AA92: =LEN(C92)+LEN(D92)+LEN(E92)+LEN(F92)+LEN(G92)+LEN(H92)+LEN(I92)+LEN(K92)+LEN(L92)+LEN(M92)+LEN(N92) -> 20
A93: myb288485 | B93: 1908 | C93: C ASSI NGA CONCESSIONS LI MITE D | D93: NA | E93: about square miles in the | F93: NA | G93: NA | H93: NA | I93: canada | J93: rights over a dirtriot of about 11,000 square miles in the territories of the | K93: NA | L93: NA | M93: NA | N93: NA | O93: a | Q93: b | U93: b | Z93: 1 | AA93: =LEN(C93) -> 32
A94: myb300828 | B94: 1908 | C94: FIGG S PEAK DEVELOPMENT | D94: NA | E94: NA | F94: NA | G94: NA | H94: NA | I94: london | J94: eight shares of the former company, further capital being raised by an issue of | K94: NA | L94: NA | M94: NA | N94: NA | O94: a | Z94: 1 | AA94: =LEN(C94) -> 23
A95: myb304160 | B95: 1908 | C95: SOUTH AFKICAN COMPANY | D95: NA | E95: NA | F95: NA | G95: NA | H95: NA | I95: transvaal | J95: The accounts for year ended December 31st, 1905, submitted in Johannes | K95: NA | L95: NA | M95: NA | N95: NA | O95: a | Z95: 1 | AA95: =LEN(C95) -> 21
A96: myb310176 | B96: 1908 | C96: ATLANTIC FINANCE CORPORATION | I96: british columbia | J96: are issued and fully paid. No prospectus was issued ; £7,500 working capital | O96: b | AA96: =LEN(C96)+LEN(D96)+LEN(E96)+LEN(F96)+LEN(G96)+LEN(H96)+LEN(I96)+LEN(K96)+LEN(L96)+LEN(M96)+LEN(N96) -> 44
A97: myb311920 | B97: 1908 | C97: BRITISH AND ARGENTINE CORPORATION LIMITED | I97: london | J97: BRITISH MOLYBDENITE Cbl ANY. LIMITED; | O97: b | AA97: =LEN(C97)+LEN(D97)+LEN(E97)+LEN(F97)+LEN(G97)+LEN(H97)+LEN(I97)+LEN(K97)+LEN(L97)+LEN(M97)+LEN(N97) -> 47
A98: myb312077 | B98: 1908 | C98: BROOKE S A NT H RACITE SYNDI CATE LIMITED | D98: NA | E98: NA | F98: NA | G98: NA | H98: NA | I98: newcastle | J98: 175,000. Transfer form, common ; fee, 2s. 6d. | K98: NA | L98: NA | M98: NA | N98: NA | O98: a | Z98: 2 | AA98: =LEN(C98) -> 41
A99: myb315363 | B99: 1908 | C99: DEMERARA EXPLORATION COMPANY LIMITED | I99: buckingham | J99: issued and fully paid. No accounts received. Transfer form, common ; fee, 2 . 6d. denaby a nd ca7d£ by m ain co lQe rTe s, ltd. Directors Qualification, lourdinary shares £1,000 . J. Buckingham Pope, Chairman | John C. Cuninghame. | Capt. M. E. W. Pope. | K99: cundv | L99: john | M99: charles | N99: board | U99: b | V99: b | X99: b | AA99: =LEN(C99)+LEN(D99)+LEN(E99)+LEN(F99)+LEN(G99)+LEN(H99)+LEN(I99)+LEN(K99)+LEN(L99)+LEN(M99)+LEN(N99) -> 67
A100: myb315363 | B100: 1908 | C100: DEMERARA EXPLORATION COMPANY LIMITED | I100: buckingham | J100: issued and fully paid. No accounts received. Transfer form, common ; fee, 2 . 6d. denaby a nd ca7d£ by m ain co lQe rTe s, ltd. Directors Qualification, lourdinary shares £1,000 . J. Buckingham Pope, Chairman | John C. Cuninghame. | Capt. M. E. W. Pope. | K100: demond | L100: fee | N100: chair | U100: b | V100: b | W100: b | Y100: b | AA100: =LEN(C100)+LEN(D100)+LEN(E100)+LEN(F100)+LEN(G100)+LEN(H100)+LEN(I100)+LEN(K100)+LEN(L100)+LEN(M100)+LEN(N100) -> 60
...

Sheet ammt
A1: id | B1: year | C1: company | D1: stock | E1: office | F1: yinc | G1: locinc | H1: loc | I1: text | J1: lastname | K1: firstname | L1: middlename | M1: prof | N1: company | O1: stock | P1: office | Q1: yinc | R1: locinc | S1: loc | T1: text | U1: lastname | V1: firstname | W1: middlename | X1: prof | Y1: cer | Z1: tot | AA1: extracted/actual | AB1: positive | AC1: negative
A2: amm218 | B2: 1907 | C2: Reynolds Alaska Development Company. Ellamar. | E2: State St, Boston | H2: boston | I2: Office, 27 State St., Boston. Howard D. Reynolds, Pres.; Blamey Stevens. | J2: reynolds | K2: howard | L2: d | M2: Pres | Z2: =LEN(C2)+LEN(D2)+LEN(E2)+LEN(F2)+LEN(G2)+LEN(H2)+LEN(J2)+LEN(K2)+LEN(L2)+LEN(M2) -> 87 | AA2: positive | AB2: t | AC2: f
A3: amm241 | B3: 1907 | C3: Yukon Consolidated Gold Fields Company. Dawson. | H3: broadway | I3: (Guggenheim Exploration Co.) Office, 71 Broadway, New York. Oscar | P3: b | Z3: =LEN(C3)+LEN(D3)+LEN(E3)+LEN(F3)+LEN(G3)+LEN(H3)+LEN(J3)+LEN(K3)+LEN(L3)+LEN(M3) -> 56 | AA3: negative | AB3: f | AC3: t
A4: amm296 | B4: 1907 | C4: Republic Zinc Company. Rush. | I4: Republic Zinc Company. Rush. | Z4: =LEN(C4)+LEN(D4)+LEN(E4)+LEN(F4)+LEN(G4)+LEN(H4)+LEN(J4)+LEN(K4)+LEN(L4)+LEN(M4) -> 28
A5: amm428 | B5: 1907 | C5: Black Prince Copper Company. Johnson. | I5: Teviston. | N5: b | Z5: =LEN(C5)+LEN(D5)+LEN(E5)+LEN(F5)+LEN(G5)+LEN(H5)+LEN(J5)+LEN(K5)+LEN(L5)+LEN(M5) -> 37 | AA5: code
A6: amm704 | B6: 1907 | C6: Henrietta Cyanide & Development Company. Big Bug, | I6: Prescott. | N6: b | Z6: =LEN(C6)+LEN(D6)+LEN(E6)+LEN(F6)+LEN(G6)+LEN(H6)+LEN(J6)+LEN(K6)+LEN(L6)+LEN(M6) -> 49 | AA6: extracted/actual | AB6: positive | AC6: negative
A7: amm1078 | B7: 1907 | C7: Union Pass Gold Mining Company. Kingman. | I7: United Globe Mines. Globe. | N7: b | Z7: =LEN(C7)+LEN(D7)+LEN(E7)+LEN(F7)+LEN(G7)+LEN(H7)+LEN(J7)+LEN(K7)+LEN(L7)+LEN(M7) -> 40 | AA7: positive | AC7: f
A8: amm1156 | B8: 1907 | C8: American Mining & Development Company. Kennett. | I8: American Mining & Development Company. Kennett. | Z8: =LEN(C8)+LEN(D8)+LEN(E8)+LEN(F8)+LEN(G8)+LEN(H8)+LEN(J8)+LEN(K8)+LEN(L8)+LEN(M8) -> 47 | AA8: negative | AB8: f
A9: amm1249 | B9: 1907 | C9: Bully Hill Copper Mining & Smelting Company. Winthrop. | I9: Bully Hill Copper Mining & Smelting Company. Winthrop. | Z9: =LEN(C9)+LEN(D9)+LEN(E9)+LEN(F9)+LEN(G9)+LEN(H9)+LEN(J9)+LEN(K9)+LEN(L9)+LEN(M9) -> 54
A10: amm1481 | B10: 1907 | C10: Empire Mines & Investment Company. Grass Valley. | I10: men. | Z10: =LEN(C10)+LEN(D10)+LEN(E10)+LEN(F10)+LEN(G10)+LEN(H10)+LEN(J10)+LEN(K10)+LEN(L10)+LEN(M10) -> 48 | AA10: types of mistakes on true positives
A11: amm1890 | B11: 1907 | C11: New Bodie Mining Company. Bodie. | I11: W. A. R. Loose, Mgr. Gold. Steam. 20 men. | J11: looal | K11: a | L11: r | M11: Mgr | U11: b | V11: b | W11: b | Z11: =LEN(C11)+LEN(D11)+LEN(E11)+LEN(F11)+LEN(G11)+LEN(H11)+LEN(J11)+LEN(K11)+LEN(L11)+LEN(M11) -> 42 | AA11: no mistake
A12: amm2198 | B12: 1907 | C12: Trojan Mining Company. Fenner. | I12: A. M. Rockwell. Supt. Bonanza King Mine. Silver, Lead & Zinc. Steam | J12: rochester | K12: a | M12: Supt | U12: b | W12: b | Z12: =LEN(C12)+LEN(D12)+LEN(E12)+LEN(F12)+LEN(G12)+LEN(H12)+LEN(J12)+LEN(K12)+LEN(L12)+LEN(M12) -> 44 | AA12: source to text | AB12: a
A13: amm2790 | B13: 1907 | C13: Gold Dollar Consolidated Mining Company. Victor. | I13: Newett. | N13: b | Z13: =LEN(C13)+LEN(D13)+LEN(E13)+LEN(F13)+LEN(G13)+LEN(H13)+LEN(J13)+LEN(K13)+LEN(L13)+LEN(M13) -> 48 | AA13: text to class | AB13: b
A14: amm2900 | B14: 1907 | C14: Home Run Leasing Company. | I14: Home Run Leasing Company. | Z14: =LEN(C14)+LEN(D14)+LEN(E14)+LEN(F14)+LEN(G14)+LEN(H14)+LEN(J14)+LEN(K14)+LEN(L14)+LEN(M14) -> 25
A15: amm2938 | B15: 1907 | C15: Indiana Gold Mining & Milling Company. Idaho Springs. | H15: indiana | I15: Indiana Gold Mining & Milling Company. Idaho Springs. | Z15: =LEN(C15)+LEN(D15)+LEN(E15)+LEN(F15)+LEN(G15)+LEN(H15)+LEN(J15)+LEN(K15)+LEN(L15)+LEN(M15) -> 61
A16: amm2955 | B16: 1907 | C16: Iron Silver Mining Company. Leadville. | I16: & Dome Mines. Gold, Silver, Lead & Zinc. Steam. 100 ton Concentrat | Z16: =LEN(C16)+LEN(D16)+LEN(E16)+LEN(F16)+LEN(G16)+LEN(H16)+LEN(J16)+LEN(K16)+LEN(L16)+LEN(M16) -> 38
A17: amm3598 | B17: 1907 | C17: Wonderful London Mines Company. Breckenridge. | H17: denver | I17: Wood (Henry E.) Ore Testing Works. 1734 Arapahoe St., Denver. | N17: b | Z17: =LEN(C17)+LEN(D17)+LEN(E17)+LEN(F17)+LEN(G17)+LEN(H17)+LEN(J17)+LEN(K17)+LEN(L17)+LEN(M17) -> 52
A18: amm3924 | B18: 1907 | C18: Greyhound Mining & Milling Company limited. | H18: custer | I18: Custer. | N18: b | Z18: =LEN(C18)+LEN(D18)+LEN(E18)+LEN(F18)+LEN(G18)+LEN(H18)+LEN(J18)+LEN(K18)+LEN(L18)+LEN(M18) -> 50
A19: amm4213 | B19: 1907 | C19: X Ray Mining Company. | I19: Pearl. | N19: b | Z19: =LEN(C19)+LEN(D19)+LEN(E19)+LEN(F19)+LEN(G19)+LEN(H19)+LEN(J19)+LEN(K19)+LEN(L19)+LEN(M19) -> 21
A20: amm4526 | B20: 1907 | C20: Consumers Ore Company. Palmer. J. R. Thompson, Gen. Mgr.; John H. Huhtala, Supt. Richmond Mine. | H20: michigan | I20: 118 MICHIGAN. | N20: b | S20: b | Z20: =LEN(C20)+LEN(D20)+LEN(E20)+LEN(F20)+LEN(G20)+LEN(H20)+LEN(J20)+LEN(K20)+LEN(L20)+LEN(M20) -> 104
A21: amm4545 | B21: 1907 | C21: Mineral Mining Company. Iron Mountain. | E21: Milwaukee, Wis | H21: milwaukee | I21: Office, Milwaukee, Wis. Elwin F. Brown, Gen. Mgr. Nanaimo, Breen, | J21: brown | K21: elwin | M21: Mgr | W21: b | Z21: =LEN(C21)+LEN(D21)+LEN(E21)+LEN(F21)+LEN(G21)+LEN(H21)+LEN(J21)+LEN(K21)+LEN(L21)+LEN(M21) -> 75
A22: amm4595 | B22: 1907 | C22: Verona Mining Company. Iron Mountain. | I22: Verona Mining Company. Iron Mountain. | Z22: =LEN(C22)+LEN(D22)+LEN(E22)+LEN(F22)+LEN(G22)+LEN(H22)+LEN(J22)+LEN(K22)+LEN(L22)+LEN(M22) -> 37
A23: amm4709 | B23: 1907 | C23: Mine La Motte Lead & Smelting Company. Mine La Motte. | I23: Supt.; S. S. Clarke, Metallurgist. Lead, Nickel, Copper & Cobalt. Steam. | J23: clarke | K23: susan | M23: Supt | W23: b | X23: b | Z23: =LEN(C23)+LEN(D23)+LEN(E23)+LEN(F23)+LEN(G23)+LEN(H23)+LEN(J23)+LEN(K23)+LEN(L23)+LEN(M23) -> 68
A24: amm5343 | B24: 1907 | C24: (Amalgamated Copper Company.) Charles W. Goodale, E. M., Mgr.; John | I24: & West Colusa Mines. Copper Sulphides; Gold & Silver. Steam & Elec | N24: b | Z24: =LEN(C24)+LEN(D24)+LEN(E24)+LEN(F24)+LEN(G24)+LEN(H24)+LEN(J24)+LEN(K24)+LEN(L24)+LEN(M24) -> 67
A25: amm5893 | B25: 1907 | C25: New Era Mining Company. Searchlight. | I25: New Era Mining Company. Searchlight. | Z25: =LEN(C25)+LEN(D25)+LEN(E25)+LEN(F25)+LEN(G25)+LEN(H25)+LEN(J25)+LEN(K25)+LEN(L25)+LEN(M25) -> 36
A26: amm5902 | B26: 1907 | C26: North Mountain Mining Company. Cherry Creek. | I26: Cyanide Plant. 25 men. | Z26: =LEN(C26)+LEN(D26)+LEN(E26)+LEN(F26)+LEN(G26)+LEN(H26)+LEN(J26)+LEN(K26)+LEN(L26)+LEN(M26) -> 44
A27: amm6462 | B27: 1907 | C27: American Goldfields Company. | E27: Marquette Bdg | H27: marquette | I27: Office, 1114 Marquette Bdg., Chicago. W. J | J27: shales | K27: w | L27: j | M27: Supt | U27: b | X27: b | Z27: =LEN(C27)+LEN(D27)+LEN(E27)+LEN(F27)+LEN(G27)+LEN(H27)+LEN(J27)+LEN(K27)+LEN(L27)+LEN(M27) -> 63
A28: amm6574 | B28: 1907 | C28: Eureka Mining Company. | I28: A. F. Nelson, Supt. Gold. Steam. | J28: neilsou | K28: a | L28: f | M28: Supt | U28: b | Z28: =LEN(C28)+LEN(D28)+LEN(E28)+LEN(F28)+LEN(G28)+LEN(H28)+LEN(J28)+LEN(K28)+LEN(L28)+LEN(M28) -> 35
A29: amm7137 | B29: 1907 | C29: Gemini-Godiva Consolidated Mining Company. Eureka. | I29: & Copper. Water & Steam. 100 men. | Z29: =LEN(C29)+LEN(D29)+LEN(E29)+LEN(F29)+LEN(G29)+LEN(H29)+LEN(J29)+LEN(K29)+LEN(L29)+LEN(M29) -> 50
A30: amm7616 | B30: 1907 | C30: Kennedy Mining Company. Platteville. | I30: W. Oberholzer, Supt. St. Paul Mine. Steam. 50 ton Concentrating Plant. | J30: oats | K30: wilhelm | L30: arno | M30: Supt | U30: b | W30: b | Z30: =LEN(C30)+LEN(D30)+LEN(E30)+LEN(F30)+LEN(G30)+LEN(H30)+LEN(J30)+LEN(K30)+LEN(L30)+LEN(M30) -> 55
A31: amm7813 | B31: 1907 | C31: Interstate Exploration Company. Endicott Bdg, St. Paul, Minn. | I31: 2*BAL0ERAS N°I232 | N31: b | Z31: =LEN(C31)+LEN(D31)+LEN(E31)+LEN(F31)+LEN(G31)+LEN(H31)+LEN(J31)+LEN(K31)+LEN(L31)+LEN(M31) -> 61
A32: amm7854 | B32: 1907 | C32: REFINING COMPANY | I32: : | N32: b | Z32: =LEN(C32)+LEN(D32)+LEN(E32)+LEN(F32)+LEN(G32)+LEN(H32)+LEN(J32)+LEN(K32)+LEN(L32)+LEN(M32) -> 16
A33: amm7973 | B33: 1907 | C33: American Smelting & Refining Company. Santa Eulalia. | E33: Broadway, New York | H33: broadway | I33: Office, 71 Broadway, New York. Thomas H. Mitchell, Supt. Sauto Do | J33: mitchell | K33: thomas | M33: Supt | W33: b | Z33: =LEN(C33)+LEN(D33)+LEN(E33)+LEN(F33)+LEN(G33)+LEN(H33)+LEN(J33)+LEN(K33)+LEN(L33)+LEN(M33) -> 97
A34: amm8045 | B34: 1907 | C34: Clarinas Mining Company. Santa Barbara. | I34: & | N34: b | Z34: =LEN(C34)+LEN(D34)+LEN(E34)+LEN(F34)+LEN(G34)+LEN(H34)+LEN(J34)+LEN(K34)+LEN(L34)+LEN(M34) -> 39
A35: amm8104 | B35: 1907 | C35: Clarinas Mining Company. Santa Barbara. | I35: & | N35: b | Z35: =LEN(C35)+LEN(D35)+LEN(E35)+LEN(F35)+LEN(G35)+LEN(H35)+LEN(J35)+LEN(K35)+LEN(L35)+LEN(M35) -> 39
A36: amm8154 | B36: 1907 | C36: Grenadena Mining Company. Santa Barbara. | I36: Grenadena Mining Company. Santa Barbara. | Z36: =LEN(C36)+LEN(D36)+LEN(E36)+LEN(F36)+LEN(G36)+LEN(H36)+LEN(J36)+LEN(K36)+LEN(L36)+LEN(M36) -> 40
A37: amm8366 | B37: 1907 | C37: Coahuila Mining & Smelting Company. Viesca. | I37: Ragaz, Gen. Supt. of Mines; Ernest Harms, Metallurgist & Gen. Supt. of | J37: harman | K37: ernest | M37: Gen. Supt | N37: b | U37: b | Z37: =LEN(C37)+LEN(D37)+LEN(E37)+LEN(F37)+LEN(G37)+LEN(H37)+LEN(J37)+LEN(K37)+LEN(L37)+LEN(M37) -> 64
A38: amm8615 | B38: 1907 | C38: Mina Grande Mining & Milling Company. Tepehuanes. | I38: Eliseo C. Julio, Mgr. Silver & Gold. Steam. 100 men. | J38: judkewitsch | K38: eliseo | L38: c | M38: Mgr | N38: b | U38: b | Z38: =LEN(C38)+LEN(D38)+LEN(E38)+LEN(F38)+LEN(G38)+LEN(H38)+LEN(J38)+LEN(K38)+LEN(L38)+LEN(M38) -> 70
A39: amm8990 | B39: 1907 | C39: Bolanos Mining Company. Bolanos. | I39: Bolanos Mining Company. Bolanos. | Z39: =LEN(C39)+LEN(D39)+LEN(E39)+LEN(F39)+LEN(G39)+LEN(H39)+LEN(J39)+LEN(K39)+LEN(L39)+LEN(M39) -> 32
A40: amm9061 | B40: 1907 | C40: La Fortuna Mining Company. Ahualulco. | I40: La Fortuna Mining Company. Ahualulco. | Z40: =LEN(C40)+LEN(D40)+LEN(E40)+LEN(F40)+LEN(G40)+LEN(H40)+LEN(J40)+LEN(K40)+LEN(L40)+LEN(M40) -> 37
A41: amm9139 | B41: 1907 | C41: Esperanza Mining Company. El Oro. | I41: Esperanza Mining Company. El Oro. | Z41: =LEN(C41)+LEN(D41)+LEN(E41)+LEN(F41)+LEN(G41)+LEN(H41)+LEN(J41)+LEN(K41)+LEN(L41)+LEN(M41) -> 33
A42: amm9352 | B42: 1907 | C42: (American Metal Co., New York.) F. F. Salisbury, Mgr. Minas Viejas | I42: Villaldama. | N42: b | Z42: =LEN(C42)+LEN(D42)+LEN(E42)+LEN(F42)+LEN(G42)+LEN(H42)+LEN(J42)+LEN(K42)+LEN(L42)+LEN(M42) -> 66
A43: amm9406 | B43: 1907 | C43: Baldomero Mining Company. Ocotlan. | E43: Broadway, New York | H43: broadway | I43: Office, 80 Broadway, New York. Charles A. Hamilton, Gen. Mgr.; Charles | J43: hamilto | K43: charles | L43: a | M43: Mgr | U43: a | Y43: 1 | Z43: =LEN(C43)+LEN(D43)+LEN(E43)+LEN(F43)+LEN(G43)+LEN(H43)+LEN(J43)+LEN(K43)+LEN(L43)+LEN(M43) -> 79
A44: amm9442 | B44: 1907 | C44: Conejo Colorado Mining Company. Ocotlan. | I44: Steam. 10 Stamps & 2 Huntington Mills. 50 men. | Z44: =LEN(C44)+LEN(D44)+LEN(E44)+LEN(F44)+LEN(G44)+LEN(H44)+LEN(J44)+LEN(K44)+LEN(L44)+LEN(M44) -> 40
A45: amm9722 | B45: 1907 | C45: Las Tablas Copper Company. Aguacaliente de Baca. | I45: 200 men. | N45: b | Z45: =LEN(C45)+LEN(D45)+LEN(E45)+LEN(F45)+LEN(G45)+LEN(H45)+LEN(J45)+LEN(K45)+LEN(L45)+LEN(M45) -> 48
A46: amm9759 | B46: 1907 | C46: Arizona & Sonora Gold Mining & Development Company. Cucurpe. | H46: arizona | I46: Arizona & Sonora Gold Mining & Development Company. Cucurpe. | Z46: =LEN(C46)+LEN(D46)+LEN(E46)+LEN(F46)+LEN(G46)+LEN(H46)+LEN(J46)+LEN(K46)+LEN(L46)+LEN(M46) -> 68
A47: amm10007 | B47: 1907 | C47: Ruby Gold & Copper Company. Ortiz. | I47: 50 men. | Z47: =LEN(C47)+LEN(D47)+LEN(E47)+LEN(F47)+LEN(G47)+LEN(H47)+LEN(J47)+LEN(K47)+LEN(L47)+LEN(M47) -> 34
A48: amm10012 | B48: 1907 | C48: San Bernardino Mining Company. Cananea. J. M. Gibbs, Mgr. Copper, Silver & Gold. Steam. 25 men. | H48: cananea | I48: San Bernardino Mining Company. Cananea. J. M. Gibbs, Mgr. Copper, Silver & Gold. Steam. 25 men. | J48: gibbon | K48: joseph | M48: Mgr | U48: b | W48: b | Z48: =LEN(C48)+LEN(D48)+LEN(E48)+LEN(F48)+LEN(G48)+LEN(H48)+LEN(J48)+LEN(K48)+LEN(L48)+LEN(M48) -> 118
A49: amm10165 | B49: 1907 | C49: Bote Mining Company. Zacatecas. | I49: Mills & 80 ton Cyanide Plant. 750 men. | N49: b | Z49: =LEN(C49)+LEN(D49)+LEN(E49)+LEN(F49)+LEN(G49)+LEN(H49)+LEN(J49)+LEN(K49)+LEN(L49)+LEN(M49) -> 31
A50: amm10426 | B50: 1907 | C50: Great Northern Mines Limited. Camborne and Poplar. | E50: Nelson | I50: Office, Nelson. B. C. W. F. Cochrane, Mgr.; Barkley Crilly, Supt. Oyster | J50: cochrave | K50: w | L50: f | M50: Mgr | U50: a | Y50: 1 | Z50: =LEN(C50)+LEN(D50)+LEN(E50)+LEN(F50)+LEN(G50)+LEN(H50)+LEN(J50)+LEN(K50)+LEN(L50)+LEN(M50) -> 69
A51: amm10612 | B51: 1907 | C51: (Canadian Consolidated Mines Limited.) James Cronin | I51: Moyie. | N51: b | Z51: =LEN(C51)+LEN(D51)+LEN(E51)+LEN(F51)+LEN(G51)+LEN(H51)+LEN(J51)+LEN(K51)+LEN(L51)+LEN(M51) -> 51
A52: amm11008 | B52: 1907 | C52: Thetford Chrome Company. | I52: Black Lake. | N52: b | Z52: =LEN(C52)+LEN(D52)+LEN(E52)+LEN(F52)+LEN(G52)+LEN(H52)+LEN(J52)+LEN(K52)+LEN(L52)+LEN(M52) -> 24
A53: amm11032 | B53: 1907 | C53: (American Smelting & Refining Company.) Office, Bymes Bdg., Denver. | I53: Franklin Guiterman, Gen. Mgr.; Frederick P. Bayles, Supt. Steam & | J53: guilford | K53: franklin | M53: Mgr | N53: b | U53: b | Z53: =LEN(C53)+LEN(D53)+LEN(E53)+LEN(F53)+LEN(G53)+LEN(H53)+LEN(J53)+LEN(K53)+LEN(L53)+LEN(M53) -> 86
A54: amm11047 | B54: 1907 | C54: Curtis Coal Mining Company. Colorado Springs. | H54: colorado | I54: Curtis Coal Mining Company. Colorado Springs. | Z54: =LEN(C54)+LEN(D54)+LEN(E54)+LEN(F54)+LEN(G54)+LEN(H54)+LEN(J54)+LEN(K54)+LEN(L54)+LEN(M54) -> 54
A55: amm11372 | B55: 1907 | C55: COAL MINES— NEW BRUNSWICK— NOVA SCOTIA. 229 | H55: new brunswick | I55: COAL MINES— NEW BRUNSWICK— NOVA SCOTIA. 229 | N55: b | S55: b | Z55: =LEN(C55)+LEN(D55)+LEN(E55)+LEN(F55)+LEN(G55)+LEN(H55)+LEN(J55)+LEN(K55)+LEN(L55)+LEN(M55) -> 57
A56: amm11459 | B56: 1911 | C56: BEATSON COPPER CO., LATOUCHE, ALASKA. B2. | I56: Andrew K. Beatson. Manager. Bonanza Mine. Copper-Silver. Open Cut | J56: beatson | K56: andrew | L56: k | M56: Manager | Z56: =LEN(C56)+LEN(D56)+LEN(E56)+LEN(F56)+LEN(G56)+LEN(H56)+LEN(J56)+LEN(K56)+LEN(L56)+LEN(M56) -> 62
A57: amm11779 | B57: 1911 | C57: AUGUSTA MINING CO., PATAGONIA, SANTA CRUZ COUNTY. D. | I57: William Kemp, Supt. Copper. Shaft. Steam and Air. 25 Men. | J57: kemble | K57: william | M57: Supt | U57: b | Z57: =LEN(C57)+LEN(D57)+LEN(E57)+LEN(F57)+LEN(G57)+LEN(H57)+LEN(J57)+LEN(K57)+LEN(L57)+LEN(M57) -> 69
A58: amm12353 | B58: 1911 | C58: McMILLEN STONEWALL MINING CO., GLOBE, GILA COUNTY. D. | I58: McMILLEN STONEWALL MINING CO., GLOBE, GILA COUNTY. D. | Z58: =LEN(C58)+LEN(D58)+LEN(E58)+LEN(F58)+LEN(G58)+LEN(H58)+LEN(J58)+LEN(K58)+LEN(L58)+LEN(M58) -> 53
A59: amm12653 | B59: 1911 | C59: SHATTUCK-ARIZONA COPPER CO., BISBEE, COCHISE COUNTY. C. | E59: Duluth, Minnesota | H59: duluth | I59: Office, Duluth, Minnesota. L. C. Shattuck, Manager. Copper. 900' Shaft. | J59: sharwood | K59: lemuel | L59: c | M59: Manager | U59: b | Z59: =LEN(C59)+LEN(D59)+LEN(E59)+LEN(F59)+LEN(G59)+LEN(H59)+LEN(J59)+LEN(K59)+LEN(L59)+LEN(M59) -> 101
A60: amm12815 | B60: 1911 | C60: VICTOR & BELL CROWN MINING CO., WENDEN, YUMA COUNTY. D. | I60: VICTOR & BELL CROWN MINING CO., WENDEN, YUMA COUNTY. D. | Z60: =LEN(C60)+LEN(D60)+LEN(E60)+LEN(F60)+LEN(G60)+LEN(H60)+LEN(J60)+LEN(K60)+LEN(L60)+LEN(M60) -> 55
A61: amm13051 | B61: 1911 | C61: BLUFF CITY MINING CO., QUINCY, PLUMAS CO. E. | H61: quincy | I61: BLUFF CITY MINING CO., QUINCY, PLUMAS CO. E. | Z61: =LEN(C61)+LEN(D61)+LEN(E61)+LEN(F61)+LEN(G61)+LEN(H61)+LEN(J61)+LEN(K61)+LEN(L61)+LEN(M61) -> 51
A62: amm13150 | B62: 1911 | C62: CALIFORNIA CONS. MINING CO., ROLLIN, SISKIYOU CO. B2. | I62: Laurel Group. Gold. Tunnels. Electricity and Air. 25 Men. | Z62: =LEN(C62)+LEN(D62)+LEN(E62)+LEN(F62)+LEN(G62)+LEN(H62)+LEN(J62)+LEN(K62)+LEN(L62)+LEN(M62) -> 53
A63: amm13512 | B63: 1911 | C63: FRESNO MAGNESITE CO., REEDLEY, FRESNO CO. B2. | H63: fresno | I63: FRESNO MAGNESITE CO., REEDLEY, FRESNO CO. B2. | Z63: =LEN(C63)+LEN(D63)+LEN(E63)+LEN(F63)+LEN(G63)+LEN(H63)+LEN(J63)+LEN(K63)+LEN(L63)+LEN(M63) -> 52
A64: amm14185 | B64: 1911 | C64: ORO GRANDE MINE, CARRVILLE, SISKIYOU CO. D. | I64: Strode Brothers, Owners. Gold. Tunnel. Water. 10 Stamps. 15 Men. | J64: brothers | K64: strode | M64: Owner | U64: b | V64: b | Z64: =LEN(C64)+LEN(D64)+LEN(E64)+LEN(F64)+LEN(G64)+LEN(H64)+LEN(J64)+LEN(K64)+LEN(L64)+LEN(M64) -> 62
A65: amm14522 | B65: 1911 | C65: SPANISH RIDGE MINING CO., WASHINGTON, NEVADA CO. D. | H65: washington | I65: SPANISH RIDGE MINING CO., WASHINGTON, NEVADA CO. D. | Z65: =LEN(C65)+LEN(D65)+LEN(E65)+LEN(F65)+LEN(G65)+LEN(H65)+LEN(J65)+LEN(K65)+LEN(L65)+LEN(M65) -> 62
A66: amm14632 | B66: 1911 | C66: TRINITY DREDGING & POWER CO., LEWISTON, TRINITY CO. D. | E66: Fay Bdg | I66: Office, 516 Fay Bdg , Los Angeles. H. E. Chesebro, Manager. Placer Gold | J66: cherry | K66: h | M66: Manager | U66: b | W66: b | Z66: =LEN(C66)+LEN(D66)+LEN(E66)+LEN(F66)+LEN(G66)+LEN(H66)+LEN(J66)+LEN(K66)+LEN(L66)+LEN(M66) -> 75
A67: amm14989 | B67: 1911 | C67: CALLIOPE MINING CO., OURAY, OURAY CO. B2 | I67: 129 | N67: b | Z67: =LEN(C67)+LEN(D67)+LEN(E67)+LEN(F67)+LEN(G67)+LEN(H67)+LEN(J67)+LEN(K67)+LEN(L67)+LEN(M67) -> 40
A68: amm15554 | B68: 1911 | C68: HUMMING BIRD M. & M. CO., IDAHO SPRINGS, CLEAR CREEK CO. D | H68: teller | I68: HUMPHREY & THOMPSON, BOX 851, CRIPPLE CREEK, TELLER CO. B. | N68: b | Z68: =LEN(C68)+LEN(D68)+LEN(E68)+LEN(F68)+LEN(G68)+LEN(H68)+LEN(J68)+LEN(K68)+LEN(L68)+LEN(M68) -> 65
A69: amm15685 | B69: 1911 | C69: LARIMORE GOLD MINING & MILLING CO., ELDORA, BOULDER CO. B2 | H69: sutton | I69: Isaac Sutton, Manager. Gold-Silver. Shafts. Steam and Air. Developing. | J69: sutton | K69: isaac | M69: Manager | S69: b | Z69: =LEN(C69)+LEN(D69)+LEN(E69)+LEN(F69)+LEN(G69)+LEN(H69)+LEN(J69)+LEN(K69)+LEN(L69)+LEN(M69) -> 83
A70: amm15737 | B70: 1911 | C70: LOWE (W. B.) MINING & MILLING CO., SILVERTON, SAN JUAN CO. X. | H70: yukon | I70: W. B. Lowe, Manager. Arpad and Yukon Groups. Lead-Silver-Gold-Copper. | J70: lowe | K70: w | M70: Manager | S70: b | W70: b | Z70: =LEN(C70)+LEN(D70)+LEN(E70)+LEN(F70)+LEN(G70)+LEN(H70)+LEN(J70)+LEN(K70)+LEN(L70)+LEN(M70) -> 79
A71: amm15939 | B71: 1911 | C71: O'REILLY GOLD MINING CO., BRECKENRIDGE, SUMMIT CO. B2 | H71: breckenridge | I71: O'REILLY GOLD MINING CO., BRECKENRIDGE, SUMMIT CO. B2 | Z71: =LEN(C71)+LEN(D71)+LEN(E71)+LEN(F71)+LEN(G71)+LEN(H71)+LEN(J71)+LEN(K71)+LEN(L71)+LEN(M71) -> 66
A72: amm16206 | B72: 1911 | C72: SOUND DEMOCRAT MINE, ANIMAS FORKS, SAN JUAN CO. B2 | I72: Terry Brothers & Smith, Operators; Joseph H Terry, Manager. Gold. | J72: terry | K72: joseph | M72: Manager | W72: b | Z72: =LEN(C72)+LEN(D72)+LEN(E72)+LEN(F72)+LEN(G72)+LEN(H72)+LEN(J72)+LEN(K72)+LEN(L72)+LEN(M72) -> 68
A73: amm16254 | B73: 1911 | C73: SUNNYSIDE MINES, EUREKA, SAN JUAN CO. B | H73: eureka | I73: SUNNYSIDE MINES, EUREKA, SAN JUAN CO. B | Z73: =LEN(C73)+LEN(D73)+LEN(E73)+LEN(F73)+LEN(G73)+LEN(H73)+LEN(J73)+LEN(K73)+LEN(L73)+LEN(M73) -> 46
A74: amm16490 | B74: 1911 | C74: ALICE MINING CO., MULLAN, SHOSHONE CO. B. | I74: ALICE MINING CO., MULLAN, SHOSHONE CO. B. | Z74: =LEN(C74)+LEN(D74)+LEN(E74)+LEN(F74)+LEN(G74)+LEN(H74)+LEN(J74)+LEN(K74)+LEN(L74)+LEN(M74) -> 41
A75: amm16561 | B75: 1911 | C75: BOISE BASIN HYDRAULIC A POWER CO, LIMITED, PLACERVILLE. A. | I75: Water. 20 Stamps. 25 Men. | N75: b | Z75: =LEN(C75)+LEN(D75)+LEN(E75)+LEN(F75)+LEN(G75)+LEN(H75)+LEN(J75)+LEN(K75)+LEN(L75)+LEN(M75) -> 58
A76: amm16678 | B76: 1911 | C76: GOLD POINT EXPLORATION & EXTRACTION CO., BLACKFOOT. G. | I76: S. V. Clevenger, Manager. Auriferous Sand. Gasolene. 25-ton Cyanide | J76: cleveland | K76: s | M76: Manager | W76: b | Z76: =LEN(C76)+LEN(D76)+LEN(E76)+LEN(F76)+LEN(G76)+LEN(H76)+LEN(J76)+LEN(K76)+LEN(L76)+LEN(M76) -> 71
A77: amm16726 | B77: 1911 | C77: IDAHO CHAMPION MINING & MILLING CO., ELK CITY, IDAHO CO. D. | I77: 1000' Tunnel. Steam and Air. 10 Stamps. 25-ton Concentrating Mill and | Z77: =LEN(C77)+LEN(D77)+LEN(E77)+LEN(F77)+LEN(G77)+LEN(H77)+LEN(J77)+LEN(K77)+LEN(L77)+LEN(M77) -> 59
A78: amm16754 | B78: 1911 | C78: IDAHO LEAD-SILVER MINING CO., OSBURN, SHOSHONE CO. B2. | I78: 150-ton Concentrating Mill. 50 Men. | Z78: =LEN(C78)+LEN(D78)+LEN(E78)+LEN(F78)+LEN(G78)+LEN(H78)+LEN(J78)+LEN(K78)+LEN(L78)+LEN(M78) -> 54
A79: amm17340 | B79: 1911 | C79: CALUMET & HECLA MINING CO., CALUMET, HOUGHTON CO. A. | I79: ger: Walter Fitch. General Supt.: W. A. Childs. Supt.; W. M Gibson. | J79: fiske | K79: walter | M79: General Manager | X79: b | Z79: =LEN(C79)+LEN(D79)+LEN(E79)+LEN(F79)+LEN(G79)+LEN(H79)+LEN(J79)+LEN(K79)+LEN(L79)+LEN(M79) -> 78
A80: amm17545 | B80: 1911 | C80: MINE LA MOTTE LEAD & SMELTING CO., MINE LA MOTTE. A. | I80: Supt. Lead-Nickel-Copper-Cobalt. Shafts. Steam and Air. 500-ton Con | Z80: =LEN(C80)+LEN(D80)+LEN(E80)+LEN(F80)+LEN(G80)+LEN(H80)+LEN(J80)+LEN(K80)+LEN(L80)+LEN(M80) -> 52
A81: amm18150 | B81: 1911 | C81: DEL MONTE GOLDFIELD MINING CO., LUNING, ESMERALDA CO. D. | I81: Tunnel. Gasolene and Air. 15 Men. | Z81: =LEN(C81)+LEN(D81)+LEN(E81)+LEN(F81)+LEN(G81)+LEN(H81)+LEN(J81)+LEN(K81)+LEN(L81)+LEN(M81) -> 56
A82: amm18348 | B82: 1911 | C82: MANHATTAN WAR EAGLE MINING & MILLING CO., MANHATTAN. B2. | I82: Walter Techow, Manager. Jumping Jack Mine. Gold. Shaft. Electricity | J82: tebbetts | K82: walter | M82: Manager | U82: b | Z82: =LEN(C82)+LEN(D82)+LEN(E82)+LEN(F82)+LEN(G82)+LEN(H82)+LEN(J82)+LEN(K82)+LEN(L82)+LEN(M82) -> 77
A83: amm18379 | B83: 1911 | C83: MONARCH MINES, WELLS, ELKO CO. B2. | I83: MONARCH MINES, WELLS, ELKO CO. B2. | Z83: =LEN(C83)+LEN(D83)+LEN(E83)+LEN(F83)+LEN(G83)+LEN(H83)+LEN(J83)+LEN(K83)+LEN(L83)+LEN(M83) -> 34
A84: amm18468 | B84: 1911 | C84: NINETY-NINE COPPER CO., GOOD SPRINGS, CLARK CO. D. | I84: J. B. Jenson, Supt. Ninety-Nine and Sultana Mines. Copper-Lea i-Zir.c. | J84: jennings | K84: j | L84: c | M84: Supt | W84: b | Z84: =LEN(C84)+LEN(D84)+LEN(E84)+LEN(F84)+LEN(G84)+LEN(H84)+LEN(J84)+LEN(K84)+LEN(L84)+LEN(M84) -> 64
A85: amm18981 | B85: 1911 | C85: YOUNG AMERICA MINE, MAGDALENA, SOCORRO CO. D. | I85: trolytic Copper Refinery. Steam, Electricity and Air. 200 Men. | N85: b | Z85: =LEN(C85)+LEN(D85)+LEN(E85)+LEN(F85)+LEN(G85)+LEN(H85)+LEN(J85)+LEN(K85)+LEN(L85)+LEN(M85) -> 45
A86: amm19350 | B86: 1911 | C86: TENNESSEE COPPER CO., COPPER HILL, POLK CO. A. | E86: Broadway, New York | H86: broadway | I86: Office, 11 Broadway, New York. Nathaniel H. Emmons. Manager. Burra | J86: emil | K86: nathaniel | L86: h | M86: Manager | U86: b | Z86: =LEN(C86)+LEN(D86)+LEN(E86)+LEN(F86)+LEN(G86)+LEN(H86)+LEN(J86)+LEN(K86)+LEN(L86)+LEN(M86) -> 94
A87: amm19424 | B87: 1911 | C87: BINGHAM MINES CO., BINGHAM, SALT LAKE CO. A. | H87: bingham | I87: BINGHAM MINES CO., BINGHAM, SALT LAKE CO. A. | Z87: =LEN(C87)+LEN(D87)+LEN(E87)+LEN(F87)+LEN(G87)+LEN(H87)+LEN(J87)+LEN(K87)+LEN(L87)+LEN(M87) -> 52
A88: amm19436 | B88: 1911 | C88: BINGHAM WEST DIP TUNNEL CO., BINGHAM, SALT LAKE CO. G. | H88: bingham | I88: BINGHAM WEST DIP TUNNEL CO., BINGHAM, SALT LAKE CO. G. | Z88: =LEN(C88)+LEN(D88)+LEN(E88)+LEN(F88)+LEN(G88)+LEN(H88)+LEN(J88)+LEN(K88)+LEN(L88)+LEN(M88) -> 62
A89: amm19550 | B89: 1911 | C89: DRAGON MINING CO., SILVER CITY, JUAB CO. B2. | E89: Provo | I89: Office, Provo. L. E. Riter, Jr., Manager; E. E. Gardiner, Supt. Iron. Shaft- | J89: ritchie | K89: l | M89: Manager | P89: b | U89: b | W89: b | Z89: =LEN(C89)+LEN(D89)+LEN(E89)+LEN(F89)+LEN(G89)+LEN(H89)+LEN(J89)+LEN(K89)+LEN(L89)+LEN(M89) -> 64
A90: amm19708 | B90: 1911 | C90: Mckinlsy mining co., sursxa, juab co. g. | I90: W. D. Myers, Manager. Silver-Lead-Gold. Shaft. Electricity and Air. | J90: mwwfecwfkny | K90: w | L90: d | M90: Manager | N90: a | U90: a | Y90: 30 | Z90: =LEN(C90)+LEN(D90)+LEN(E90)+LEN(F90)+LEN(G90)+LEN(H90)+LEN(J90)+LEN(K90)+LEN(L90)+LEN(M90) -> 60
A91: amm19836 | B91: 1911 | C91: SELMA MINES CO., KNIGHTVILLE, JUAB CO. D. | I91: SELMA MINES CO., KNIGHTVILLE, JUAB CO. D. | Z91: =LEN(C91)+LEN(D91)+LEN(E91)+LEN(F91)+LEN(G91)+LEN(H91)+LEN(J91)+LEN(K91)+LEN(L91)+LEN(M91) -> 41
A92: amm19983 | B92: 1911 | C92: Consolidated Groups. Copper. Open Cuts and Tunnels. Steam Shovels. | H92: boston | I92: Frank G. Janney, General Supt. Boston Mill. 312 Stamps and 3000-ton | J92: jancu | K92: frank | L92: g | M92: General Supt | N92: b | U92: b | Z92: =LEN(C92)+LEN(D92)+LEN(E92)+LEN(F92)+LEN(G92)+LEN(H92)+LEN(J92)+LEN(K92)+LEN(L92)+LEN(M92) -> 96
A93: amm20629 | B93: 1911 | C93: RAMON CARONA MINING CO., NAICA. B2. | I93: George Stimson. Supt. Silver-Lead-Copper. Shaft. Gasolene. 50 Men. | J93: stimpson | K93: george | M93: Supt | U93: a | Y93: 1 | Z93: =LEN(C93)+LEN(D93)+LEN(E93)+LEN(F93)+LEN(G93)+LEN(H93)+LEN(J93)+LEN(K93)+LEN(L93)+LEN(M93) -> 53
A94: amm20699 | B94: 1911 | C94: SANTO DOMINGO PLACER MINING CO., CHIHUAHUA. B2. | I94: Robert Bruce, Manager. Auriferous Gravel. Steam and Air. 150 Men. | J94: bruce | K94: robert | L94: e | M94: Manager | W94: b | Z94: =LEN(C94)+LEN(D94)+LEN(E94)+LEN(F94)+LEN(G94)+LEN(H94)+LEN(J94)+LEN(K94)+LEN(L94)+LEN(M94) -> 66
A95: amm21009 | B95: 1911 | C95: GUADALUPE CONSOLIDATED MINING CO., INDE. B. | I95: and Air. 4 Bryan Mills and 100-ton Cyanide Plant. 150 Men. | Z95: =LEN(C95)+LEN(D95)+LEN(E95)+LEN(F95)+LEN(G95)+LEN(H95)+LEN(J95)+LEN(K95)+LEN(L95)+LEN(M95) -> 43
A96: amm21227 | B96: 1911 | C96: AUGUSTIAS MINING CO., POZOS. A. | I96: Mills and 200-ton Cyanide Plant. 250 Men. | Z96: =LEN(C96)+LEN(D96)+LEN(E96)+LEN(F96)+LEN(G96)+LEN(H96)+LEN(J96)+LEN(K96)+LEN(L96)+LEN(M96) -> 31
A97: amm21464 | B97: 1911 | C97: SAN FELIPE MINING CO., COYUCA. B2. | I97: Shafts. Steam. 5 Stamps. 50 Men. | Z97: =LEN(C97)+LEN(D97)+LEN(E97)+LEN(F97)+LEN(G97)+LEN(H97)+LEN(J97)+LEN(K97)+LEN(L97)+LEN(M97) -> 34
A98: amm21694 | B98: 1911 | C98: LOS REYES MINING CO., LOS REYES. A. | I98: Director; Arthur F. Flynt, Manager; Alexander M. Grimm, Mine Supt.; | J98: fluhr | K98: arthur | M98: Manager | U98: b | W98: b | Z98: =LEN(C98)+LEN(D98)+LEN(E98)+LEN(F98)+LEN(G98)+LEN(H98)+LEN(J98)+LEN(K98)+LEN(L98)+LEN(M98) -> 53
A99: amm22389 | B99: 1911 | C99: CONTRA ESTACA CONS. MEXICAN MINING CO., CONTRA ESTACA. A. | I99: ger; Dwight B. Boyden, Supt. Contra Estaca and El Pilar Mines. Gold- | J99: boyd | K99: dwight | M99: Manager | U99: b | W99: b | X99: b | Z99: =LEN(C99)+LEN(D99)+LEN(E99)+LEN(F99)+LEN(G99)+LEN(H99)+LEN(J99)+LEN(K99)+LEN(L99)+LEN(M99) -> 74
A100: amm22804 | B100: 1911 | C100: MULATOS MINING CO., MULATOS. B2. | I100: MULATOS MINING CO., MULATOS. B2. | Z100: =LEN(C100)+LEN(D100)+LEN(E100)+LEN(F100)+LEN(G100)+LEN(H100)+LEN(J100)+LEN(K100)+LEN(L100)+LEN(M100) -> 32
...

Sheet mmmt
A1: id | B1: year | C1: text | D1: company | E1: capital | F1: minerals | G1: owns | H1: owned | I1: doutput | J1: technology | K1: incor | L1: loc | M1: lastname | N1: firstname | O1: middlename | P1: prof | Q1: company | R1: capital | S1: minerals | T1: owns | U1: owned | V1: doutput | W1: technology | X1: incor | Y1: loc | Z1: text | AA1: lastname | AB1: firstname | AC1: middlename | AD1: prof | AE1: cer | AF1: tot | AH1: extracted/actual | AI1: positive | AJ1: negative
A2: mmm5 | B2: 1926 | C2: po, asientso ags, | D2: aguascalientes metal co. | L2: asientso ags | Y2: a | AE2: 1 | AF2: =LEN(D2)+LEN(E2)+LEN(F2)+LEN(G2)+LEN(H2)+LEN(I2)+LEN(J2)+LEN(K2)+LEN(L2)+LEN(M2)+LEN(N2)+LEN(O2)+LEN(P2) -> 36 | AH2: positive | AI2: t | AJ2: f
A3: mmm15 | B3: 1926 | C3: 200000 | D3: cia min la fortuna sa | E3: 96665.056 | L3: aguascalientes | AF3: =LEN(D3)+LEN(E3)+LEN(F3)+LEN(G3)+LEN(H3)+LEN(I3)+LEN(J3)+LEN(K3)+LEN(L3)+LEN(M3)+LEN(N3)+LEN(O3)+LEN(P3) -> 45 | AH3: negative | AI3: f | AJ3: t
A4: mmm21 | B4: 1926 | C4: 212 725 | D4: compania minera san geronimo sa | L4: aguascalientes | R4: b | AF4: =LEN(D4)+LEN(E4)+LEN(F4)+LEN(G4)+LEN(H4)+LEN(I4)+LEN(J4)+LEN(K4)+LEN(L4)+LEN(M4)+LEN(N4)+LEN(O4)+LEN(P4) -> 45
A5: mmm24 | B5: 1926 | C5: copper silver | D5: compania minera san geronimo sa | F5: copper silver | L5: aguascalientes | AF5: =LEN(D5)+LEN(E5)+LEN(F5)+LEN(G5)+LEN(H5)+LEN(I5)+LEN(J5)+LEN(K5)+LEN(L5)+LEN(M5)+LEN(N5)+LEN(O5)+LEN(P5) -> 58 | AH5: code
A6: mmm31 | B6: 1926 | C6: location& po, asientos, ags, | D6: compania min socorro y an sa | L6: asientos ags | AF6: =LEN(D6)+LEN(E6)+LEN(F6)+LEN(G6)+LEN(H6)+LEN(I6)+LEN(J6)+LEN(K6)+LEN(L6)+LEN(M6)+LEN(N6)+LEN(O6)+LEN(P6) -> 40 | AH6: extracted/actual | AI6: positive | AJ6: negative
A7: mmm33 | B7: 1926 | C7: 2800 | D7: compania min socorro y an sa | E7: 1353.3108 | L7: aguascalientes | Q7: b | AF7: =LEN(D7)+LEN(E7)+LEN(F7)+LEN(G7)+LEN(H7)+LEN(I7)+LEN(J7)+LEN(K7)+LEN(L7)+LEN(M7)+LEN(N7)+LEN(O7)+LEN(P7) -> 54 | AH7: positive | AJ7: f
A8: mmm42 | B8: 1926 | C8: daily out put, 300 metric tons., | D8: minerva mining co. s. a. | I8: 300 metric tons. | L8: aguascalientes | AF8: =LEN(D8)+LEN(E8)+LEN(F8)+LEN(G8)+LEN(H8)+LEN(I8)+LEN(J8)+LEN(K8)+LEN(L8)+LEN(M8)+LEN(N8)+LEN(O8)+LEN(P8) -> 54 | AH8: negative | AI8: f
A9: mmm50 | B9: 1926 | C9: spt of power, .j. kaufer, asientos, ags. | D9: minerva mining co. s. a. | L9: asientos ags | M9: kasper | P9: spt of power | AA9: b | AB9: b | AF9: =LEN(D9)+LEN(E9)+LEN(F9)+LEN(G9)+LEN(H9)+LEN(I9)+LEN(J9)+LEN(K9)+LEN(L9)+LEN(M9)+LEN(N9)+LEN(O9)+LEN(P9) -> 54
A10: mmm56 | B10: 1926 | C10: mexico city office, a.venida capuchinas 44, manager., mr l majar | D10: compañia del boleo | L10: mr l majar | Y10: b | AA10: b | AB10: b | AD10: b | AF10: =LEN(D10)+LEN(E10)+LEN(F10)+LEN(G10)+LEN(H10)+LEN(I10)+LEN(J10)+LEN(K10)+LEN(L10)+LEN(M10)+LEN(N10)+LEN(O10)+LEN(P10) -> 28 | AH10: types of mistakes on true positives
A11: mmm57 | B11: 1926 | C11: copper | D11: compañia del boleo | F11: copper | L11: baja california. | AF11: =LEN(D11)+LEN(E11)+LEN(F11)+LEN(G11)+LEN(H11)+LEN(I11)+LEN(J11)+LEN(K11)+LEN(L11)+LEN(M11)+LEN(N11)+LEN(O11)+LEN(P11) -> 40 | AH11: no mistake
A12: mmm61 | B12: 1926 | C12: refining plant location, sta. rosalia, b · c ·, | D12: compañia del boleo | L12: sta rosalia bc | AF12: =LEN(D12)+LEN(E12)+LEN(F12)+LEN(G12)+LEN(H12)+LEN(I12)+LEN(J12)+LEN(K12)+LEN(L12)+LEN(M12)+LEN(N12)+LEN(O12)+LEN(P12) -> 32 | AH12: source to text | AI12: a
A13: mmm61 | B13: 1926 | C13: refining plant location, sta. rosalia, b · c ·, | D13: compañia del boleo | L13: sta rosalia bc | AF13: =LEN(D13)+LEN(E13)+LEN(F13)+LEN(G13)+LEN(H13)+LEN(I13)+LEN(J13)+LEN(K13)+LEN(L13)+LEN(M13)+LEN(N13)+LEN(O13)+LEN(P13) -> 32 | AH13: text to source | AI13: b
A14: mmm68 | B14: 1926 | C14: ming. Eng., .j. cazanove., sta. ro salia, b. c. | D14: compañia del boleo | L14: ro salia bc | Y14: a | AA14: b | AB14: b | AD14: b | AE14: 1 | AF14: =LEN(D14)+LEN(E14)+LEN(F14)+LEN(G14)+LEN(H14)+LEN(I14)+LEN(J14)+LEN(K14)+LEN(L14)+LEN(M14)+LEN(N14)+LEN(O14)+LEN(P14) -> 29
A15: mmm75 | B15: 1926 | C15: foreign office, 40 w. congress st. tucson, ariz., | D15: cia y reduccion del golfo s. a. | L15: st tucson ariz | AF15: =LEN(D15)+LEN(E15)+LEN(F15)+LEN(G15)+LEN(H15)+LEN(I15)+LEN(J15)+LEN(K15)+LEN(L15)+LEN(M15)+LEN(N15)+LEN(O15)+LEN(P15) -> 45
A16: mmm76 | B16: 1926 | C16: silver gold arsenic. | D16: cia y reduccion del golfo s. a. | F16: silver gold arsenic. | L16: baja california. | AF16: =LEN(D16)+LEN(E16)+LEN(F16)+LEN(G16)+LEN(H16)+LEN(I16)+LEN(J16)+LEN(K16)+LEN(L16)+LEN(M16)+LEN(N16)+LEN(O16)+LEN(P16) -> 67
A17: mmm78 | B17: 1926 | C17: grl. spt., geo. w. pickett, san antonio, b. c. | D17: cia y reduccion del golfo s. a. | L17: san antonio bc | M17: pickard | N17: geo | P17: grl. spt. | AA17: b | AC17: b | AF17: =LEN(D17)+LEN(E17)+LEN(F17)+LEN(G17)+LEN(H17)+LEN(I17)+LEN(J17)+LEN(K17)+LEN(L17)+LEN(M17)+LEN(N17)+LEN(O17)+LEN(P17) -> 64
A18: mmm84 | B18: 1926 | C18: lead zinc silver. | D18: calera mining co. | F18: lead zinc silver. | L18: chihuahua | AF18: =LEN(D18)+LEN(E18)+LEN(F18)+LEN(G18)+LEN(H18)+LEN(I18)+LEN(J18)+LEN(K18)+LEN(L18)+LEN(M18)+LEN(N18)+LEN(O18)+LEN(P18) -> 43
A19: mmm84 | B19: 1926 | C19: lead zinc silver. | D19: calera mining co. | F19: lead zinc silver. | L19: chihuahua | AF19: =LEN(D19)+LEN(E19)+LEN(F19)+LEN(G19)+LEN(H19)+LEN(I19)+LEN(J19)+LEN(K19)+LEN(L19)+LEN(M19)+LEN(N19)+LEN(O19)+LEN(P19) -> 43
A20: mmm91 | B20: 1926 | C20: asst. grl. mgr., e. s. plumb, chihuahua, chih. | D20: calera mining co. | L20: chihuahua chih | M20: plews | N20: edwanl | P20: asst. grl. mgr. | AA20: b | AC20: b | AF20: =LEN(D20)+LEN(E20)+LEN(F20)+LEN(G20)+LEN(H20)+LEN(I20)+LEN(J20)+LEN(K20)+LEN(L20)+LEN(M20)+LEN(N20)+LEN(O20)+LEN(P20) -> 57
A21: mmm100 | B21: 1926 | C21: location, & p. o., chihuahua, chih. | D21: cia . minera alianza | L21: chihuahua chih | AF21: =LEN(D21)+LEN(E21)+LEN(F21)+LEN(G21)+LEN(H21)+LEN(I21)+LEN(J21)+LEN(K21)+LEN(L21)+LEN(M21)+LEN(N21)+LEN(O21)+LEN(P21) -> 34
A22: mmm102 | B22: 1926 | C22: manager, a. l. kraft, chihuahua, chih. | D22: cia . minera alianza | L22: chihuahua chih | M22: kothsctaild | N22: a | O22: h | P22: manager | AA22: b | AC22: b | AF22: =LEN(D22)+LEN(E22)+LEN(F22)+LEN(G22)+LEN(H22)+LEN(I22)+LEN(J22)+LEN(K22)+LEN(L22)+LEN(M22)+LEN(N22)+LEN(O22)+LEN(P22) -> 54
A23: mmm108 | B23: 1926 | C23: owners, the prieto estate., | D23: cia. Minera astreas y otros | L23: chihuahua | AF23: =LEN(D23)+LEN(E23)+LEN(F23)+LEN(G23)+LEN(H23)+LEN(I23)+LEN(J23)+LEN(K23)+LEN(L23)+LEN(M23)+LEN(N23)+LEN(O23)+LEN(P23) -> 36
A24: mmm116 | B24: 1926 | C24: cyanidation., | D24: cia. Minera cienega sa | J24: cyanidation. | L24: chihuahua | AF24: =LEN(D24)+LEN(E24)+LEN(F24)+LEN(G24)+LEN(H24)+LEN(I24)+LEN(J24)+LEN(K24)+LEN(L24)+LEN(M24)+LEN(N24)+LEN(O24)+LEN(P24) -> 43
A25: mmm117 | B25: 1926 | C25: daily output, 50 metric tons., | D25: cia. Minera cienega sa | I25: 50 metric tons. | L25: chihuahua | AF25: =LEN(D25)+LEN(E25)+LEN(F25)+LEN(G25)+LEN(H25)+LEN(I25)+LEN(J25)+LEN(K25)+LEN(L25)+LEN(M25)+LEN(N25)+LEN(O25)+LEN(P25) -> 46
A26: mmm120 | B26: 1926 | C26: purch. agt., clyde harding, el paso, texas. | D26: cia. Minera cienega sa | L26: el paso texas | M26: hardenbergh | N26: clyde | P26: purch. agt. | AA26: b | AF26: =LEN(D26)+LEN(E26)+LEN(F26)+LEN(G26)+LEN(H26)+LEN(I26)+LEN(J26)+LEN(K26)+LEN(L26)+LEN(M26)+LEN(N26)+LEN(O26)+LEN(P26) -> 62
A27: mmm124 | B27: 1926 | C27: this company owns the leponte y an. mines. | D27: cia. minera de naica | G27: this company owns the leponte y an. mines. | L27: chihuahua | AF27: =LEN(D27)+LEN(E27)+LEN(F27)+LEN(G27)+LEN(H27)+LEN(I27)+LEN(J27)+LEN(K27)+LEN(L27)+LEN(M27)+LEN(N27)+LEN(O27)+LEN(P27) -> 71
A28: mmm147 | B28: 1926 | C28: foreign office, warren, ariz., | D28: cia . min . erupcion y an. s. a. | L28: office warren ariz | Y28: b | AF28: =LEN(D28)+LEN(E28)+LEN(F28)+LEN(G28)+LEN(H28)+LEN(I28)+LEN(J28)+LEN(K28)+LEN(L28)+LEN(M28)+LEN(N28)+LEN(O28)+LEN(P28) -> 50
A29: mmm148 | B29: 1926 | C29: lead silver. | D29: cia . min . erupcion y an. s. a. | F29: lead silver. | L29: chihuahua | AF29: =LEN(D29)+LEN(E29)+LEN(F29)+LEN(G29)+LEN(H29)+LEN(I29)+LEN(J29)+LEN(K29)+LEN(L29)+LEN(M29)+LEN(N29)+LEN(O29)+LEN(P29) -> 53
A30: mmm148 | B30: 1926 | C30: this company is subsidiary of ahumada lead co. | D30: cia . min . erupcion y an. s. a. | G30: this company is subsidiary of ahumada lead co. | L30: chihuahua | T30: b | U30: b | AF30: =LEN(D30)+LEN(E30)+LEN(F30)+LEN(G30)+LEN(H30)+LEN(I30)+LEN(J30)+LEN(K30)+LEN(L30)+LEN(M30)+LEN(N30)+LEN(O30)+LEN(P30) -> 87
A31: mmm151 | B31: 1926 | C31: purch. Agt., john b. rawlings, 315 two republics bdg., el paso. texas. | D31: cia . min . erupcion y an. s. a. | L31: el paso texas | M31: raub | N31: john | P31: purch. Agt. | AA31: b | AC31: b | AF31: =LEN(D31)+LEN(E31)+LEN(F31)+LEN(G31)+LEN(H31)+LEN(I31)+LEN(J31)+LEN(K31)+LEN(L31)+LEN(M31)+LEN(N31)+LEN(O31)+LEN(P31) -> 64
A32: mmm155 | B32: 1926 | C32: manager, jose bovio, chihuahua, chih | D32: cia. min. la sorpresa y an. s. a. | L32: chihuahua chih | M32: bovill | N32: jose | P32: manager | AA32: b | AF32: =LEN(D32)+LEN(E32)+LEN(F32)+LEN(G32)+LEN(H32)+LEN(I32)+LEN(J32)+LEN(K32)+LEN(L32)+LEN(M32)+LEN(N32)+LEN(O32)+LEN(P32) -> 64
A33: mmm158 | B33: 1926 | C33: manager, j. c. shepard, chihuahua, chih. | D33: cia. min. mexicana de la cieneguilla | L33: chihuahua chih | M33: shepard | N33: j | P33: manager | AC33: b | AF33: =LEN(D33)+LEN(E33)+LEN(F33)+LEN(G33)+LEN(H33)+LEN(I33)+LEN(J33)+LEN(K33)+LEN(L33)+LEN(M33)+LEN(N33)+LEN(O33)+LEN(P33) -> 65
A34: mmm161 | B34: 1926 | C34: this conmpany owns the san pascual mines . | D34: cia. Min. san pascual de las adargas s. a. | G34: this conmpany owns the san pascual mines . | L34: chihuahua | AF34: =LEN(D34)+LEN(E34)+LEN(F34)+LEN(G34)+LEN(H34)+LEN(I34)+LEN(J34)+LEN(K34)+LEN(L34)+LEN(M34)+LEN(N34)+LEN(O34)+LEN(P34) -> 93
A35: mmm161 | B35: 1926 | C35: lead silver gold. | D35: cia. Min. san pascual de las adargas s. a. | F35: lead silver gold. | L35: chihuahua | AF35: =LEN(D35)+LEN(E35)+LEN(F35)+LEN(G35)+LEN(H35)+LEN(I35)+LEN(J35)+LEN(K35)+LEN(L35)+LEN(M35)+LEN(N35)+LEN(O35)+LEN(P35) -> 68
A36: mmm161 | B36: 1926 | C36: this conmpany owns the san pascual mines . | D36: cia. Min. san pascual de las adargas s. a. | G36: this conmpany owns the san pascual mines . | L36: chihuahua | AF36: =LEN(D36)+LEN(E36)+LEN(F36)+LEN(G36)+LEN(H36)+LEN(I36)+LEN(J36)+LEN(K36)+LEN(L36)+LEN(M36)+LEN(N36)+LEN(O36)+LEN(P36) -> 93
A37: mmm172 | B37: 1926 | C37: gold silver. | D37: dolores mines co. | F37: gold silver. | L37: chihuahua | AF37: =LEN(D37)+LEN(E37)+LEN(F37)+LEN(G37)+LEN(H37)+LEN(I37)+LEN(J37)+LEN(K37)+LEN(L37)+LEN(M37)+LEN(N37)+LEN(O37)+LEN(P37) -> 38
A38: mmm174 | B38: 1926 | C38: daily output, 200 metric tons, | D38: dolores mines co. | I38: 200 metric tons | L38: chihuahua | AF38: =LEN(D38)+LEN(E38)+LEN(F38)+LEN(G38)+LEN(H38)+LEN(I38)+LEN(J38)+LEN(K38)+LEN(L38)+LEN(M38)+LEN(N38)+LEN(O38)+LEN(P38) -> 41
A39: mmm177 | B39: 1926 | C39: grl. Mgr., f. m. estes, la dura, son. | D39: dolores mines co. | L39: la dura son | M39: estates | N39: francis | P39: grl. Mgr. | AA39: b | AC39: b | AF39: =LEN(D39)+LEN(E39)+LEN(F39)+LEN(G39)+LEN(H39)+LEN(I39)+LEN(J39)+LEN(K39)+LEN(L39)+LEN(M39)+LEN(N39)+LEN(O39)+LEN(P39) -> 51
A40: mmm186 | B40: 1926 | C40: foreign office, 780 fifth ave. new york, | D40: el potosi mining co. | L40: ave new york | Y40: b | AF40: =LEN(D40)+LEN(E40)+LEN(F40)+LEN(G40)+LEN(H40)+LEN(I40)+LEN(J40)+LEN(K40)+LEN(L40)+LEN(M40)+LEN(N40)+LEN(O40)+LEN(P40) -> 32
A41: mmm192 | B41: 1926 | C41: secr., w. j. walworth, new york., | D41: el potosi mining co. | L41: new york | M41: walworth | N41: w | P41: secr. | AC41: b | AF41: =LEN(D41)+LEN(E41)+LEN(F41)+LEN(G41)+LEN(H41)+LEN(I41)+LEN(J41)+LEN(K41)+LEN(L41)+LEN(M41)+LEN(N41)+LEN(O41)+LEN(P41) -> 42
A42: mmm197 | B42: 1926 | C42: chairman, e. b. schley, new york., | D42: el potosi mining co. | L42: new york | M42: schlesinger | N42: evander | P42: chairman | AA42: b | AC42: b | AF42: =LEN(D42)+LEN(E42)+LEN(F42)+LEN(G42)+LEN(H42)+LEN(I42)+LEN(J42)+LEN(K42)+LEN(L42)+LEN(M42)+LEN(N42)+LEN(O42)+LEN(P42) -> 54
A43: mmm199 | B43: 1926 | C43: superintendent, h. a. walker., chihuahua, chih. | D43: el potosi mining co. | L43: chihuahua chih | AA43: b | AB43: b | AC43: b | AD43: b | AF43: =LEN(D43)+LEN(E43)+LEN(F43)+LEN(G43)+LEN(H43)+LEN(I43)+LEN(J43)+LEN(K43)+LEN(L43)+LEN(M43)+LEN(N43)+LEN(O43)+LEN(P43) -> 34
A44: mmm209 | B44: 1926 | C44: owners, Dale Brothers,, chihuahua, chih. | D44: inglaterra mining co. | L44: chihuahua chih | AF44: =LEN(D44)+LEN(E44)+LEN(F44)+LEN(G44)+LEN(H44)+LEN(I44)+LEN(J44)+LEN(K44)+LEN(L44)+LEN(M44)+LEN(N44)+LEN(O44)+LEN(P44) -> 35
A45: mmm211 | B45: 1926 | C45: location, santa barbara., chih., | D45: moctezuma lead company | L45: santa barbara chih | AF45: =LEN(D45)+LEN(E45)+LEN(F45)+LEN(G45)+LEN(H45)+LEN(I45)+LEN(J45)+LEN(K45)+LEN(L45)+LEN(M45)+LEN(N45)+LEN(O45)+LEN(P45) -> 40
A46: mmm220 | B46: 1926 | C46: daily output, 300 metric tons, | D46: palmarejo & mexican gold fields ltd. | I46: 300 metric tons | L46: chihuahua | AF46: =LEN(D46)+LEN(E46)+LEN(F46)+LEN(G46)+LEN(H46)+LEN(I46)+LEN(J46)+LEN(K46)+LEN(L46)+LEN(M46)+LEN(N46)+LEN(O46)+LEN(P46) -> 60
A47: mmm228 | B47: 1926 | C47: organized, in 1906 in arizona., | D47: rio plata mining co. | K47: organized, in 1906 in arizona., | L47: chihuahua | AF47: =LEN(D47)+LEN(E47)+LEN(F47)+LEN(G47)+LEN(H47)+LEN(I47)+LEN(J47)+LEN(K47)+LEN(L47)+LEN(M47)+LEN(N47)+LEN(O47)+LEN(P47) -> 61
A48: mmm230 | B48: 1926 | C48: location, río plata, chih., | D48: rio plata mining co. | L48: río plata chih | AF48: =LEN(D48)+LEN(E48)+LEN(F48)+LEN(G48)+LEN(H48)+LEN(I48)+LEN(J48)+LEN(K48)+LEN(L48)+LEN(M48)+LEN(N48)+LEN(O48)+LEN(P48) -> 34
A49: mmm231 | B49: 1926 | C49: p. o., guazapares, chih., | D49: rio plata mining co. | L49: o guazapares chih | Y49: b | AF49: =LEN(D49)+LEN(E49)+LEN(F49)+LEN(G49)+LEN(H49)+LEN(I49)+LEN(J49)+LEN(K49)+LEN(L49)+LEN(M49)+LEN(N49)+LEN(O49)+LEN(P49) -> 37
A50: mmm232 | B50: 1926 | C50: silver gold | D50: rio plata mining co. | F50: silver gold | L50: chihuahua | AF50: =LEN(D50)+LEN(E50)+LEN(F50)+LEN(G50)+LEN(H50)+LEN(I50)+LEN(J50)+LEN(K50)+LEN(L50)+LEN(M50)+LEN(N50)+LEN(O50)+LEN(P50) -> 40
A51: mmm249 | B51: 1926 | C51: mill. spt., glen. l. allen, parral, chih. | D51: san francisco mines of mexico ltd | L51: parral chih | M51: allen | N51: glen | O51: boyce | P51: mill. spt. | AC51: b | AF51: =LEN(D51)+LEN(E51)+LEN(F51)+LEN(G51)+LEN(H51)+LEN(I51)+LEN(J51)+LEN(K51)+LEN(L51)+LEN(M51)+LEN(N51)+LEN(O51)+LEN(P51) -> 68
A52: mmm250 | B52: 1926 | C52: mech. eng., w . g . savage, parral, chih. | D52: san francisco mines of mexico ltd | L52: parral chih | M52: saup | N52: w | O52: c | P52: mech. eng. | AA52: b | AC52: b | AF52: =LEN(D52)+LEN(E52)+LEN(F52)+LEN(G52)+LEN(H52)+LEN(I52)+LEN(J52)+LEN(K52)+LEN(L52)+LEN(M52)+LEN(N52)+LEN(O52)+LEN(P52) -> 60
A53: mmm252 | B53: 1926 | C53: struct. steel foreman, henry weithaus, | D53: san francisco mines of mexico ltd | L53: chihuahua | M53: weiss | N53: henry | P53: struct. steel foreman | AA53: b | AF53: =LEN(D53)+LEN(E53)+LEN(F53)+LEN(G53)+LEN(H53)+LEN(I53)+LEN(J53)+LEN(K53)+LEN(L53)+LEN(M53)+LEN(N53)+LEN(O53)+LEN(P53) -> 73
A54: mmm256 | B54: 1926 | C54: $7. 000,000 u. s. c. | D54: san toy mining co. | L54: chihuahua | R54: b | AF54: =LEN(D54)+LEN(E54)+LEN(F54)+LEN(G54)+LEN(H54)+LEN(I54)+LEN(J54)+LEN(K54)+LEN(L54)+LEN(M54)+LEN(N54)+LEN(O54)+LEN(P54) -> 27
A55: mmm257 | B55: 1926 | C55: the company owns the juarez la central, la fotuna, independencia & bustillos mines. | D55: san toy mining co. | G55: the company owns the juarez la central, la fotuna, independencia & bustillos mines. | L55: chihuahua | AF55: =LEN(D55)+LEN(E55)+LEN(F55)+LEN(G55)+LEN(H55)+LEN(I55)+LEN(J55)+LEN(K55)+LEN(L55)+LEN(M55)+LEN(N55)+LEN(O55)+LEN(P55) -> 110
A56: mmm261 | B56: 1926 | C56: location & p. o., batopilas, chih., | D56: the batopilas mining co. | L56: batopilas chih | AF56: =LEN(D56)+LEN(E56)+LEN(F56)+LEN(G56)+LEN(H56)+LEN(I56)+LEN(J56)+LEN(K56)+LEN(L56)+LEN(M56)+LEN(N56)+LEN(O56)+LEN(P56) -> 38
A57: mmm274 | B57: 1926 | C57: location, sta. domingo, near sta. eulalia, chih. | D57: the buena tierra mining co. ltd | L57: sta eulalia chih | AF57: =LEN(D57)+LEN(E57)+LEN(F57)+LEN(G57)+LEN(H57)+LEN(I57)+LEN(J57)+LEN(K57)+LEN(L57)+LEN(M57)+LEN(N57)+LEN(O57)+LEN(P57) -> 47
A58: mmm288 | B58: 1926 | C58: grl. mgr., a . p. cortelyou., | D58: the concheño mining co. | L58: chihuahua | AA58: b | AB58: b | AC58: b | AD58: b | AF58: =LEN(D58)+LEN(E58)+LEN(F58)+LEN(G58)+LEN(H58)+LEN(I58)+LEN(J58)+LEN(K58)+LEN(L58)+LEN(M58)+LEN(N58)+LEN(O58)+LEN(P58) -> 32
A59: mmm291 | B59: 1926 | C59: master mech., narcizo ruiz. Sr., concheño, chih. | D59: the concheño mining co. | L59: concheño chih | AA59: b | AB59: b | AD59: b | AF59: =LEN(D59)+LEN(E59)+LEN(F59)+LEN(G59)+LEN(H59)+LEN(I59)+LEN(J59)+LEN(K59)+LEN(L59)+LEN(M59)+LEN(N59)+LEN(O59)+LEN(P59) -> 36
A60: mmm294 | B60: 1926 | C60: foreign office, 1549 railway exchange bdg. chicago, ill., | D60: the cusi mining co. | L60: bdg chicago ill | AF60: =LEN(D60)+LEN(E60)+LEN(F60)+LEN(G60)+LEN(H60)+LEN(I60)+LEN(J60)+LEN(K60)+LEN(L60)+LEN(M60)+LEN(N60)+LEN(O60)+LEN(P60) -> 34
A61: mmm307 | B61: 1926 | C61: local office, baca, chih., | D61: the international ore & smelting co. | L61: office baca chih | Y61: b | AF61: =LEN(D61)+LEN(E61)+LEN(F61)+LEN(G61)+LEN(H61)+LEN(I61)+LEN(J61)+LEN(K61)+LEN(L61)+LEN(M61)+LEN(N61)+LEN(O61)+LEN(P61) -> 52
A62: mmm308 | B62: 1926 | C62: main office in mexico, apartado 136 saltillo, coah., | D62: the international ore & smelting co. | L62: apartado saltillo coah | Y62: b | AF62: =LEN(D62)+LEN(E62)+LEN(F62)+LEN(G62)+LEN(H62)+LEN(I62)+LEN(J62)+LEN(K62)+LEN(L62)+LEN(M62)+LEN(N62)+LEN(O62)+LEN(P62) -> 58
A63: mmm325 | B63: 1926 | C63: president, alfonso madero, san pedro, coah. | D63: compañia exploradora y explotadora de minas, s. a. | L63: san pedro coah | M63: maczregor | N63: alfonso | P63: president | AA63: b | AF63: =LEN(D63)+LEN(E63)+LEN(F63)+LEN(G63)+LEN(H63)+LEN(I63)+LEN(J63)+LEN(K63)+LEN(L63)+LEN(M63)+LEN(N63)+LEN(O63)+LEN(P63) -> 89
A64: mmm326 | B64: 1926 | C64: secr., emillo madero, san pedro, coah. | D64: compañia exploradora y explotadora de minas, s. a. | L64: san pedro coah | M64: madden | N64: emillo | P64: secr. | AA64: b | AB64: a | AE64: 3 | AF64: =LEN(D64)+LEN(E64)+LEN(F64)+LEN(G64)+LEN(H64)+LEN(I64)+LEN(J64)+LEN(K64)+LEN(L64)+LEN(M64)+LEN(N64)+LEN(O64)+LEN(P64) -> 81
A65: mmm327 | B65: 1926 | C65: treas., raul madero, san pedro, coah. | D65: compañia exploradora y explotadora de minas, s. a. | L65: san pedro coah | M65: madden | N65: raul | P65: treas. | AA65: b | AF65: =LEN(D65)+LEN(E65)+LEN(F65)+LEN(G65)+LEN(H65)+LEN(I65)+LEN(J65)+LEN(K65)+LEN(L65)+LEN(M65)+LEN(N65)+LEN(O65)+LEN(P65) -> 80
A66: mmm332 | B66: 1926 | C66: mining eng., alberto p gonzalez, bolivar 35, monterrey, n. l. | D66: compañia exploradora y explotadora de minas, s. a. | L66: monterrey n l | M66: gomez | N66: alberto | P66: mining eng. | AA66: b | AC66: b | AF66: =LEN(D66)+LEN(E66)+LEN(F66)+LEN(G66)+LEN(H66)+LEN(I66)+LEN(J66)+LEN(K66)+LEN(L66)+LEN(M66)+LEN(N66)+LEN(O66)+LEN(P66) -> 86
A67: mmm335 | B67: 1926 | C67: mexico city office, ave, madero 2. (apartado 2920.), | D67: compañia minera de minerales s. a. | L67: ave madero apartado | AF67: =LEN(D67)+LEN(E67)+LEN(F67)+LEN(G67)+LEN(H67)+LEN(I67)+LEN(J67)+LEN(K67)+LEN(L67)+LEN(M67)+LEN(N67)+LEN(O67)+LEN(P67) -> 53
A68: mmm337 | B68: 1926 | C68: grl. Mgr., f. e. salas,, saltillo, coah. | D68: compañia minera de minerales s. a. | L68: saltillo coah | AA68: b | AB68: b | AC68: b | AD68: b | AF68: =LEN(D68)+LEN(E68)+LEN(F68)+LEN(G68)+LEN(H68)+LEN(I68)+LEN(J68)+LEN(K68)+LEN(L68)+LEN(M68)+LEN(N68)+LEN(O68)+LEN(P68) -> 47
A69: mmm337 | B69: 1926 | C69: grl. Mgr., f. e. salas,, saltillo, coah. | D69: compañia minera de minerales s. a. | L69: saltillo coah | AA69: b | AB69: b | AC69: b | AD69: b | AF69: =LEN(D69)+LEN(E69)+LEN(F69)+LEN(G69)+LEN(H69)+LEN(I69)+LEN(J69)+LEN(K69)+LEN(L69)+LEN(M69)+LEN(N69)+LEN(O69)+LEN(P69) -> 47
A70: mmm341 | B70: 1926 | C70: sierra mojada, coah., c/o a. s. & r. co., see special information (end of mining list.), | D70: cia. Metalurgica mexicana | L70: of mining list | Y70: b | AF70: =LEN(D70)+LEN(E70)+LEN(F70)+LEN(G70)+LEN(H70)+LEN(I70)+LEN(J70)+LEN(K70)+LEN(L70)+LEN(M70)+LEN(N70)+LEN(O70)+LEN(P70) -> 39
A71: mmm348 | B71: 1926 | C71: The company owns the esmeralda, providencia, tercera zona, etc., mines. The cia. Min. de peñoles s. a. owns 50% of the shares of this co. and operates these mines. See the sierra mojada esmeralda units of the cia. Min. de peñoles s. a. | D71: cia. Min. la constancia la constancia s. a. | G71: The company owns the esmeralda, providencia, tercera zona, etc., mines. The cia. Min. de peñoles s. a. owns 50% of the shares of this co. and operates these mines. See the sierra mojada esmeralda units of the cia. Min. de peñoles s. a. | L71: coahuila | Q71: a | AE71: 15 | AF71: =LEN(D71)+LEN(E71)+LEN(F71)+LEN(G71)+LEN(H71)+LEN(I71)+LEN(J71)+LEN(K71)+LEN(L71)+LEN(M71)+LEN(N71)+LEN(O71)+LEN(P71) -> 286
A72: mmm352 | B72: 1926 | C72: silver lead zinc. | D72: cia. minera favorita y a n.s. a. | F72: silver lead zinc. | L72: coahuila | AF72: =LEN(D72)+LEN(E72)+LEN(F72)+LEN(G72)+LEN(H72)+LEN(I72)+LEN(J72)+LEN(K72)+LEN(L72)+LEN(M72)+LEN(N72)+LEN(O72)+LEN(P72) -> 57
A73: mmm353 | B73: 1926 | C73: president & gr. mgr., luis guimbardo, monterrey., n. l. | D73: cia. minera favorita y a n.s. a. | L73: monterrey n l | M73: guiana | N73: luis | P73: president & gr. mgr. | AA73: b | AF73: =LEN(D73)+LEN(E73)+LEN(F73)+LEN(G73)+LEN(H73)+LEN(I73)+LEN(J73)+LEN(K73)+LEN(L73)+LEN(M73)+LEN(N73)+LEN(O73)+LEN(P73) -> 75
A74: mmm353 | B74: 1926 | C74: president & gr. mgr., luis guimbardo, monterrey., n. l. | D74: cia. minera favorita y a n.s. a. | L74: monterrey n l | M74: guiana | N74: luis | P74: president & gr. mgr. | AA74: b | AF74: =LEN(D74)+LEN(E74)+LEN(F74)+LEN(G74)+LEN(H74)+LEN(I74)+LEN(J74)+LEN(K74)+LEN(L74)+LEN(M74)+LEN(N74)+LEN(O74)+LEN(P74) -> 75
A75: mmm357 | B75: 1926 | C75: p. o., esmeralda, | D75: cia. Minera la parreña | L75: p o esmeralda | Y75: b | AF75: =LEN(D75)+LEN(E75)+LEN(F75)+LEN(G75)+LEN(H75)+LEN(I75)+LEN(J75)+LEN(K75)+LEN(L75)+LEN(M75)+LEN(N75)+LEN(O75)+LEN(P75) -> 35
A76: mmm361 | B76: 1926 | C76: location, bajan, coah., | D76: cia. Minera norias de bajan s. a. | L76: bajan coah | AF76: =LEN(D76)+LEN(E76)+LEN(F76)+LEN(G76)+LEN(H76)+LEN(I76)+LEN(J76)+LEN(K76)+LEN(L76)+LEN(M76)+LEN(N76)+LEN(O76)+LEN(P76) -> 43
A77: mmm371 | B77: 1926 | C77: location & p. o., higueras, coah., | D77: cia. Min palomas y cabrillas s. a. | L77: higueras coah | AF77: =LEN(D77)+LEN(E77)+LEN(F77)+LEN(G77)+LEN(H77)+LEN(I77)+LEN(J77)+LEN(K77)+LEN(L77)+LEN(M77)+LEN(N77)+LEN(O77)+LEN(P77) -> 47
A78: mmm384 | B78: 1926 | C78: location & p.o., rio escondido, coah., | D78: minas carboniferas de rio escondido | L78: rio escondido coah | AF78: =LEN(D78)+LEN(E78)+LEN(F78)+LEN(G78)+LEN(H78)+LEN(I78)+LEN(J78)+LEN(K78)+LEN(L78)+LEN(M78)+LEN(N78)+LEN(O78)+LEN(P78) -> 53
A79: mmm398 | B79: 1926 | C79: zinc metallurgist, g. ross, saltillo, coah. | D79: the international ore & smelting co. | L79: saltillo coah | M79: ross | N79: graham | P79: zinc metallurgist | AF79: =LEN(D79)+LEN(E79)+LEN(F79)+LEN(G79)+LEN(H79)+LEN(I79)+LEN(J79)+LEN(K79)+LEN(L79)+LEN(M79)+LEN(N79)+LEN(O79)+LEN(P79) -> 76
A80: mmm402 | B80: 1926 | C80: location & p. o., cloete,, coah., coah. | D80: the new sabinas co. ltd. | L80: cloete coah coah | AF80: =LEN(D80)+LEN(E80)+LEN(F80)+LEN(G80)+LEN(H80)+LEN(I80)+LEN(J80)+LEN(K80)+LEN(L80)+LEN(M80)+LEN(N80)+LEN(O80)+LEN(P80) -> 40
A81: mmm417 | B81: 1926 | C81: l. 600,000 | D81: the mazapil copper co. ltd. | L81: coahuila | R81: b | AF81: =LEN(D81)+LEN(E81)+LEN(F81)+LEN(G81)+LEN(H81)+LEN(I81)+LEN(J81)+LEN(K81)+LEN(L81)+LEN(M81)+LEN(N81)+LEN(O81)+LEN(P81) -> 35
A82: mmm422 | B82: 1926 | C82: chairman, joseph ramsden, manchester, england | D82: the mazapil copper co. ltd. | L82: manchester england | M82: ramirez | N82: joseph | P82: chairman | AA82: b | AF82: =LEN(D82)+LEN(E82)+LEN(F82)+LEN(G82)+LEN(H82)+LEN(I82)+LEN(J82)+LEN(K82)+LEN(L82)+LEN(M82)+LEN(N82)+LEN(O82)+LEN(P82) -> 66
A83: mmm423 | B83: 1926 | C83: grl. mgr., r. h. jeffrey, saltillo, coah. | D83: the mazapil copper co. ltd. | L83: saltillo coah | M83: jdowpawtximited | N83: r | P83: grl. mgr. | AA83: b | AC83: b | AF83: =LEN(D83)+LEN(E83)+LEN(F83)+LEN(G83)+LEN(H83)+LEN(I83)+LEN(J83)+LEN(K83)+LEN(L83)+LEN(M83)+LEN(N83)+LEN(O83)+LEN(P83) -> 65
A84: mmm423 | B84: 1926 | C84: grl. mgr., r. h. jeffrey, saltillo, coah. | D84: the mazapil copper co. ltd. | L84: saltillo coah | M84: jdowpawtximited | N84: r | P84: grl. mgr. | AA84: b | AC84: b | AF84: =LEN(D84)+LEN(E84)+LEN(F84)+LEN(G84)+LEN(H84)+LEN(I84)+LEN(J84)+LEN(K84)+LEN(L84)+LEN(M84)+LEN(N84)+LEN(O84)+LEN(P84) -> 65
A85: mmm437 | B85: 1926 | C85: grl. mgr., r. h. jeffrey, saltillo, | D85: a vino mines ltd. | L85: saltillo | M85: je ek | N85: r | P85: grl. mgr. | Q85: b | AA85: b | AC85: b | AF85: =LEN(D85)+LEN(E85)+LEN(F85)+LEN(G85)+LEN(H85)+LEN(I85)+LEN(J85)+LEN(K85)+LEN(L85)+LEN(M85)+LEN(N85)+LEN(O85)+LEN(P85) -> 40
A86: mmm442 | B86: 1926 | C86: organized, on june 7th 1904., | D86: bacis gold & silver mining co. ltd. | K86: organized, on june 7th 1904., | L86: durango | AF86: =LEN(D86)+LEN(E86)+LEN(F86)+LEN(G86)+LEN(H86)+LEN(I86)+LEN(J86)+LEN(K86)+LEN(L86)+LEN(M86)+LEN(N86)+LEN(O86)+LEN(P86) -> 72
A87: mmm444 | B87: 1926 | C87: location, bacis district, santiago papasquiero, durango | D87: bacis gold & silver mining co. ltd. | L87: santiago papasquiero durango | AF87: =LEN(D87)+LEN(E87)+LEN(F87)+LEN(G87)+LEN(H87)+LEN(I87)+LEN(J87)+LEN(K87)+LEN(L87)+LEN(M87)+LEN(N87)+LEN(O87)+LEN(P87) -> 63
A88: mmm470 | B88: 1926 | C88: mill name, santa ana y anexas., | D88: cia. min. san andres de la sierra s. a. | L88: ana y anexas | Y88: b | AF88: =LEN(D88)+LEN(E88)+LEN(F88)+LEN(G88)+LEN(H88)+LEN(I88)+LEN(J88)+LEN(K88)+LEN(L88)+LEN(M88)+LEN(N88)+LEN(O88)+LEN(P88) -> 51
A89: mmm472 | B89: 1926 | C89: mill p. o., canelas, dgo., | D89: cia. min. san andres de la sierra s. a. | L89: canelas dgo | AF89: =LEN(D89)+LEN(E89)+LEN(F89)+LEN(G89)+LEN(H89)+LEN(I89)+LEN(J89)+LEN(K89)+LEN(L89)+LEN(M89)+LEN(N89)+LEN(O89)+LEN(P89) -> 50
A90: mmm475 | B90: 1926 | C90: smelter name, cia. fundidora de la sierra., | D90: cia. min. san andres de la sierra s. a. | L90: de la sierra | AF90: =LEN(D90)+LEN(E90)+LEN(F90)+LEN(G90)+LEN(H90)+LEN(I90)+LEN(J90)+LEN(K90)+LEN(L90)+LEN(M90)+LEN(N90)+LEN(O90)+LEN(P90) -> 51
A91: mmm499 | B91: 1926 | C91: location, san juan de guadalupe, dgo., | D91: alberto genty y cia. | L91: de guadalupe dgo | Y91: b | AF91: =LEN(D91)+LEN(E91)+LEN(F91)+LEN(G91)+LEN(H91)+LEN(I91)+LEN(J91)+LEN(K91)+LEN(L91)+LEN(M91)+LEN(N91)+LEN(O91)+LEN(P91) -> 36
A92: mmm500 | B92: 1926 | C92: p. o., estacion rivas, dgo., | D92: alberto genty y cia. | L92: estacion rivas dgo | AF92: =LEN(D92)+LEN(E92)+LEN(F92)+LEN(G92)+LEN(H92)+LEN(I92)+LEN(J92)+LEN(K92)+LEN(L92)+LEN(M92)+LEN(N92)+LEN(O92)+LEN(P92) -> 38
A93: mmm504 | B93: 1926 | C93: gold silver. | D93: anita custom mill | F93: gold silver. | L93: durango | AF93: =LEN(D93)+LEN(E93)+LEN(F93)+LEN(G93)+LEN(H93)+LEN(I93)+LEN(J93)+LEN(K93)+LEN(L93)+LEN(M93)+LEN(N93)+LEN(O93)+LEN(P93) -> 36
A94: mmm513 | B94: 1926 | C94: gold, silver, lead | D94: inde gold mining co. | F94: gold, silver, lead | L94: durango | AF94: =LEN(D94)+LEN(E94)+LEN(F94)+LEN(G94)+LEN(H94)+LEN(I94)+LEN(J94)+LEN(K94)+LEN(L94)+LEN(M94)+LEN(N94)+LEN(O94)+LEN(P94) -> 45
A95: mmm516 | B95: 1926 | C95: daily output, 100 metric tons, | D95: inde gold mining co. | I95: 100 metric tons | L95: durango | AF95: =LEN(D95)+LEN(E95)+LEN(F95)+LEN(G95)+LEN(H95)+LEN(I95)+LEN(J95)+LEN(K95)+LEN(L95)+LEN(M95)+LEN(N95)+LEN(O95)+LEN(P95) -> 42
A96: mmm537 | B96: 1926 | C96: cyanidation., | D96: san luis mining co. | J96: cyanidation. | L96: durango | AF96: =LEN(D96)+LEN(E96)+LEN(F96)+LEN(G96)+LEN(H96)+LEN(I96)+LEN(J96)+LEN(K96)+LEN(L96)+LEN(M96)+LEN(N96)+LEN(O96)+LEN(P96) -> 38
A97: mmm548 | B97: 1926 | C97: location & p. o., guanacevi, dgo., | D97: the soto mines co. s. a. | L97: guanacevi dgo | AF97: =LEN(D97)+LEN(E97)+LEN(F97)+LEN(G97)+LEN(H97)+LEN(I97)+LEN(J97)+LEN(K97)+LEN(L97)+LEN(M97)+LEN(N97)+LEN(O97)+LEN(P97) -> 37
A98: mmm552 | B98: 1926 | C98: table & flotation concentration., | D98: the soto mines co. s. a. | J98: table & flotation concentration. | L98: durango | AF98: =LEN(D98)+LEN(E98)+LEN(F98)+LEN(G98)+LEN(H98)+LEN(I98)+LEN(J98)+LEN(K98)+LEN(L98)+LEN(M98)+LEN(N98)+LEN(O98)+LEN(P98) -> 63
A99: mmm559 | B99: 1926 | C99: 1.000,000 oro nac. | D99: cia. minera aurora y anexas s. a. | L99: guanajuato | R99: b | AF99: =LEN(D99)+LEN(E99)+LEN(F99)+LEN(G99)+LEN(H99)+LEN(I99)+LEN(J99)+LEN(K99)+LEN(L99)+LEN(M99)+LEN(N99)+LEN(O99)+LEN(P99) -> 43
A100: mmm567 | B100: 1926 | C100: organized, in mexico on august 9, 1924, | D100: cia. minera cristo rey y anexas s. a. | K100: organized, in mexico on august 9, 1924, | L100: guanajuato | AF100: =LEN(D100)+LEN(E100)+LEN(F100)+LEN(G100)+LEN(H100)+LEN(I100)+LEN(J100)+LEN(K100)+LEN(L100)+LEN(M100)+LEN(N100)+LEN(O100)+LEN(P100) -> 87
...

Sheet alumnit
A1: id | B1: source | C1: year | D1: lastname | E1: firstname | F1: middlename | G1: prof | H1: org | I1: loc | J1: year | K1: lastname | L1: firstname | M1: middlename | N1: prof | O1: org | P1: loc | Q1: cer | R1: tot | T1: extracted/actual | U1: positive | V1: negative
A2: co21472 | B2: colmines | C2: 1898 | D2: hill | E2: w | F2: h | G2: student | H2: colmines | I2: NA | P2: 1 | R2: =LEN(C2)+LEN(D2)+LEN(E2)+LEN(F2)+LEN(G2)+LEN(H2) -> 25 | T2: positive | U2: t | V2: f
A3: co34769 | B3: colmines | C3: 1905 | D3: patterson | E3: a | F3: w | G3: student | H3: colmines | I3: NA | P3: 1 | R3: =LEN(C3)+LEN(D3)+LEN(E3)+LEN(F3)+LEN(G3)+LEN(H3) -> 30 | T3: negative | U3: f | V3: t
A4: co48041 | B4: colmines | C4: 1902 | D4: wells | E4: f | F4: o | G4: student | H4: colmines | I4: NA | P4: 1 | R4: =LEN(C4)+LEN(D4)+LEN(E4)+LEN(F4)+LEN(G4)+LEN(H4) -> 26
A5: cu12925 | B5: cu | C5: 1892 | D5: drasel | E5: c | G5: student | H5: cu | I5: ny city | R5: =LEN(C5)+LEN(D5)+LEN(E5)+LEN(F5)+LEN(G5)+LEN(H5) -> 20 | T5: code
A6: cu16012 | B6: cu | C6: 1911 | D6: frank | E6: earle | G6: student | H6: cu | I6: ny city | J6: b | R6: =LEN(C6)+LEN(D6)+LEN(E6)+LEN(F6)+LEN(G6)+LEN(H6) -> 23 | T6: extracted/actual | U6: positive | V6: negative
A7: cu18812 | B7: cu | C7: 1907 | D7: guinchard | E7: a | G7: student | H7: cu | I7: ny city | R7: =LEN(C7)+LEN(D7)+LEN(E7)+LEN(F7)+LEN(G7)+LEN(H7) -> 23 | T7: positive | V7: f
A8: cu19207 | B8: cu | C8: 1898 | D8: hall | E8: harry | G8: student | H8: cu | I8: ny city | M8: b | R8: =LEN(C8)+LEN(D8)+LEN(E8)+LEN(F8)+LEN(G8)+LEN(H8) -> 22 | T8: negative | U8: f
A9: cu20488 | B9: cu | C9: 1892 | D9: hay | E9: a | G9: student | H9: cu | I9: ny city | R9: =LEN(C9)+LEN(D9)+LEN(E9)+LEN(F9)+LEN(G9)+LEN(H9) -> 17
A10: cu21124 | B10: cu | C10: 1911 | D10: herter | E10: a | F10: h | G10: student | H10: cu | I10: ny city | R10: =LEN(C10)+LEN(D10)+LEN(E10)+LEN(F10)+LEN(G10)+LEN(H10) -> 21 | T10: types of mistakes on true positives
A11: cu21791 | B11: cu | C11: 1885 | D11: hoffbauer | E11: o | G11: student | H11: cu | I11: ny city | M11: b | R11: =LEN(C11)+LEN(D11)+LEN(E11)+LEN(F11)+LEN(G11)+LEN(H11) -> 23 | T11: no mistake
A12: cu22577 | B12: cu | C12: 1904 | D12: howe | E12: a | F12: a | G12: student | H12: cu | I12: ny city | M12: b | R12: =LEN(C12)+LEN(D12)+LEN(E12)+LEN(F12)+LEN(G12)+LEN(H12) -> 19 | T12: source to text | U12: a
A13: cu23330 | B13: cu | C13: 1909 | D13: hutchinson | E13: george | F13: e | G13: student | H13: cu | I13: ny city | R13: =LEN(C13)+LEN(D13)+LEN(E13)+LEN(F13)+LEN(G13)+LEN(H13) -> 30 | T13: text to source | U13: b
A14: cu26219 | B14: cu | C14: 1884 | D14: lamb | E14: augustus | F14: j | G14: student | H14: cu | I14: ny city | R14: =LEN(C14)+LEN(D14)+LEN(E14)+LEN(F14)+LEN(G14)+LEN(H14) -> 26
A15: cu28529 | B15: cu | C15: 1912 | D15: macdermott | E15: s | F15: s | G15: student | H15: cu | I15: ny city | R15: =LEN(C15)+LEN(D15)+LEN(E15)+LEN(F15)+LEN(G15)+LEN(H15) -> 25
A16: cu29080 | B16: cu | C16: 1885 | D16: mannheim | E16: paul | F16: a | G16: student | H16: cu | I16: ny city | R16: =LEN(C16)+LEN(D16)+LEN(E16)+LEN(F16)+LEN(G16)+LEN(H16) -> 26
A17: cu31533 | B17: cu | C17: 1912 | D17: moffett | E17: h | G17: student | H17: cu | I17: ny city | M17: b | R17: =LEN(C17)+LEN(D17)+LEN(E17)+LEN(F17)+LEN(G17)+LEN(H17) -> 21
A18: cu36129 | B18: cu | C18: 1906 | D18: popper | E18: e | G18: student | H18: cu | I18: ny city | R18: =LEN(C18)+LEN(D18)+LEN(E18)+LEN(F18)+LEN(G18)+LEN(H18) -> 20
A19: cu37053 | B19: cu | C19: 1910 | D19: raphael | E19: a | G19: student | H19: cu | I19: ny city | M19: b | R19: =LEN(C19)+LEN(D19)+LEN(E19)+LEN(F19)+LEN(G19)+LEN(H19) -> 21
A20: cu44627 | B20: cu | C20: 1894 | D20: taylor | E20: o | G20: student | H20: cu | I20: ny city | L20: b | R20: =LEN(C20)+LEN(D20)+LEN(E20)+LEN(F20)+LEN(G20)+LEN(H20) -> 20
A21: cu46393 | B21: cu | C21: 1912 | D21: van | E21: t | G21: student | H21: cu | I21: ny city | K21: b | M21: b | R21: =LEN(C21)+LEN(D21)+LEN(E21)+LEN(F21)+LEN(G21)+LEN(H21) -> 17
A22: cu5040 | B22: cu | C22: 1902 | D22: brcneman | E22: h | F22: c | G22: student | H22: cu | I22: ny city | K22: a | Q22: 1 | R22: =LEN(C22)+LEN(D22)+LEN(E22)+LEN(F22)+LEN(G22)+LEN(H22) -> 23
A23: cu5940 | B23: cu | C23: 1884 | D23: bryce | E23: w | G23: student | H23: cu | I23: ny city | R23: =LEN(C23)+LEN(D23)+LEN(E23)+LEN(F23)+LEN(G23)+LEN(H23) -> 19
A24: cu6025 | B24: cu | C24: 1903 | D24: buckmaster | E24: f | F24: c | G24: student | H24: cu | I24: ny city | R24: =LEN(C24)+LEN(D24)+LEN(E24)+LEN(F24)+LEN(G24)+LEN(H24) -> 25
A25: cu7529 | B25: cu | C25: 1892 | D25: casamajor | E25: g | F25: h | G25: student | H25: cu | I25: ny city | R25: =LEN(C25)+LEN(D25)+LEN(E25)+LEN(F25)+LEN(G25)+LEN(H25) -> 24
A26: cu7564 | B26: cu | C26: 1893 | D26: caspe | E26: a | G26: student | H26: cu | I26: ny city | R26: =LEN(C26)+LEN(D26)+LEN(E26)+LEN(F26)+LEN(G26)+LEN(H26) -> 19
A27: cu8314 | B27: cu | C27: 1906 | D27: church | E27: j | F27: a | G27: student | H27: cu | I27: ny city | R27: =LEN(C27)+LEN(D27)+LEN(E27)+LEN(F27)+LEN(G27)+LEN(H27) -> 21
A28: en34067 | B28: eni | C28: 1905 | D28: ostos | E28: j | G28: student | H28: eni | I28: mexico city | J28: b | R28: =LEN(C28)+LEN(D28)+LEN(E28)+LEN(F28)+LEN(G28)+LEN(H28) -> 20
A29: en34315 | B29: eni | C29: 1905 | D29: palacio | E29: r | G29: student | H29: eni | I29: mexico city | J29: b | R29: =LEN(C29)+LEN(D29)+LEN(E29)+LEN(F29)+LEN(G29)+LEN(H29) -> 22
A30: en46554 | B30: eni | C30: 1905 | D30: vazquez | E30: s | G30: student | H30: eni | I30: mexico city | J30: b | R30: =LEN(C30)+LEN(D30)+LEN(E30)+LEN(F30)+LEN(G30)+LEN(H30) -> 22
A31: fr2471 | B31: frei | C31: 1865 | D31: de crano | E31: e | I31: san francisco usa | J31: b | M31: b | N31: b | O31: b | R31: =LEN(C31)+LEN(D31)+LEN(E31)+LEN(F31)+LEN(G31)+LEN(H31) -> 13
A32: fr2510 | B32: frei | C32: 1871 | D32: dietze | E32: georg | F32: moritz | I32: freiberg sachsen | J32: ?b | N32: b | O32: b | R32: =LEN(C32)+LEN(D32)+LEN(E32)+LEN(F32)+LEN(G32)+LEN(H32) -> 21
A33: fr2638 | B33: frei | C33: 1871 | D33: lowe | E33: francis | F33: asbury | G33: student | H33: freiberg school | I33: washington usa | R33: =LEN(C33)+LEN(D33)+LEN(E33)+LEN(F33)+LEN(G33)+LEN(H33) -> 43
A34: fr2697 | B34: frei | C34: 1871 | D34: zoric | E34: svetosar | G34: student | H34: freiberg school | I34: titel ungarn | J34: b | R34: =LEN(C34)+LEN(D34)+LEN(E34)+LEN(F34)+LEN(G34)+LEN(H34) -> 39
A35: fr2732 | B35: frei | C35: 1873 | D35: stoiber | E35: eduard | F35: georg | G35: student | H35: freiberg school | I35: new york usa | R35: =LEN(C35)+LEN(D35)+LEN(E35)+LEN(F35)+LEN(G35)+LEN(H35) -> 44
A36: fr2813 | B36: frei | C36: 1874 | D36: heck | E36: carl | I36: dierdorf rheinpreuben | J36: b | N36: b | O36: b | R36: =LEN(C36)+LEN(D36)+LEN(E36)+LEN(F36)+LEN(G36)+LEN(H36) -> 12
A37: fr2955 | B37: frei | C37: 1876 | D37: fuch8 | E37: ernst | F37: fiirchtegott | I37: chemnitz sachsen | J37: b | K37: a | M37: a | N37: b | O37: b | Q37: 3 | R37: =LEN(C37)+LEN(D37)+LEN(E37)+LEN(F37)+LEN(G37)+LEN(H37) -> 26
A38: fr2987 | B38: frei | C38: 1877 | D38: wei8 | E38: carl | F38: eduard | G38: student | H38: freiberg school | I38: marienberg | K38: a | Q38: 1 | R38: =LEN(C38)+LEN(D38)+LEN(E38)+LEN(F38)+LEN(G38)+LEN(H38) -> 40
A39: fr2988 | B39: frei | C39: 1876 | D39: zetzsche | E39: heinrich | F39: paul | I39: altenburg | N39: b | O39: b | R39: =LEN(C39)+LEN(D39)+LEN(E39)+LEN(F39)+LEN(G39)+LEN(H39) -> 24
A40: fr3001 | B40: frei | C40: 1883 | D40: fischer | E40: heinrich | F40: carl | G40: student | H40: freiberg school | I40: colditz sachsen | R40: =LEN(C40)+LEN(D40)+LEN(E40)+LEN(F40)+LEN(G40)+LEN(H40) -> 45
A41: fr3010 | B41: frei | C41: 1877 | D41: jeramjanz | E41: stephan | I41: erivan rubland | J41: b | N41: b | O41: b | R41: =LEN(C41)+LEN(D41)+LEN(E41)+LEN(F41)+LEN(G41)+LEN(H41) -> 20
A42: fr3210 | B42: frei | C42: 1886 | D42: krantz | E42: friedrich | F42: august | G42: student | H42: freiberg school | I42: aimaberg rubland | R42: =LEN(C42)+LEN(D42)+LEN(E42)+LEN(F42)+LEN(G42)+LEN(H42) -> 47
A43: fr3306 | B43: frei | C43: 1883 | D43: eydam | E43: willy | I43: weida b | J43: b | N43: b | O43: b | R43: =LEN(C43)+LEN(D43)+LEN(E43)+LEN(F43)+LEN(G43)+LEN(H43) -> 14
A44: fr3341 | B44: frei | C44: 1883 | D44: herter | E44: emil | F44: franz | I44: pleiske b | J44: b | N44: b | O44: b | R44: =LEN(C44)+LEN(D44)+LEN(E44)+LEN(F44)+LEN(G44)+LEN(H44) -> 19
A45: fr3343 | B45: frei | C45: 1884 | D45: schulze | G45: student | H45: freiberg school | I45: NA | L45: b | M45: b | R45: =LEN(C45)+LEN(D45)+LEN(E45)+LEN(F45)+LEN(G45)+LEN(H45) -> 33
A46: fr3368 | B46: frei | C46: 1885 | D46: v dessauer | E46: anton | G46: student | H46: freiberg school | I46: munchen | R46: =LEN(C46)+LEN(D46)+LEN(E46)+LEN(F46)+LEN(G46)+LEN(H46) -> 41
A47: fr3465 | B47: frei | C47: 1889 | D47: roldan e pego | G47: student | H47: freiberg school | I47: NA | L47: b | R47: =LEN(C47)+LEN(D47)+LEN(E47)+LEN(F47)+LEN(G47)+LEN(H47) -> 39
A48: fr3528 | B48: frei | C48: 1887 | D48: zell | E48: max | G48: student | H48: freiberg school | I48: neuruppin | R48: =LEN(C48)+LEN(D48)+LEN(E48)+LEN(F48)+LEN(G48)+LEN(H48) -> 33
A49: fr3610 | B49: frei | C49: 1889 | D49: keller | E49: richard | G49: student | H49: freiberg school | I49: city wisconsin usa | R49: =LEN(C49)+LEN(D49)+LEN(E49)+LEN(F49)+LEN(G49)+LEN(H49) -> 39
A50: fr3662 | B50: frei | C50: 1889 | D50: hey | E50: gustav | F50: adolf | I50: freiberg sachsen | J50: b | N50: b | O50: b | R50: =LEN(C50)+LEN(D50)+LEN(E50)+LEN(F50)+LEN(G50)+LEN(H50) -> 18
A51: fr3692 | B51: frei | C51: 1890 | D51: schneiders | E51: karl | F51: gottfried | G51: student | H51: freiberg school | I51: aachen preuben | R51: =LEN(C51)+LEN(D51)+LEN(E51)+LEN(F51)+LEN(G51)+LEN(H51) -> 49
A52: fr3708 | B52: frei | C52: 1890 | D52: wehner | E52: frederik | F52: carl | G52: student | H52: freiberg school | I52: england | R52: =LEN(C52)+LEN(D52)+LEN(E52)+LEN(F52)+LEN(G52)+LEN(H52) -> 44
A53: fr3718 | B53: frei | C53: 1890 | D53: boddinghaus | E53: walther | I53: elberfeld | J53: b | N53: b | O53: b | R53: =LEN(C53)+LEN(D53)+LEN(E53)+LEN(F53)+LEN(G53)+LEN(H53) -> 22
A54: fr3781 | B54: frei | C54: 1891 | D54: v wolff | E54: erich | F54: maximilian | G54: student | H54: freiberg school | I54: baron hintzenberg rubland | R54: =LEN(C54)+LEN(D54)+LEN(E54)+LEN(F54)+LEN(G54)+LEN(H54) -> 48
A55: fr3852 | B55: frei | C55: 1893 | D55: abe | E55: richard | G55: student | H55: freiberg school | I55: witten preuben | R55: =LEN(C55)+LEN(D55)+LEN(E55)+LEN(F55)+LEN(G55)+LEN(H55) -> 36
A56: fr3874 | B56: frei | C56: 1893 | D56: lister | E56: arthur | F56: leonard | G56: student | H56: freiberg school | I56: yercand indien | R56: =LEN(C56)+LEN(D56)+LEN(E56)+LEN(F56)+LEN(G56)+LEN(H56) -> 45
A57: fr3906 | B57: frei | C57: 1897 | D57: bernhard | E57: gustav | F57: walther | I57: schlobchemnitz bei chemnitz | N57: b | O57: b | R57: =LEN(C57)+LEN(D57)+LEN(E57)+LEN(F57)+LEN(G57)+LEN(H57) -> 25
A58: fr4049 | B58: frei | C58: 1895 | D58: bauer | E58: oswald | F58: friedrich | I58: goldingen rubl | J58: b | N58: b | O58: b | R58: =LEN(C58)+LEN(D58)+LEN(E58)+LEN(F58)+LEN(G58)+LEN(H58) -> 24
A59: fr4085 | B59: frei | C59: 1900 | D59: korwazki | E59: wasili | I59: ananiew rubland | N59: b | O59: b | R59: =LEN(C59)+LEN(D59)+LEN(E59)+LEN(F59)+LEN(G59)+LEN(H59) -> 18
A60: fr4118 | B60: frei | C60: 1896 | D60: spitzner | E60: karl | F60: justus | G60: student | H60: freiberg school | I60: dresden | R60: =LEN(C60)+LEN(D60)+LEN(E60)+LEN(F60)+LEN(G60)+LEN(H60) -> 44
A61: fr4135 | B61: frei | C61: 1897 | D61: balasinovici | E61: eugeniu | G61: student | H61: freiberg school | I61: cordareni rumii | R61: =LEN(C61)+LEN(D61)+LEN(E61)+LEN(F61)+LEN(G61)+LEN(H61) -> 45
A62: fr4279 | B62: frei | C62: 1897 | D62: hilgenberg | E62: hermann | F62: max | I62: cassel preuben | J62: b | N62: b | O62: b | R62: =LEN(C62)+LEN(D62)+LEN(E62)+LEN(F62)+LEN(G62)+LEN(H62) -> 24
A63: fr4298 | B63: frei | C63: 1897 | D63: kulbach | E63: oswald | F63: moritz | I63: tabbifer rubland | J63: b | N63: b | O63: b | R63: =LEN(C63)+LEN(D63)+LEN(E63)+LEN(F63)+LEN(G63)+LEN(H63) -> 23
A64: fr4344 | B64: frei | C64: 1898 | D64: schott | E64: albert | F64: ernst | G64: student | H64: freiberg school | I64: chemnitz sachsen | R64: =LEN(C64)+LEN(D64)+LEN(E64)+LEN(F64)+LEN(G64)+LEN(H64) -> 43
A65: fr4412 | B65: frei | C65: 1899 | D65: v kupffer | E65: eduard | F65: friedrich | G65: student | H65: freiberg school | I65: moskau | R65: =LEN(C65)+LEN(D65)+LEN(E65)+LEN(F65)+LEN(G65)+LEN(H65) -> 50
A66: fr4477 | B66: frei | C66: 1904 | D66: dabkowicz | E66: jan | G66: student | H66: freiberg school | I66: warschau | R66: =LEN(C66)+LEN(D66)+LEN(E66)+LEN(F66)+LEN(G66)+LEN(H66) -> 38
A67: fr4540 | B67: frei | C67: 1904 | D67: v neyman | E67: kasimir | F67: wilhelm | I67: kharkov ukraine | N67: b | O67: b | R67: =LEN(C67)+LEN(D67)+LEN(E67)+LEN(F67)+LEN(G67)+LEN(H67) -> 26
A68: fr4545 | B68: frei | C68: 1899 | D68: paul | E68: wilhelm | I68: goslar preu en | J68: b | N68: b | O68: b | R68: =LEN(C68)+LEN(D68)+LEN(E68)+LEN(F68)+LEN(G68)+LEN(H68) -> 15
A69: fr4602 | B69: frei | C69: 1905 | D69: brill | E69: bernhard | G69: student | H69: freiberg school | I69: jassy rum | R69: =LEN(C69)+LEN(D69)+LEN(E69)+LEN(F69)+LEN(G69)+LEN(H69) -> 39
A70: fr4648 | B70: frei | C70: 1900 | D70: konjaroff | E70: georgi | G70: student | H70: freiberg school | I70: plowdir bulgarien | J70: b | R70: =LEN(C70)+LEN(D70)+LEN(E70)+LEN(F70)+LEN(G70)+LEN(H70) -> 41
A71: fr4685 | B71: frei | C71: 1900 | D71: popoff | E71: paul | G71: student | H71: freiberg school | I71: irkutsk rubland | J71: b | R71: =LEN(C71)+LEN(D71)+LEN(E71)+LEN(F71)+LEN(G71)+LEN(H71) -> 36
A72: fr4714 | B72: frei | C72: 1900 | D72: steinberg | E72: wladimir | G72: student | H72: freiberg school | I72: odessa rubland | J72: b | R72: =LEN(C72)+LEN(D72)+LEN(E72)+LEN(F72)+LEN(G72)+LEN(H72) -> 43
A73: fr4839 | B73: frei | C73: 1902 | D73: singher | E73: leibu | G73: student | H73: freiberg school | I73: vaslui rum | R73: =LEN(C73)+LEN(D73)+LEN(E73)+LEN(F73)+LEN(G73)+LEN(H73) -> 38
A74: fr4958 | B74: frei | C74: 1904 | D74: browne | E74: robert | G74: student | H74: freiberg school | I74: new york usa | R74: =LEN(C74)+LEN(D74)+LEN(E74)+LEN(F74)+LEN(G74)+LEN(H74) -> 38
A75: fr4979 | B75: frei | C75: 1903 | D75: gorenstein | E75: nachim | I75: kiew rubland | J75: b | N75: b | O75: b | R75: =LEN(C75)+LEN(D75)+LEN(E75)+LEN(F75)+LEN(G75)+LEN(H75) -> 20
A76: fr4989 | B76: frei | C76: 1904 | D76: jones | E76: sidney | G76: student | H76: freiberg school | I76: kapstadt stidafrika | R76: =LEN(C76)+LEN(D76)+LEN(E76)+LEN(F76)+LEN(G76)+LEN(H76) -> 37
A77: fr5058 | B77: frei | C77: 1903 | D77: warnecke | E77: heinrich | F77: paul | I77: hornhausen preuben | J77: b | N77: b | O77: b | R77: =LEN(C77)+LEN(D77)+LEN(E77)+LEN(F77)+LEN(G77)+LEN(H77) -> 24
A78: fr5112 | B78: frei | C78: 1905 | D78: glockler | E78: carl | F78: adam | G78: student | H78: freiberg school | I78: wasserau rubi | R78: =LEN(C78)+LEN(D78)+LEN(E78)+LEN(F78)+LEN(G78)+LEN(H78) -> 42
A79: fr5129 | B79: frei | C79: 1905 | D79: johnson | E79: bernard | F79: angas | G79: student | H79: freiberg school | I79: london england | R79: =LEN(C79)+LEN(D79)+LEN(E79)+LEN(F79)+LEN(G79)+LEN(H79) -> 45
A80: fr5176 | B80: frei | C80: 1904 | D80: ralff | E80: eugen | I80: belopolie rubland | J80: b | N80: b | O80: b | R80: =LEN(C80)+LEN(D80)+LEN(E80)+LEN(F80)+LEN(G80)+LEN(H80) -> 14
A81: fr5208 | B81: frei | C81: 1904 | D81: v gel | E81: paul | F81: herbert | I81: herbert dresden | J81: b | K81: a | N81: b | O81: b | Q81: 1 | R81: =LEN(C81)+LEN(D81)+LEN(E81)+LEN(F81)+LEN(G81)+LEN(H81) -> 20
A82: fr5214 | B82: frei | C82: 1904 | D82: weise | E82: gerhard | F82: oskar | I82: sayda | J82: b | N82: b | O82: b | R82: =LEN(C82)+LEN(D82)+LEN(E82)+LEN(F82)+LEN(G82)+LEN(H82) -> 21
A83: fr5230 | B83: frei | C83: 1905 | D83: brandt | E83: rudolf | F83: erich | I83: zwickau sachsen | J83: b | N83: b | O83: b | R83: =LEN(C83)+LEN(D83)+LEN(E83)+LEN(F83)+LEN(G83)+LEN(H83) -> 21
A84: fr5368 | B84: frei | C84: 1906 | D84: ficker | E84: kurt | F84: johannes | I84: johannes dresden | J84: b | N84: b | O84: b | R84: =LEN(C84)+LEN(D84)+LEN(E84)+LEN(F84)+LEN(G84)+LEN(H84) -> 22
A85: fr5413 | B85: frei | C85: 1906 | D85: molls | E85: eduard | F85: otto | I85: nowapraga b | J85: b | N85: b | O85: b | R85: =LEN(C85)+LEN(D85)+LEN(E85)+LEN(F85)+LEN(G85)+LEN(H85) -> 19
A86: fr5415 | B86: frei | C86: 1912 | D86: moshaizew | E86: andreas | F86: lwowitsch | I86: kotelniki russia | N86: b | O86: b | R86: =LEN(C86)+LEN(D86)+LEN(E86)+LEN(F86)+LEN(G86)+LEN(H86) -> 29
A87: fr5464 | B87: frei | C87: 1908 | D87: beck | E87: felix | F87: walter | G87: student | H87: freiberg school | I87: sachsen | R87: =LEN(C87)+LEN(D87)+LEN(E87)+LEN(F87)+LEN(G87)+LEN(H87) -> 41
A88: fr5773 | B88: frei | C88: 1911 | D88: nette | E88: paul | F88: rudolf | G88: student | H88: freiberg school | I88: oberschlema sachsen | R88: =LEN(C88)+LEN(D88)+LEN(E88)+LEN(F88)+LEN(G88)+LEN(H88) -> 41
A89: fr5791 | B89: frei | C89: 1911 | D89: schonfelder | E89: ernst | F89: erich | G89: student | H89: freiberg school | I89: holzminden braunschweig | R89: =LEN(C89)+LEN(D89)+LEN(E89)+LEN(F89)+LEN(G89)+LEN(H89) -> 47
A90: fr5797 | B90: frei | C90: 1910 | D90: schwirkus | E90: rudolf | F90: walter | I90: freiberg sachsen | J90: b | N90: b | O90: b | R90: =LEN(C90)+LEN(D90)+LEN(E90)+LEN(F90)+LEN(G90)+LEN(H90) -> 25
A91: fr5923 | B91: frei | C91: 1912 | D91: glanzberg | E91: rudolf | F91: erwin | I91: grillenburg sachsen | J91: b | N91: b | O91: b | R91: =LEN(C91)+LEN(D91)+LEN(E91)+LEN(F91)+LEN(G91)+LEN(H91) -> 24
A92: fr6000 | B92: frei | C92: 1913 | D92: wiirfel | E92: alwin | F92: gotthard | G92: student | H92: freiberg school | I92: li ibau sachsen | K92: a | Q92: 2 | R92: =LEN(C92)+LEN(D92)+LEN(E92)+LEN(F92)+LEN(G92)+LEN(H92) -> 46
A93: fr6022 | B93: frei | C93: 1914 | D93: wiegemann | E93: rosa | I93: freiberg sachsen | J93: b | N93: b | O93: b | R93: =LEN(C93)+LEN(D93)+LEN(E93)+LEN(F93)+LEN(G93)+LEN(H93) -> 17
A94: fr6034 | B94: frei | C94: 1916 | D94: geuthner | E94: walther | G94: student | H94: freiberg school | I94: leipzig | R94: =LEN(C94)+LEN(D94)+LEN(E94)+LEN(F94)+LEN(G94)+LEN(H94) -> 41
A95: fr6061 | B95: frei | C95: 1922 | D95: mtiller | E95: ernst | G95: merchant | H95: freiberg school | I95: zitzau | R95: =LEN(C95)+LEN(D95)+LEN(E95)+LEN(F95)+LEN(G95)+LEN(H95) -> 39
A96: fr6080 | B96: frei | C96: 1918 | D96: beck | E96: gottfried | G96: student | H96: freiberg school | I96: schleiz germany | R96: =LEN(C96)+LEN(D96)+LEN(E96)+LEN(F96)+LEN(G96)+LEN(H96) -> 39
A97: fr6093 | B97: frei | C97: 1917 | D97: dachselt | E97: johannes | I97: freiberg sa | R97: =LEN(C97)+LEN(D97)+LEN(E97)+LEN(F97)+LEN(G97)+LEN(H97) -> 20
A98: fr6127 | B98: frei | C98: 1917 | D98: klinger | E98: rudolf | I98: kau frnann | R98: =LEN(C98)+LEN(D98)+LEN(E98)+LEN(F98)+LEN(G98)+LEN(H98) -> 17
A99: fr6166 | B99: frei | C99: 1922 | D99: rautenberg | G99: pastor | I99: NA | R99: =LEN(C99)+LEN(D99)+LEN(E99)+LEN(F99)+LEN(G99)+LEN(H99) -> 20
A100: fr6317 | B100: frei | C100: 1918 | D100: raber | E100: rudolf | I100: schwyz switzerland | R100: =LEN(C100)+LEN(D100)+LEN(E100)+LEN(F100)+LEN(G100)+LEN(H100) -> 15
...

Sheet aime
A1: id | B1: year | C1: simpname | D1: nationality | E1: edu | F1: prof | G1: org | H1: loc | I1: simpname | J1: nationality | K1: edu | L1: prof | M1: org | N1: loc | O1: cer | P1: tot | R1: extracted/actual | S1: positive | T1: negative
A2: tai83 | B2: 1873 | C2: faber, d | H2: new york city | I2: b | P2: =LEN(C2)+LEN(D2)+LEN(E2)+LEN(F2)+LEN(G2)+LEN(H2) -> 21 | R2: positive | S2: t | T2: f
A3: tai86 | B3: 1873 | C3: firmstone, w | H3: easton pa | P3: =LEN(C3)+LEN(D3)+LEN(E3)+LEN(F3)+LEN(G3)+LEN(H3) -> 21 | R3: negative | S3: f | T3: t
A4: tai137 | B4: 1873 | C4: humphreys, a | H4: new york city | P4: =LEN(C4)+LEN(D4)+LEN(E4)+LEN(F4)+LEN(G4)+LEN(H4) -> 25
A5: tai152 | B5: 1873 | C5: k, n | G5: fountain mill | H5: westmoreland co pa | I5: b | M5: b | N5: b | P5: =LEN(C5)+LEN(D5)+LEN(E5)+LEN(F5)+LEN(G5)+LEN(H5) -> 35 | R5: code
A6: tai201 | B6: 1873 | C6: pearse, j | H6: dauphin co pa | M6: b | N6: b | P6: =LEN(C6)+LEN(D6)+LEN(E6)+LEN(F6)+LEN(G6)+LEN(H6) -> 22 | R6: extracted/actual | S6: positive | T6: negative
A7: tai251 | B7: 1873 | C7: symincton, w | H7: brooklyn n y | I7: b | P7: =LEN(C7)+LEN(D7)+LEN(E7)+LEN(F7)+LEN(G7)+LEN(H7) -> 24 | R7: positive | T7: f
A8: tai287 | B8: 1876 | C8: allen, o | H8: new haven conn | P8: =LEN(C8)+LEN(D8)+LEN(E8)+LEN(F8)+LEN(G8)+LEN(H8) -> 22 | R8: negative | S8: f
A9: tai301 | B9: 1876 | C9: beardslek, c | G9: u.s. navy | H9: washington d.c. | P9: =LEN(C9)+LEN(D9)+LEN(E9)+LEN(F9)+LEN(G9)+LEN(H9) -> 36
A10: tai307 | B10: 1876 | C10: bennett, d | H10: montgomery co pa | M10: b | N10: b | P10: =LEN(C10)+LEN(D10)+LEN(E10)+LEN(F10)+LEN(G10)+LEN(H10) -> 26 | R10: types of mistakes on true positives
A11: tai336 | B11: 1876 | C11: bowir, a | H11: san francisco cal | I11: a | O11: 2 | P11: =LEN(C11)+LEN(D11)+LEN(E11)+LEN(F11)+LEN(G11)+LEN(H11) -> 25 | R11: no mistake
A12: tai367 | B12: 1876 | C12: burden, i | H12: troy n y | P12: =LEN(C12)+LEN(D12)+LEN(E12)+LEN(F12)+LEN(G12)+LEN(H12) -> 17 | R12: source to text | S12: a
A13: tai374 | B13: 1876 | C13: burtue, p | H13: paris france | I13: a | J13: b | O13: 3 | P13: =LEN(C13)+LEN(D13)+LEN(E13)+LEN(F13)+LEN(G13)+LEN(H13) -> 21 | R13: text to class | S13: b
A14: tai430 | B14: 1876 | C14: croxton, s | H14: canal dover ohio | N14: b | P14: =LEN(C14)+LEN(D14)+LEN(E14)+LEN(F14)+LEN(G14)+LEN(H14) -> 26
A15: tai457 | B15: 1876 | C15: duval, c | G15: care wm. ford | H15: san francisco cal | M15: b | N15: b | P15: =LEN(C15)+LEN(D15)+LEN(E15)+LEN(F15)+LEN(G15)+LEN(H15) -> 38
A16: tai462 | B16: 1876 | C16: ellsworta, a | G16: care union iron works | H16: san francisco cal | I16: a | O16: 1 | P16: =LEN(C16)+LEN(D16)+LEN(E16)+LEN(F16)+LEN(G16)+LEN(H16) -> 50
A17: tai547 | B17: 1876 | C17: harden, o | H17: charleston s. c. | N17: b | P17: =LEN(C17)+LEN(D17)+LEN(E17)+LEN(F17)+LEN(G17)+LEN(H17) -> 25
A18: tai593 | B18: 1876 | C18: humphreys, a | H18: new york city | P18: =LEN(C18)+LEN(D18)+LEN(E18)+LEN(F18)+LEN(G18)+LEN(H18) -> 25
A19: tai665 | B19: 1876 | C19: macfarlane, t | H19: quebec canada. | J19: b | P19: =LEN(C19)+LEN(D19)+LEN(E19)+LEN(F19)+LEN(G19)+LEN(H19) -> 27
A20: tai699 | B20: 1876 | C20: mickley, e | H20: hokendauqua pa | P20: =LEN(C20)+LEN(D20)+LEN(E20)+LEN(F20)+LEN(G20)+LEN(H20) -> 24
A21: tai813 | B21: 1876 | C21: ropinson, l | H21: philadelphia pa | I21: a | O21: 2 | P21: =LEN(C21)+LEN(D21)+LEN(E21)+LEN(F21)+LEN(G21)+LEN(H21) -> 26
A22: tai973 | B22: 1876 | C22: wood, h | H22: streator ill | M22: b | P22: =LEN(C22)+LEN(D22)+LEN(E22)+LEN(F22)+LEN(G22)+LEN(H22) -> 19
A23: tai984 | B23: 1877 | C23: agasiz, a | H23: cambridge mass | I23: a | L23: b | O23: 2 | P23: =LEN(C23)+LEN(D23)+LEN(E23)+LEN(F23)+LEN(G23)+LEN(H23) -> 23
A24: tai1030 | B24: 1877 | C24: bonnell, s | H24: new york city | P24: =LEN(C24)+LEN(D24)+LEN(E24)+LEN(F24)+LEN(G24)+LEN(H24) -> 23
A25: tai1093 | B25: 1877 | C25: champin, h | H25: chateauneuf de mazenc dr me | N25: a | O25: 3 | P25: =LEN(C25)+LEN(D25)+LEN(E25)+LEN(F25)+LEN(G25)+LEN(H25) -> 37
A26: tai1220 | B26: 1877 | C26: garlick, e | H26: indianapolis ind | P26: =LEN(C26)+LEN(D26)+LEN(E26)+LEN(F26)+LEN(G26)+LEN(H26) -> 26
A27: tai1287 | B27: 1877 | C27: haut, r | G27: eliza furnaces | H27: pittsburgh pa | P27: =LEN(C27)+LEN(D27)+LEN(E27)+LEN(F27)+LEN(G27)+LEN(H27) -> 34
A28: tai1307 | B28: 1877 | C28: himrop, c | H28: youngstown ohio | I28: a | O28: 2 | P28: =LEN(C28)+LEN(D28)+LEN(E28)+LEN(F28)+LEN(G28)+LEN(H28) -> 24
A29: tai1354 | B29: 1877 | C29: kelly, r | H29: new york city | P29: =LEN(C29)+LEN(D29)+LEN(E29)+LEN(F29)+LEN(G29)+LEN(H29) -> 21
A30: tai1376 | B30: 1877 | C30: lauder, w | F30: manager | H30: riddlesburg pa | L30: b | M30: b | P30: =LEN(C30)+LEN(D30)+LEN(E30)+LEN(F30)+LEN(G30)+LEN(H30) -> 30
A31: tai1469 | B31: 1877 | C31: olcott, e | G31: orinoco exploring and mining co. | H31: walnut st philada | P31: =LEN(C31)+LEN(D31)+LEN(E31)+LEN(F31)+LEN(G31)+LEN(H31) -> 58
A32: tai1494 | B32: 1877 | C32: pickanps, h | H32: nelsonville ohio | I32: a | O32: 4 | P32: =LEN(C32)+LEN(D32)+LEN(E32)+LEN(F32)+LEN(G32)+LEN(H32) -> 27
A33: tai1529 | B33: 1877 | C33: raper, c | H33: easton pa | I33: a | O33: 2 | P33: =LEN(C33)+LEN(D33)+LEN(E33)+LEN(F33)+LEN(G33)+LEN(H33) -> 17
A34: tai1559 | B34: 1877 | C34: ross, w | H34: cincinnati ohio | P34: =LEN(C34)+LEN(D34)+LEN(E34)+LEN(F34)+LEN(G34)+LEN(H34) -> 22
A35: tai1570 | B35: 1877 | C35: sanders, r | H35: philadelphia pa | P35: =LEN(C35)+LEN(D35)+LEN(E35)+LEN(F35)+LEN(G35)+LEN(H35) -> 25
A36: tai1578 | B36: 1877 | C36: scott, n | H36: twenty mile stand ohio | P36: =LEN(C36)+LEN(D36)+LEN(E36)+LEN(F36)+LEN(G36)+LEN(H36) -> 30
A37: tai1596 | B37: 1877 | C37: smeaton, w | G37: columbia school of mines | H37: new york city | M37: b | P37: =LEN(C37)+LEN(D37)+LEN(E37)+LEN(F37)+LEN(G37)+LEN(H37) -> 47
A38: tai1671 | B38: 1877 | C38: warren, h | G38: care a. w. thompson | H38: san francisco cal | P38: =LEN(C38)+LEN(D38)+LEN(E38)+LEN(F38)+LEN(G38)+LEN(H38) -> 45
A39: tai1696 | B39: 1877 | C39: wickrs, g | H39: alleghany co va | I39: a | M39: b | N39: b | O39: 2 | P39: =LEN(C39)+LEN(D39)+LEN(E39)+LEN(F39)+LEN(G39)+LEN(H39) -> 24
A40: tai1810 | B40: 1880 | C40: brown, a | H40: cleveland ohio | P40: =LEN(C40)+LEN(D40)+LEN(E40)+LEN(F40)+LEN(G40)+LEN(H40) -> 22
A41: tai1813 | B41: 1880 | C41: brown, f | H41: cleveland ohio | P41: =LEN(C41)+LEN(D41)+LEN(E41)+LEN(F41)+LEN(G41)+LEN(H41) -> 22
A42: tai1841 | B42: 1880 | C42: case, w | H42: port henry n y | M42: b | P42: =LEN(C42)+LEN(D42)+LEN(E42)+LEN(F42)+LEN(G42)+LEN(H42) -> 21
A43: tai1865 | B43: 1880 | C43: colrtron, c | G43: columbia school of mines | H43: new york city | P43: =LEN(C43)+LEN(D43)+LEN(E43)+LEN(F43)+LEN(G43)+LEN(H43) -> 48
A44: tai1897 | B44: 1880 | C44: crossley, w | D44: english | H44: dalton in furness england | P44: =LEN(C44)+LEN(D44)+LEN(E44)+LEN(F44)+LEN(G44)+LEN(H44) -> 43
A45: tai1914 | B45: 1880 | C45: davenport, r | G45: midvale steel works | H45: nicetown philadelphia | P45: =LEN(C45)+LEN(D45)+LEN(E45)+LEN(F45)+LEN(G45)+LEN(H45) -> 52
A46: tai1921 | B46: 1880 | C46: de, c | H46: cambridgeport mass | I46: b | P46: =LEN(C46)+LEN(D46)+LEN(E46)+LEN(F46)+LEN(G46)+LEN(H46) -> 23
A47: tai1992 | B47: 1880 | C47: freeman, h | H47: alto pass Ill | M47: b | P47: =LEN(C47)+LEN(D47)+LEN(E47)+LEN(F47)+LEN(G47)+LEN(H47) -> 23
A48: tai2007 | B48: 1880 | C48: gardner, g | H48: greenfield mass | N48: b | P48: =LEN(C48)+LEN(D48)+LEN(E48)+LEN(F48)+LEN(G48)+LEN(H48) -> 25
A49: tai2013 | B49: 1880 | C49: gibson, v | H49: eg shakspere new mexico | M49: b | N49: b | P49: =LEN(C49)+LEN(D49)+LEN(E49)+LEN(F49)+LEN(G49)+LEN(H49) -> 32
A50: tai2023 | B50: 1880 | C50: graham, t | H50: philadelphia pa | P50: =LEN(C50)+LEN(D50)+LEN(E50)+LEN(F50)+LEN(G50)+LEN(H50) -> 24
A51: tai2073 | B51: 1880 | C51: henry, e | H51: titusville pa | P51: =LEN(C51)+LEN(D51)+LEN(E51)+LEN(F51)+LEN(G51)+LEN(H51) -> 21
A52: tai2125 | B52: 1880 | C52: janin, h | G52: occidental hotel | H52: san francisco cal | P52: =LEN(C52)+LEN(D52)+LEN(E52)+LEN(F52)+LEN(G52)+LEN(H52) -> 41
A53: tai2141 | B53: 1880 | C53: jossa, n | D53: russian | H53: st petersburg russia | L53: b | P53: =LEN(C53)+LEN(D53)+LEN(E53)+LEN(F53)+LEN(G53)+LEN(H53) -> 35
A54: tai2168 | B54: 1880 | C54: land, w | H54: atlanta ga | I54: b | P54: =LEN(C54)+LEN(D54)+LEN(E54)+LEN(F54)+LEN(G54)+LEN(H54) -> 17
A55: tai2228 | B55: 1880 | C55: mccultlou, e | H55: aurora ill | I55: a | O55: 4 | P55: =LEN(C55)+LEN(D55)+LEN(E55)+LEN(F55)+LEN(G55)+LEN(H55) -> 22
A56: tai2287 | B56: 1880 | C56: noble, c | H56: anniston alabama | P56: =LEN(C56)+LEN(D56)+LEN(E56)+LEN(F56)+LEN(G56)+LEN(H56) -> 24
A57: tai2336 | B57: 1880 | C57: preklor, h | G57: cambria steel co | H57: johnstown pa | I57: a | M57: b | O57: 2 | P57: =LEN(C57)+LEN(D57)+LEN(E57)+LEN(F57)+LEN(G57)+LEN(H57) -> 38
A58: tai2424 | B58: 1880 | C58: sherrerd, j | H58: secaucus n j | P58: =LEN(C58)+LEN(D58)+LEN(E58)+LEN(F58)+LEN(G58)+LEN(H58) -> 23
A59: tai2458 | B59: 1880 | C59: strieby, w | H59: santa f new mexico | L59: b | M59: b | N59: b | P59: =LEN(C59)+LEN(D59)+LEN(E59)+LEN(F59)+LEN(G59)+LEN(H59) -> 28
A60: tai2483 | B60: 1880 | C60: thompson, h | H60: pottsville pa | P60: =LEN(C60)+LEN(D60)+LEN(E60)+LEN(F60)+LEN(G60)+LEN(H60) -> 24
A61: tai2484 | B61: 1880 | C61: thonarp, l | H61: liege belgium | I61: a | O61: 2 | P61: =LEN(C61)+LEN(D61)+LEN(E61)+LEN(F61)+LEN(G61)+LEN(H61) -> 23
A62: tai2489 | B62: 1880 | C62: townsend, d | H62: philadelphia pa | P62: =LEN(C62)+LEN(D62)+LEN(E62)+LEN(F62)+LEN(G62)+LEN(H62) -> 26
A63: tai2499 | B63: 1880 | C63: van vornuts, w | H63: manhattanville n y | I63: a | O63: 4 | P63: =LEN(C63)+LEN(D63)+LEN(E63)+LEN(F63)+LEN(G63)+LEN(H63) -> 32
A64: tai2501 | B64: 1880 | C64: van, b | H64: eureka nevada | I64: b | P64: =LEN(C64)+LEN(D64)+LEN(E64)+LEN(F64)+LEN(G64)+LEN(H64) -> 19
A65: tai2552 | B65: 1880 | C65: williams, w | G65: gautier steel co. | H65: johnstown pa | M65: b | N65: b | P65: =LEN(C65)+LEN(D65)+LEN(E65)+LEN(F65)+LEN(G65)+LEN(H65) -> 40
A66: tai2587 | B66: 1882 | C66: allen, j | H66: ore knob n c | M66: b | N66: a | O66: 3 | P66: =LEN(C66)+LEN(D66)+LEN(E66)+LEN(F66)+LEN(G66)+LEN(H66) -> 20
A67: tai2640 | B67: 1882 | C67: bertolet, a | H67: crown point n y | M67: b | P67: =LEN(C67)+LEN(D67)+LEN(E67)+LEN(F67)+LEN(G67)+LEN(H67) -> 26
A68: tai2660 | B68: 1882 | C68: borpa, e | H68: philadelphia pa | I68: a | O68: 2 | P68: =LEN(C68)+LEN(D68)+LEN(E68)+LEN(F68)+LEN(G68)+LEN(H68) -> 23
A69: tai2673 | B69: 1882 | C69: brakm, h | H69: new york city | P69: =LEN(C69)+LEN(D69)+LEN(E69)+LEN(F69)+LEN(G69)+LEN(H69) -> 21
A70: tai2682 | B70: 1882 | C70: brinley, c | H70: philadelphia pa | P70: =LEN(C70)+LEN(D70)+LEN(E70)+LEN(F70)+LEN(G70)+LEN(H70) -> 25
A71: tai2699 | B71: 1882 | C71: brown, h | H71: cleveland ohio | P71: =LEN(C71)+LEN(D71)+LEN(E71)+LEN(F71)+LEN(G71)+LEN(H71) -> 22
A72: tai2815 | B72: 1882 | C72: coxe, a | H72: drifton pa | M72: b | P72: =LEN(C72)+LEN(D72)+LEN(E72)+LEN(F72)+LEN(G72)+LEN(H72) -> 17
A73: tai2820 | B73: 1882 | C73: cramer, e | H73: montezuma colorado | N73: b | P73: =LEN(C73)+LEN(D73)+LEN(E73)+LEN(F73)+LEN(G73)+LEN(H73) -> 27
A74: tai2822 | B74: 1882 | C74: cranz, w | H74: tucson arizona | M74: b | N74: b | P74: =LEN(C74)+LEN(D74)+LEN(E74)+LEN(F74)+LEN(G74)+LEN(H74) -> 22
A75: tai2842 | B75: 1882 | C75: curren, j | H75: pottsville pa | I75: b | P75: =LEN(C75)+LEN(D75)+LEN(E75)+LEN(F75)+LEN(G75)+LEN(H75) -> 22
A76: tai2950 | B76: 1882 | C76: franklin, w | H76: ashland md | M76: b | P76: =LEN(C76)+LEN(D76)+LEN(E76)+LEN(F76)+LEN(G76)+LEN(H76) -> 21
A77: tai2983 | B77: 1882 | C77: goodale, c | H77: charleston arizona | M77: b | P77: =LEN(C77)+LEN(D77)+LEN(E77)+LEN(F77)+LEN(G77)+LEN(H77) -> 28
A78: tai2999 | B78: 1882 | C78: griffin, j | H78: phoenixville pa | P78: =LEN(C78)+LEN(D78)+LEN(E78)+LEN(F78)+LEN(G78)+LEN(H78) -> 25
A79: tai3024 | B79: 1882 | C79: hann, i | H79: sharpsburg pa | I79: a | M79: b | O79: 2 | P79: =LEN(C79)+LEN(D79)+LEN(E79)+LEN(F79)+LEN(G79)+LEN(H79) -> 20
A80: tai3033 | B80: 1882 | C80: harris, w | H80: montclair nj | P80: =LEN(C80)+LEN(D80)+LEN(E80)+LEN(F80)+LEN(G80)+LEN(H80) -> 21
A81: tai3047 | B81: 1882 | C81: hausbina, f | H81: tin cup colorado | I81: a | O81: 3 | P81: =LEN(C81)+LEN(D81)+LEN(E81)+LEN(F81)+LEN(G81)+LEN(H81) -> 27
A82: tai3055 | B82: 1882 | C82: hctron, f | H82: new york city | I82: a | O82: 3 | P82: =LEN(C82)+LEN(D82)+LEN(E82)+LEN(F82)+LEN(G82)+LEN(H82) -> 22
A83: tai3111 | B83: 1882 | C83: hurrox, w | H83: new york city | P83: =LEN(C83)+LEN(D83)+LEN(E83)+LEN(F83)+LEN(G83)+LEN(H83) -> 22
A84: tai3241 | B84: 1882 | C84: lowe, f | H84: batopilas chihuahua | I84: b | P84: =LEN(C84)+LEN(D84)+LEN(E84)+LEN(F84)+LEN(G84)+LEN(H84) -> 26
A85: tai3299 | B85: 1882 | C85: mckenziz, j | H85: new york city | I85: a | O85: 2 | P85: =LEN(C85)+LEN(D85)+LEN(E85)+LEN(F85)+LEN(G85)+LEN(H85) -> 24
A86: tai3411 | B86: 1882 | C86: parsons, c | H86: boston mass | P86: =LEN(C86)+LEN(D86)+LEN(E86)+LEN(F86)+LEN(G86)+LEN(H86) -> 21
A87: tai3420 | B87: 1882 | C87: pecuin, e | H87: cleveland ohio | I87: a | O87: 2 | P87: =LEN(C87)+LEN(D87)+LEN(E87)+LEN(F87)+LEN(G87)+LEN(H87) -> 23
A88: tai3499 | B88: 1882 | C88: rick, a | H88: stockholm sweden | I88: a | O88: 3 | P88: =LEN(C88)+LEN(D88)+LEN(E88)+LEN(F88)+LEN(G88)+LEN(H88) -> 23
A89: tai3499 | B89: 1882 | C89: rick, a | H89: stockholm sweden | I89: a | O89: 3 | P89: =LEN(C89)+LEN(D89)+LEN(E89)+LEN(F89)+LEN(G89)+LEN(H89) -> 23
A90: tai3578 | B90: 1882 | C90: serz, g | H90: bonne terre mo | I90: a | M90: b | N90: b | O90: 2 | P90: =LEN(C90)+LEN(D90)+LEN(E90)+LEN(F90)+LEN(G90)+LEN(H90) -> 21
A91: tai3628 | B91: 1882 | C91: storper, e | H91: ophir colorado | I91: a | O91: 3 | P91: =LEN(C91)+LEN(D91)+LEN(E91)+LEN(F91)+LEN(G91)+LEN(H91) -> 24
A92: tai3652 | B92: 1882 | C92: terrt, w | H92: mineville n y | I92: a | M92: b | O92: 4 | P92: =LEN(C92)+LEN(D92)+LEN(E92)+LEN(F92)+LEN(G92)+LEN(H92) -> 21
A93: tai3661 | B93: 1882 | C93: thomas, j | H93: catasauqua pa | P93: =LEN(C93)+LEN(D93)+LEN(E93)+LEN(F93)+LEN(G93)+LEN(H93) -> 22
A94: tai3669 | B94: 1882 | C94: thomson, j | H94: bergen point n j | P94: =LEN(C94)+LEN(D94)+LEN(E94)+LEN(F94)+LEN(G94)+LEN(H94) -> 26
A95: tai3687 | B95: 1882 | C95: trompson, h | H95: pottsville pa | I95: a | O95: 2 | P95: =LEN(C95)+LEN(D95)+LEN(E95)+LEN(F95)+LEN(G95)+LEN(H95) -> 24
A96: tai3703 | B96: 1882 | C96: van, l | H96: granite basin cal | I96: b | M96: b | P96: =LEN(C96)+LEN(D96)+LEN(E96)+LEN(F96)+LEN(G96)+LEN(H96) -> 23
A97: tai3703 | B97: 1882 | C97: van, l | H97: granite basin cal | I97: b | M97: b | P97: =LEN(C97)+LEN(D97)+LEN(E97)+LEN(F97)+LEN(G97)+LEN(H97) -> 23
A98: tai3782 | B98: 1882 | C98: witlarp, h | H98: port henry n y | I98: a | M98: b | O98: 2 | P98: =LEN(C98)+LEN(D98)+LEN(E98)+LEN(F98)+LEN(G98)+LEN(H98) -> 24
A99: tai3786 | B99: 1882 | C99: wittmack, c | H99: strasburg germany | P99: =LEN(C99)+LEN(D99)+LEN(E99)+LEN(F99)+LEN(G99)+LEN(H99) -> 28
A100: tai3855 | B100: 1884 | C100: bachman, f | H100: phoenixville pa | P100: =LEN(C100)+LEN(D100)+LEN(E100)+LEN(F100)+LEN(G100)+LEN(H100) -> 25
...

Sheet mybprueba
A1: id | B1: year | C1: text | D1: company | E1: Correct
A2: myb24 | B2: 1887 | C2: For 1886-7, 10s. per share interim dividends have been paid. | D2: Adamant Diamond Mining Company Limited | E2: t
A3: myb675 | B3: 1887 | C3: the two boards which appear more advantageous to both companies than those | D3: Anglo African Diamond Mining Company | E3: t
A4: myb1359 | B4: 1887 | C4: mining, Ac. The company also possesses certain contracts and shares in the | D4: Aruba Island Gold Mining Company | E4: t
A5: myb3650 | B5: 1887 | C5: preference shares of the new company. | D5: Canadian Copper And Sulphur Company | E5: t
A6: myb4534 | B6: 1887 | C6: Less cost of mining and milling, at £2 3s. per ton... ... 10,750 | D6: Charters Towers Queensland Gold Mining | E6: t
A7: myb8055 | B7: 1887 | C7: An important feature connected with the property is that sufficient work has been done to | D7: Essaman Gold Mining Company Limited | E7: t
A8: myb8488 | B8: 1887 | C8: Liquidator s Offices. | D8: Frederick Valley Gold Mining Limited | E8: t
A9: myb10901 | B9: 1887 | C9: expectations from the lowest to the furthest extended part of the mine. | D9: Indian Consolidated Gold Company Limited | E9: t
A10: myb12462 | B10: 1887 | C10: but half-yearly meetings are held in May to receive the agent s report. The | D10: Leadhills Silver Lead Mining And | E10: t
A11: myb15562 | B11: 1887 | C11: Secretary. Offices. | D11: New Emma Silver Mining Company | E11: t
A12: myb22289 | B12: 1887 | C12: tbe damage sustained at the mine. | D12: South Darren Mining Company Limited | E12: t
A13: myb23311 | B13: 1887 | C13: TASMANIAN TIN MINING COMPANY, | D13: Tasmanian Tin Mining Company Limited | E13: t
... A40: myb93570 | B40: 1891 | C40: Sinclair MacLeay, merchant, 167, Winchester | D40: Adventurers Ashanti And Wassau Limited | E40: b
A41: myb94175 | B41: 1891 | C41: Solicitors. Mining Manager. Auditor. | D41: Anglo Saxon Gold Mining Syndicate
A42: myb99090 | B42: 1891 | C42: allotted is 16,000, on which £8,687 10s. has been paid, being 10s. 3d. per share | D42: Day Dawn And Norfolk Mines
A43: myb107745 | B43: 1891 | C43: Auditor. Secretary. Offices. | D43: New Pittsburg Grass Valley Gold
A44: myb108524 | B44: 1891 | C44: have been retained. | D44: North Australian Mining Company Limited
A45: myb110915 | B45: 1891 | C45: ment, and the balance as required in sums of 2s., at intervals of not less than | D45: Quindio Quicksilver Mines Limited
A46: myb117300 | B46: 1891 | C46: Howard Hodges. 17 and 18, Basinghall Street, E.C. | D46: Barrett Gold Mining Company Limited
A47: myb119625 | B47: 1891 | C47: developing Matabeleland and territories in South ana Central Africa, and arrangements were | D47: Exploring Land Minerals Limited
A48: myb120632 | B48: 1891 | C48: GRIQUALAND WEST DIAMOND MINING COMPANY, | D48: Griqualand West Diamond Mining Company
A49: myb120861 | B49: 1891 | C49: tain if any of the reefs make below it, before going to the expense of sinking permanent shafts | D49: Henderson And Forbes Gold Mining
A50: myb127065 | B50: 1891 | C50: the remaining 10,000 shares at present, they decided to shut down the mine temporarily. | D50: Weltevreden Estate And Gold Mining
A51: myb136127 | B51: 1893 | C51: account of these preference Bhares the liabilities at the mine, which unfortunately accumulated | D51: Guadalupe Syndicate Limited
A52: myb142096 | B52: 1893 | C52: carried to reserve, and £818 3a. 3d. carried forward. Tho transfer form used is | D52: Nundydroog Gold Mining Company
... A284: myb835405 | B284: 1917 | C284: £33,000. | D284: Associated Queensland Mines Limited
A285: myb841789 | B285: 1917 | C285: 100000 | D285: Calumet And Hecla Mining Company
A286: myb842127 | B286: 1917 | C286: to which they were entitled on redemption. The object | D286: Camp Bird Limited Bakqiimmp
A287: myb842218 | B287: 1917 | C287: yOUI instal | D287: Canadian Collieries Dunsmuir Limited
A288: myb842391 | B288: 1917 | C288: received on shares held in the Mining Corpn. of Canada, Ltd., amounted to | D288: Canadian Mining Corporation Limited
A289: myb842705 | B289: 1917 | C289: mini was dissolved. | D289: Carabaya Mining Syndicate Limited
A290: myb846603 | B290: 1917 | C290: September 30, 1912, when the new plant, which consists | D290: Consolidated Langlaagte Mines Limited
A291: myb861246 | B291: 1917 | C291: shares Nos. | D291: Johannesburg Forest And Land Limited
A292: myb861308 | B292: 1917 | C292: the Atlas Works | D292: John Brown And Company Limited
A293: myb862015 | B293: 1917 | C293: loads; washing was suspended July, 1907, but during 1910 the blue ground on | D293: Kamfersdam Toinrs Limited
A294: myb862469 | B294: 1917 | C294: An ammonia leaching plant | D294: Kennecott Copper Corporation
A295: myb873298 | B295: 1917 | C295: NEw HERIoT GoLD MINING comPANY, LIMITED, | D295: New Heriwt Gold Mining Oopany
A296: myb874013 | B296: 1917 | C296: Havercroft and South Hiendley, four miles from | D296: New Monckton Collieries Limited
A297: myb874330 | B297: 1917 | C297: the Witwatersrand. | D297: New Radnwr Limited
... A386: myb1145358 | B386: 1923 | C386: Co., Ltd., the Plymouth Consolidated group of mines, together with adjoining | D386: Plymouth Consolidated Gold Mines Limited

Sheet mybprueba (2)
A1: id | B1: year | C1: text | D1: company | E1: correct
A2: 24762 | B2: 1887 | C2: quarters ending November 1, 1886, February 1 and May 2, 1887, and at the rate | D2: Viola Company Limited | E2: t
A3: 31014 | B3: 1888 | C3: has left a net profit of £1,526 5s. lod. | D3: Copiapo Mining Company Limited | E3: t
A4: 32696 | B4: 1888 | C4: DOURO GOLD MINES, LIMITED. | D4: Douro Gold Mines Limited | E4: t
A5: 76102 | B5: 1889 | C5: 1882, 9,740 | D5: Rio Tinto Company Limited | E5: t
A6: 90025 | B6: 1889 | C6: the amount placed to reserve fund and working expenses, £U,4&8 19s. 5d. ; leaving m &ea | D6: Salisbury Extension Gold Mining Company | E6: t
A7: 95364 | B7: 1891 | C7: The company is now being wound up by the Court of Chancery, an order for | D7: Bishop Creek Gold Mining Company | E7: t
A8: 108894 | B8: 1891 | C8: apatite, copper, gold, silver, lead, and other mines in Norway and Sweden. | D8: Norway Mining Corporation Limited | E8: t
A9: 126940 | B9: 1891 | C9: ANNUM, REPOKT. | D9: Wassau Gold Coast Mining Company | E9: t
A10: 139237 | B10: 1893 | C10: The director have to report that the development of tho company s property has l cen | D10: Mobuta Gold And Silveb | E10: t
A11: 146164 | B11: 1893 | C11: The authorised capital is £12,000, in 12,000 shares of £1 each, of which 7,663 | D11: Spanish Prospecting Syndicate Limited | E11: t
A12: 166547 | B12: 1894 | C12: The authorised capital is £30,000, in 30,000 shares of £1 each, of which 20,995 | D12: East Grassington Mines Limited | E12: t
A13: 166617 | B13: 1894 | C13: EAST POOL MINING COMPANY. | D13: East Pool Mining Company | E13: t
... A22: 309336 | B22: 1908 | C22: British Borneo Exploration, South West Africa Co., 4c, also debentures in the | D22: Anglo Continentall Gold Syndicate | E22: t
A23: 326850 | B23: 1908 | C23: 385842 | D23: Rio Tinto Company Limited | E23: t
A24: 328040 | B24: 1908 | C24: Thomas Honey, Chairman I Fredk. C. Marten. | H. Ghidsal. I C. C. Banc, i T. E. Honey, | D24: Servian Syndicate Limited | E24: f
A25: 334354 | B25: 1909 | C25: 3s. 6d. ; 1907 : highest, 4s. 6d. ; lowest, 3d. ; 1908 : highest, 2s. 9d. ; lowest, nil. | D25: Day Dawn Gold Mines Limited | E25: t
A26: 340092 | B26: 1909 | C26: underwriting 210,000 shares, also to the former owners of the property a sum of | D26: Tasmanian Gold Company Limited | E26: t
A27: 343048 | B27: 1909 | C27: into 143,066 ordinary and 176,250 deferred shares of 103. each, the deferred | D27: Ashan And Concessio Ite | E27: t
A28: 345460 | B28: 1909 | C28: vendors received £30,000 in fully-paid shares. In 1891 the company purchased | D28: City And Suburban Gold Mining | E28: t
A29: 352523 | B29: 1909 | C29: The authorised capital | D29: Koffyfontein Estates Limited | E29: t
A30: 362909 | B30: 1909 | C30: call on 3,427 shares was 6s., payable Juno Oth, 1907. | D30: Vaal River Diamond Company Limited | E30: t
A31: 387867 | B31: 1909 | C31: an accumulating sinking fund of £2,000 per annum, but after November 11th, | D31: Wemyss Collieries Trust Limited | E31: t
A32: 403854 | B32: 1910 | C32: share for every two shares held : | D32: Gelden Huis Deep Limited | E32: t
A33: 404537 | B33: 1910 | C33: 17,000 fully-paid shares and £3,670 debentures in the Bartie Corporation, Ltd. | D33: Gold Coast Investment Company | E33: t
A34: 436275 | B34: 1910 | C34: properties and rights at Lymni, Cyprus. The consideration was £4,000 in | D34: Lymni Copper Mining Syndicate Limited | E34: t
A35: 458483 | B35: 1911 | C35: general miners in Nigeria. The authorised capital is £6,000 in 6,000 shares of £1 | D35: Alluvi Syndicate Lnlgeri Limited | E35: t
... A95: 1075979 | B95: 1922 | C95: creditors £246; share premium account £4,708. | D95: Anglo French Ural Syndicate Limited | E95: t
A96: 1110534 | B96: 1922 | C96: 2552064 | D96: Sungel Best Mines Limited | E96: b
A97: 1116633 | B97: 1923 | C97: Africa, Ltd., 1,000 North Oogies Witbank Collieries, Ltd., 1,006 Tait and 00., | D97: African Land And Investment Limited | E97: t
A98: 1116662 | B98: 1923 | C98: District, Transvaal. In conjunction with the Southern Oregon Goldfields, Ltd., | D98: African Mining Agency Limited | E98: t
A99: 1127716 | B99: 1923 | C99: net profits from the working of the mines is to be applied in paying off the prior | D99: Dunderland Iron Ore Company Limited | E99: t
A100: 1153004 | B100: 1923 | C100: Box 2269, The Corner House, Johannesburg. | D100: Transvaal Coal Corporation Limited | E100: t
A101: 1153849 | B101: 1923 | C101: holders at par. | D101: United Collieries Limited | E101: t
E102: 11
E103: 0.89

Sheet Sheet1
B1: company/organization | C1: capital | D1: year regist | E1: location | F1: lastname | G1: firstname | H1: middlename | I1: role | J1: nationality | K1: education | L1: Overall | W1: MYB | X1: AMM | Y1: MMM | Z1: ALUMNI | AA1: AIME
A2: myb | B2: 0.43765281 | C2: 0.99266504 | D2: 0.99266504 | E2: 0.93459658 | F2: 0.88753056 | G2: 0.94132029 | H2: 0.91687042 | I2: 0.96577017 | L2: =AVERAGE(B2:K2) -> 0.88363386 | V2: Company/Organization | W2: 0.43765281 | X2: 0.73838631 | Y2: 0.92665037 | Z2: 0.72616137 | AA2: 0.89731051
A3: amm | B3: 0.73838631 | C3: 0.98777506 | D3: 0.98288509 | E3: 0.96495518 | F3: 0.83129584 | G3: 0.97555012 | H3: 0.87775061 | I3: 0.98288509 | L3: =AVERAGE(B3:K3) -> 0.91768541 | V3: Capital | W3: 0.99266504 | X3: 0.98777506 | Y3: 0.96821516 | AA3: 0
A4: mmm | B4: 0.92176039 | C4: 0.96821516 | D4: 0.99755501 | E4: 0.88997555 | F4: 0.7408313 | G4: 0.94621027 | H4: 0.76528117 | I4: 0.96332518 | L4: =AVERAGE(B4:K4) -> 0.89914425 | V4: Year Regist | W4: 0.99266504 | X4: 0.98288509 | Y4: 0.99755501 | Z4: 0.799511 | AA4: 0
A5: alumni | B5: 0.72616137 | D5: 0.799511 | F5: 0.94621027 | G5: 0.93887531 | H5: 0.66992665 | I5: 0.76772616 | L5: =AVERAGE(B5:K5) -> 0.80806846 | V5: Location | W5: 0.75794621 | X5: 0.94376528 | Y5: 0.88997555 | AA5: 0.92665037
A6: AIME | B6: 0.89731051 | E6: 0.92420538 | F6: 0.86552567 | G6: 0.86552567 | H6: 0.86552567 | I6: 0.95354523 | J6: 0.99511002 | K6: 1 | L6: =AVERAGE(B6:K6) -> 0.92084352 | V6: Lastname | W6: 0.88753056 | X6: 0.83129584 | Y6: 0.7408313 | Z6: 0.94621027 | AA6: 0.86552567
V7: Firstname | W7: 0.94132029 | X7: 0.97555012 | Y7: 0.94621027 | Z7: 0.93887531
V8: Middlename | W8: 0.91687042 | X8: 0.87775061 | Y8: 0.76528117 | Z8: 0.66992665
B9: simpname | C9: nationality | D9: edu | E9: prof | F9: org | G9: loc | V9: Role | W9: 0.96577017 | X9: 0.98288509 | Y9: 0.96332518 | Z9: 0.76772616 | AA9: 0.95599022
B10: 0.86552567 | C10: 0.99511002 | D10: 1 | V10: Nationality | AA10: 0.99511002
V11: Education | AA11: 1
B12: myb | C12: amm | D12: mmm | E12: Overall | F12: alumni | G12: AIME | H12: Overall | J12: =UPPER(A12) | K12: =UPPER(B12) -> MYB | L12: =UPPER(C12) -> AMM | M12: =UPPER(D12) -> MMM | N12: =UPPER(E12) -> OVERALL | O12: =UPPER(F12) -> ALUMNI | P12: =UPPER(G12) -> AIME | Q12: =UPPER(H12) -> OVERALL | R12: =UPPER(I12) | V12: Overall | W12: 0.86155257 | X12: 0.91503667 | Y12: 0.8997555 | Z12: 0.80806846 | AA12: 0.9400978
A13: N | B13: 409 | C13: 384 | D13: 368 | E13: =SUM(B13:D13) -> 1161 | F13: 384 | G13: 382 | H13: =SUM(F13:G13) -> 766 | J13: N | K13: =B13 -> 409 | L13: =C13 -> 384 | M13: =D13 -> 368 | N13: =E13 -> 1161 | O13: =F13 -> 384 | P13: =G13 -> 382 | Q13: =H13 -> 766 | V13: CER | W13: 0.013907582 | X13: 0.0052818592 | Y13: 0.0016250621 | Z13: 0.0032051282 | AA13: 0.010342814
A14: CER | B14: =mybt!Z412 -> 0.013907582 | C14: =ammt!Y387 -> 0.0052818592 | D14: =mmmt!AE371 -> 0.0016250621 | E14: =((B$13*B14)+(C$13*C14)+(D$13*D14))/E$13 -> 0.0071614623 | F14: =alumnit!Q387 -> 0.0032051282 | G14: =aime!O385 -> 0.010342814 | H14: =((F$13*F14)+(G$13*G14))/H$13 -> 0.0067646531 | J14: CER | K14: =B14 -> 0.013907582 | L14: =C14 -> 0.0052818592 | M14: =D14 -> 0.0016250621 | N14: =E14 -> 0.0071614623 | O14: =F14 -> 0.0032051282 | P14: =G14 -> 0.010342814 | Q14: =H14 -> 0.0067646531
A15: company/organization | B15: =mybt!O412 -> 0.43765281 | C15: =ammt!N387 -> 0.73838631 | D15: =mmmt!Q371 -> 0.92665037 | E15: =((B$13*B15)+(C$13*C15)+(D$13*D15))/E$13 -> 0.69211686 | F15: =alumnit!O387 -> 0.72616137 | G15: =aime!M385 -> 0.89731051 | H15: =((F$13*F15)+(G$13*G15))/H$13 -> 0.81151251 | J15: =PROPER(A15) -> Company/Organization | K15: =B15 -> 0.43765281 | L15: =C15 -> 0.73838631 | M15: =D15 -> 0.92665037 | N15: =E15 -> 0.69211686 | O15: =F15 -> 0.72616137 | P15: =G15 -> 0.89731051 | Q15: =H15 -> 0.81151251
A16: capital | B16: =mybt!P412 -> 0.99266504 | C16: =ammt!O387 -> 0.98777506 | D16: =mmmt!R371 -> 0.96821516 | E16: =((B$13*B16)+(C$13*C16)+(D$13*D16))/E$13 -> 0.98329785 | H16: =((F$13*F16)+(G$13*G16))/H$13 -> 0 | J16: =PROPER(A16) -> Capital | K16: =B16 -> 0.99266504 | L16: =C16 -> 0.98777506 | M16: =D16 -> 0.96821516 | N16: =E16 -> 0.98329785 | Q16: =H16 -> 0
A17: year regist | B17: =mybt!R412 -> 0.99266504 | C17: =ammt!Q387 -> 0.98288509 | D17: =mmmt!X371 -> 0.99755501 | E17: =((B$13*B17)+(C$13*C17)+(D$13*D17))/E$13 -> 0.99098029 | F17: =alumnit!J387 -> 0.799511 | H17: =F17 -> 0.799511 | J17: =PROPER(A17) -> Year Regist | K17: =B17 -> 0.99266504 | L17: =C17 -> 0.98288509 | M17: =D17 -> 0.99755501 | N17: =E17 -> 0.99098029 | O17: =F17 -> 0.799511 | Q17: =H17 -> 0.799511
A18: location | B18: =mybt!U412 -> 0.75794621 | C18: =ammt!S387 -> 0.94376528 | D18: =mmmt!Y371 -> 0.88997555 | E18: =((B$13*B18)+(C$13*C18)+(D$13*D18))/E$13 -> 0.86125484 | G18: =aime!N385 -> 0.92665037 | H18: =((F$13*F18)+(G$13*G18))/H$13 -> 0.46211546 | J18: =PROPER(A18) -> Location | K18: =B18 -> 0.75794621 | L18: =C18 -> 0.94376528 | M18: =D18 -> 0.88997555 | N18: =E18 -> 0.86125484 | P18: =G18 -> 0.92665037 | Q18: =H18 -> 0.46211546
A19: lastname | B19: =mybt!V412 -> 0.88753056 | C19: =ammt!U387 -> 0.83129584 | D19: =mmmt!AA371 -> 0.7408313 | E19: =((B$13*B19)+(C$13*C19)+(D$13*D19))/E$13 -> 0.82243197 | F19: =alumnit!K387 -> 0.94621027 | G19: =aime!I385 -> 0.86552567 | H19: =((F$13*F19)+(G$13*G19))/H$13 -> 0.9059733 | J19: =PROPER(A19) -> Lastname | K19: =B19 -> 0.88753056 | L19: =C19 -> 0.83129584 | M19: =D19 -> 0.7408313 | N19: =E19 -> 0.82243197 | O19: =F19 -> 0.94621027 | P19: =G19 -> 0.86552567 | Q19: =H19 -> 0.9059733
A20: firstname | B20: =mybt!W412 -> 0.94132029 | C20: =ammt!V387 -> 0.97555012 | D20: =mmmt!AB371 -> 0.94621027 | E20: =((B$13*B20)+(C$13*C20)+(D$13*D20))/E$13 -> 0.95419175 | F20: =alumnit!L387 -> 0.93887531 | H20: =F20 -> 0.93887531 | J20: =PROPER(A20) -> Firstname | K20: =B20 -> 0.94132029 | L20: =C20 -> 0.97555012 | M20: =D20 -> 0.94621027 | N20: =E20 -> 0.95419175 | O20: =F20 -> 0.93887531 | Q20: =H20 -> 0.93887531
A21: middlename | B21: =mybt!X412 -> 0.91687042 | C21: =ammt!W387 -> 0.87775061 | D21: =mmmt!AC371 -> 0.76528117 | E21: =((B$13*B21)+(C$13*C21)+(D$13*D21))/E$13 -> 0.85588261 | F21: =alumnit!M387 -> 0.66992665 | H21: =F21 -> 0.66992665 | J21: =PROPER(A21) -> Middlename | K21: =B21 -> 0.91687042 | L21: =C21 -> 0.87775061 | M21: =D21 -> 0.76528117 | N21: =E21 -> 0.85588261 | O21: =F21 -> 0.66992665 | Q21: =H21 -> 0.66992665
A22: role | B22: =mybt!Y412 -> 0.96577017 | C22: =ammt!X387 -> 0.98288509 | D22: =mmmt!AD371 -> 0.96332518 | E22: =((B$13*B22)+(C$13*C22)+(D$13*D22))/E$13 -> 0.97065593 | F22: =alumnit!N387 -> 0.76772616 | G22: =aime!L385 -> 0.95599022 | H22: =((F$13*F22)+(G$13*G22))/H$13 -> 0.86161242 | J22: =PROPER(A22) -> Role | K22: =B22 -> 0.96577017 | L22: =C22 -> 0.98288509 | M22: =D22 -> 0.96332518 | N22: =E22 -> 0.97065593 | O22: =F22 -> 0.76772616 | P22: =G22 -> 0.95599022 | Q22: =H22 -> 0.86161242
A23: nationality | E23: =((B$13*B23)+(C$13*C23)+(D$13*D23))/E$13 -> 0 | G23: =aime!J385 -> 0.99511002 | H23: =G23 -> 0.99511002 | J23: =PROPER(A23) -> Nationality | P23: =G23 -> 0.99511002 | Q23: =H23 -> 0.99511002
A24: education | E24: =((B$13*B24)+(C$13*C24)+(D$13*D24))/E$13 -> 0 | G24: =aime!K385 -> 1 | H24: =G24 -> 1 | J24: =PROPER(A24) -> Education | P24: =G24 -> 1 | Q24: =H24 -> 1
A25: Overall | B25: =AVERAGE(B15:B24) -> 0.86155257 | C25: =AVERAGE(C15:C24) -> 0.91503667 | D25: =AVERAGE(D15:D24) -> 0.8997555 | E25: =((B$13*B25)+(C$13*C25)+(D$13*D25))/E$13 -> 0.89135151 | F25: =AVERAGE(F15:F24) -> 0.80806846 | G25: =AVERAGE(G15:G24) -> 0.9400978 | H25: =((F$13*F25)+(G$13*G25))/H$13 -> 0.87391077 | J25: =PROPER(A25) -> Overall | K25: =B25 -> 0.86155257 | L25: =C25 -> 0.91503667 | M25: =D25 -> 0.8997555 | N25: =E25 -> 0.89135151 | O25: =F25 -> 0.80806846 | P25: =G25 -> 0.9400978 | Q25: =H25 -> 0.87391077
B29: Last name | C29: First name | D29: Middle name | E29: Education | F29: Company/organization | G29: Location | H29: Position
B30: 0.94010417 | C30: 0.9375 | D30: 0.9375 | E30: 1 | F30: 0.9453125 | G30: 0.94010417 | H30: 1
B31: Item | C31: Accuracy
B32: Last name | C32: 0.94010417
B33: First name | C33: 0.9375
B34: Middle name | C34: 0.9375
B35: Education | C35: 1
B36: Company/organization | C36: 0.9453125
B37: Location | C37: 0.94010417
B38: Position | C38: 1
B39: Overall | C39: =AVERAGE(C32:C38) -> 0.95721726
B42: Item | C42: MYB | D42: AMM | E42: MMM | F42: ALUMNI | G42: AIME | H42: Overall | M42: ALUMNI | N42: AIME | O42: OVERALL | S42: MYB | T42: AMM | U42: MMM | V42: OVERALL
B43: N | C43: 409 | D43: 384 | E43: 368 | F43: 384 | G43: 382 | H43: 1927 | L43: N | M43: 384 | N43: 382 | O43: 766 | R43: N | S43: 409 | T43: 384 | U43: 368 | V43: 1161
A44: CER | C44: 0.013907582 | D44: 0.0052818592 | E44: 0.0016250621 | F44: 0.0032051282 | G44: 0.010342814 | H44: 0.0070037271 | K44: CER | M44: 0.0032051282 | N44: 0.010342814 | O44: 0.0067646531 | Q44: CER | S44: 0.013907582 | T44: 0.0052818592 | U44: 0.0016250621 | V44: 0.0071614623
A45: WACC | B45: Overall | C45: 0.86155257 | D45: 0.91503667 | E45: 0.8997555 | F45: 0.80806846 | G45: 0.9400978 | H45: 0.88441866 | K45: WACC | L45: Company/Organization | M45: 0.72616137 | N45: 0.89731051 | O45: 0.81151251 | Q45: WACC | R45: Company/Organization | S45: 0.43765281 | T45: 0.73838631 | U45: 0.92665037 | V45: 0.69211686
B46: Company/Organization | C46: 0.43765281 | D46: 0.73838631 | E46: 0.92665037 | F46: 0.72616137 | G46: 0.89731051 | H46: 0.73957772 | L46: Year Regist | M46: 0.799511 | O46: 0.799511 | R46: Capital | S46: 0.99266504 | T46: 0.98777506 | U46: 0.96821516 | V46: 0.98329785
B47: Capital | C47: 0.99266504 | D47: 0.98777506 | E47: 0.96821516 | H47: 0.98329785 | L47: Location | N47: 0.92665037 | O47: 0.46211546 | R47: Year Regist | S47: 0.99266504 | T47: 0.98288509 | U47: 0.99755501 | V47: 0.99098029
B48: Year Regist | C48: 0.99266504 | D48: 0.98288509 | E48: 0.99755501 | F48: 0.799511 | H48: 0.94339181 | L48: Lastname | M48: 0.94621027 | N48: 0.86552567 | O48: 0.9059733 | R48: Location | S48: 0.75794621 | T48: 0.94376528 | U48: 0.88997555 | V48: 0.86125484
B49: Location | C49: 0.75794621 | D49: 0.94376528 | E49: 0.88997555 | G49: 0.92665037 | H49: 0.87744479 | L49: Firstname | M49: 0.93887531 | O49: 0.93887531 | R49: Lastname | S49: 0.88753056 | T49: 0.83129584 | U49: 0.7408313 | V49: 0.82243197
B50: Lastname | C50: 0.88753056 | D50: 0.83129584 | E50: 0.7408313 | F50: 0.94621027 | G50: 0.86552567 | H50: 0.85564041 | L50: Middlename | M50: 0.66992665 | O50: 0.66992665 | R50: Firstname | S50: 0.94132029 | T50: 0.97555012 | U50: 0.94621027 | V50: 0.95419175
B51: Firstname | C51: 0.94132029 | D51: 0.97555012 | E51: 0.94621027 | F51: 0.93887531 | L51: Role | M51: 0.76772616 | N51: 0.95599022 | O51: 0.86161242 | R51: Middlename | S51: 0.91687042 | T51: 0.87775061 | U51: 0.76528117 | V51: 0.85588261
B52: Middlename | C52: 0.91687042 | D52: 0.87775061 | E52: 0.76528117 | F52: 0.66992665 | L52: Nationality | N52: 0.99511002 | O52: 0.99511002 | R52: Role | S52: 0.96577017 | T52: 0.98288509 | U52: 0.96332518 | V52: 0.97065593
B53: Role | C53: 0.96577017 | D53: 0.98288509 | E53: 0.96332518 | F53: 0.76772616 | G53: 0.95599022 | H53: 0.92731015 | L53: Education | N53: 1 | O53: 1 | R53: Overall | S53: 0.86155257 | T53: 0.91503667 | U53: 0.8997555 | V53: 0.89135151
B54: Nationality | G54: 0.99511002 | H54: 0.99511002 | L54: Overall | M54: 0.80806846 | N54: 0.9400978 | O54: 0.87391077
B55: Education | G55: 1 | H55: 1
